Workbook

Sheet RESUMEN GENERAL
B1: TESORERÍA 5°B — RESUMEN GENERAL CONSOLIDADO
B2: Dinero efectivamente recibido, utilizado y disponible. El Monto Real en Tesorería no incluye aportes pendientes.
B4: CONCEPTO | C4: TESORERÍA | D4: PRESIDENTA | E4: TOTAL CURSO
B5: INGRESOS EFECTIVAMENTE RECIBIDOS | C5: =SUMIFS(MOVIMIENTOS!$I:$I,MOVIMIENTOS!$D:$D,"Aporte",MOVIMIENTOS!$G:$G,"Tesorería")+SUMIFS(MOVIMIENTOS!$I:$I,MOVIMIENTOS!$D:$D,"Ingreso",MOVIMIENTOS!$G:$G,"Tesorería") -> 404000 | D5: =SUMIFS(MOVIMIENTOS!$I:$I,MOVIMIENTOS!$D:$D,"Aporte",MOVIMIENTOS!$G:$G,"Presidenta")+SUMIFS(MOVIMIENTOS!$I:$I,MOVIMIENTOS!$D:$D,"Ingreso",MOVIMIENTOS!$G:$G,"Presidenta") -> 106000 | E5: =C5+D5 -> 510000
B6: EGRESOS EFECTIVAMENTE PAGADOS | C6: =SUMIFS(MOVIMIENTOS!$I:$I,MOVIMIENTOS!$D:$D,"Egreso",MOVIMIENTOS!$G:$G,"Tesorería") -> 200970 | D6: =SUMIFS(MOVIMIENTOS!$I:$I,MOVIMIENTOS!$D:$D,"Egreso",MOVIMIENTOS!$G:$G,"Presidenta") -> 74692 | E6: =C6+D6 -> 275662
B7: MONTO REAL EN TESORERÍA | C7: =C5-C6 -> 203030 | D7: =D5-D6 -> 31308 | E7: =C7+D7 -> 234338
B8: FONDOS TOTALES | C8: =C7 -> 203030 | D8: =D7 -> 31308 | E8: =C8+D8 -> 234338
B10: CONTROL DE REFERENCIA DEL ARCHIVO ENTREGADO
B11: Monto Real Tesorería | E11: 203030
B12: Saldo en poder de Presidenta | E12: 31308
B13: Fondos totales | E13: 234338
B15: ÚLTIMOS GASTOS
B16: FECHA | C16: DETALLE | D16: FONDO | E16: MONTO
B17: 46240 | C17: POTES HELADOS - PAPEL CELOFAN | D17: Tesorería | E17: 17330
B18: 46233 | C18: TORTA MANJAR CHOCOLATE 32 P | D18: Tesorería | E18: 25490
B19: 46225 | C19: CUCHARAS | D19: Tesorería | E19: 1100
B20: 46209 | C20: DIFERENCIA POTES (VASOS) | D20: Tesorería | E20: 4250
B21: 46192 | C21: TRANSFERENCIA A PRESIDENTA PALTAS | D21: Tesorería | E21: 5000
B22: 46192 | C22: PAN COMPLETO | D22: Tesorería | E22: 10930
B23: 46192 | C23: TOMATE BEBIDAS | D23: Tesorería | E23: 13040
B24: 46191 | C24: VIENESA ADEREZOS | D24: Tesorería | E24: 18550
B27: DATOS DEL TESORERO/A
B28: Nombre
B29: RUT
B30: Teléfono
B31: Correo

Sheet ORGANIZACION
A1: DATOS DE LA ORGANIZACIÓN
A2: Complete una vez. Estos datos se reutilizan en movimientos, comprobantes e informes.
A4: CAMPO | B4: VALOR
A5: Nombre de la organización | B5: CPA 5°B 2026
A6: Tipo de organización | B6: Curso
A7: Establecimiento / institución | B7: Escuela Palestina
A8: Año | B8: 2026
A9: RUT organización
A10: Dirección
A11: Correo
A12: Teléfono | B12: +569
A13: Representante
A14: RUT representante
A15: Tesorero/a
A16: RUT tesorero/a
A17: Teléfono tesorero/a | B17: +569
A18: Correo tesorero/a
A19: Banco de la organización
A20: Tipo de cuenta
A21: Número de cuenta
A22: Titular de la cuenta
A23: RUT titular
A24: Correo transferencias

Sheet GENERAL
A1: TESORERÍA 5°B — PLANILLA GENERAL CONSOLIDADA
A2: Horizontal y lista para imprimir/exportar. Cuotas obligatorias separadas de extraordinarias. Rojo = Presidenta; sin rojo = Tesorería.
A4: N° | B4: RUT | C4: NOMBRE | D4: APODERADO / TUTOR | E4: MARZO | F4: ABRIL | G4: MAYO | H4: JUNIO | I4: JULIO | J4: AGOSTO | K4: SEPTIEMBRE | L4: OCTUBRE | M4: NOVIEMBRE | N4: DICIEMBRE | O4: TOTAL CUOTAS OBLIGATORIAS | P4: CUMPL PROFESOR | Q4: DÍA ALUMNO / NIÑO | R4: CONVIVENCIA JUNIO | S4: COMPLETADA | T4: CUMPLEAÑOS | U4: RIFA | V4: OTRA EXTRAORDINARIA | W4: TOTAL EXTRAORDINARIO | X4: TOTAL ENTREGADO | Y4: OBSERVACIONES
A5: 1 | B5: 25310795-2 | C5: ARAYA PINO RENATA ANTONELA | D5: PATRICIA PINO | E5: =SUMIFS(MOVIMIENTOS!$I:$I,MOVIMIENTOS!$D:$D,"Aporte",MOVIMIENTOS!$E:$E,"Anual",MOVIMIENTOS!$J:$J,$C5,MOVIMIENTOS!$B:$B,">="&DATE(2026,3,1),MOVIMIENTOS!$B:$B,"<"&DATE(2026,4,1)) -> 3000 | F5: =SUMIFS(MOVIMIENTOS!$I:$I,MOVIMIENTOS!$D:$D,"Aporte",MOVIMIENTOS!$E:$E,"Anual",MOVIMIENTOS!$J:$J,$C5,MOVIMIENTOS!$B:$B,">="&DATE(2026,4,1),MOVIMIENTOS!$B:$B,"<"&DATE(2026,5,1)) -> 3000 | G5: =SUMIFS(MOVIMIENTOS!$I:$I,MOVIMIENTOS!$D:$D,"Aporte",MOVIMIENTOS!$E:$E,"Anual",MOVIMIENTOS!$J:$J,$C5,MOVIMIENTOS!$B:$B,">="&DATE(2026,5,1),MOVIMIENTOS!$B:$B,"<"&DATE(2026,6,1)) -> 3000 | H5: =SUMIFS(MOVIMIENTOS!$I:$I,MOVIMIENTOS!$D:$D,"Aporte",MOVIMIENTOS!$E:$E,"Anual",MOVIMIENTOS!$J:$J,$C5,MOVIMIENTOS!$B:$B,">="&DATE(2026,6,1),MOVIMIENTOS!$B:$B,"<"&DATE(2026,7,1)) -> 3000 | I5: =SUMIFS(MOVIMIENTOS!$I:$I,MOVIMIENTOS!$D:$D,"Aporte",MOVIMIENTOS!$E:$E,"Anual",MOVIMIENTOS!$J:$J,$C5,MOVIMIENTOS!$B:$B,">="&DATE(2026,7,1),MOVIMIENTOS!$B:$B,"<"&DATE(2026,8,1)) -> 3000 | J5: =SUMIFS(MOVIMIENTOS!$I:$I,MOVIMIENTOS!$D:$D,"Aporte",MOVIMIENTOS!$E:$E,"Anual",MOVIMIENTOS!$J:$J,$C5,MOVIMIENTOS!$B:$B,">="&DATE(2026,8,1),MOVIMIENTOS!$B:$B,"<"&DATE(2026,9,1)) -> 0 | K5: =SUMIFS(MOVIMIENTOS!$I:$I,MOVIMIENTOS!$D:$D,"Aporte",MOVIMIENTOS!$E:$E,"Anual",MOVIMIENTOS!$J:$J,$C5,MOVIMIENTOS!$B:$B,">="&DATE(2026,9,1),MOVIMIENTOS!$B:$B,"<"&DATE(2026,10,1)) -> 0 | L5: =SUMIFS(MOVIMIENTOS!$I:$I,MOVIMIENTOS!$D:$D,"Aporte",MOVIMIENTOS!$E:$E,"Anual",MOVIMIENTOS!$J:$J,$C5,MOVIMIENTOS!$B:$B,">="&DATE(2026,10,1),MOVIMIENTOS!$B:$B,"<"&DATE(2026,11,1)) -> 0 | M5: =SUMIFS(MOVIMIENTOS!$I:$I,MOVIMIENTOS!$D:$D,"Aporte",MOVIMIENTOS!$E:$E,"Anual",MOVIMIENTOS!$J:$J,$C5,MOVIMIENTOS!$B:$B,">="&DATE(2026,11,1),MOVIMIENTOS!$B:$B,"<"&DATE(2026,12,1)) -> 0 | N5: =SUMIFS(MOVIMIENTOS!$I:$I,MOVIMIENTOS!$D:$D,"Aporte",MOVIMIENTOS!$E:$E,"Anual",MOVIMIENTOS!$J:$J,$C5,MOVIMIENTOS!$B:$B,">="&DATE(2026,12,1),MOVIMIENTOS!$B:$B,"<"&DATE(2026,13,1)) -> 0 | O5: =SUM(E5:N5) -> 15000 | P5: =SUMIFS(MOVIMIENTOS!$I:$I,MOVIMIENTOS!$D:$D,"Aporte",MOVIMIENTOS!$E:$E,"Extraordinaria",MOVIMIENTOS!$F:$F,P$4,MOVIMIENTOS!$J:$J,$C5) -> 1000 | Q5: =SUMIFS(MOVIMIENTOS!$I:$I,MOVIMIENTOS!$D:$D,"Aporte",MOVIMIENTOS!$E:$E,"Extraordinaria",MOVIMIENTOS!$F:$F,Q$4,MOVIMIENTOS!$J:$J,$C5) -> 2000 | R5: =SUMIFS(MOVIMIENTOS!$I:$I,MOVIMIENTOS!$D:$D,"Aporte",MOVIMIENTOS!$E:$E,"Extraordinaria",MOVIMIENTOS!$F:$F,R$4,MOVIMIENTOS!$J:$J,$C5) -> 0 | S5: =SUMIFS(MOVIMIENTOS!$I:$I,MOVIMIENTOS!$D:$D,"Aporte",MOVIMIENTOS!$E:$E,"Extraordinaria",MOVIMIENTOS!$F:$F,S$4,MOVIMIENTOS!$J:$J,$C5) -> 0 | T5: =SUMIFS(MOVIMIENTOS!$I:$I,MOVIMIENTOS!$D:$D,"Aporte",MOVIMIENTOS!$E:$E,"Extraordinaria",MOVIMIENTOS!$F:$F,T$4,MOVIMIENTOS!$J:$J,$C5) -> 0 | U5: =SUMIFS(MOVIMIENTOS!$I:$I,MOVIMIENTOS!$D:$D,"Aporte",MOVIMIENTOS!$E:$E,"Extraordinaria",MOVIMIENTOS!$F:$F,U$4,MOVIMIENTOS!$J:$J,$C5) -> 0 | V5: =SUMIFS(MOVIMIENTOS!$I:$I,MOVIMIENTOS!$D:$D,"Aporte",MOVIMIENTOS!$E:$E,"Extraordinaria",MOVIMIENTOS!$F:$F,V$4,MOVIMIENTOS!$J:$J,$C5) -> 0 | W5: =SUM(P5:V5) -> 3000 | X5: =O5+W5 -> 18000
A6: 2 | B6: 25299343-6 | C6: ASTUDILLO PINO TABATA JESÚS | D6: ROXANA PINO | E6: =SUMIFS(MOVIMIENTOS!$I:$I,MOVIMIENTOS!$D:$D,"Aporte",MOVIMIENTOS!$E:$E,"Anual",MOVIMIENTOS!$J:$J,$C6,MOVIMIENTOS!$B:$B,">="&DATE(2026,3,1),MOVIMIENTOS!$B:$B,"<"&DATE(2026,4,1)) -> 3000 | F6: =SUMIFS(MOVIMIENTOS!$I:$I,MOVIMIENTOS!$D:$D,"Aporte",MOVIMIENTOS!$E:$E,"Anual",MOVIMIENTOS!$J:$J,$C6,MOVIMIENTOS!$B:$B,">="&DATE(2026,4,1),MOVIMIENTOS!$B:$B,"<"&DATE(2026,5,1)) -> 0 | G6: =SUMIFS(MOVIMIENTOS!$I:$I,MOVIMIENTOS!$D:$D,"Aporte",MOVIMIENTOS!$E:$E,"Anual",MOVIMIENTOS!$J:$J,$C6,MOVIMIENTOS!$B:$B,">="&DATE(2026,5,1),MOVIMIENTOS!$B:$B,"<"&DATE(2026,6,1)) -> 0 | H6: =SUMIFS(MOVIMIENTOS!$I:$I,MOVIMIENTOS!$D:$D,"Aporte",MOVIMIENTOS!$E:$E,"Anual",MOVIMIENTOS!$J:$J,$C6,MOVIMIENTOS!$B:$B,">="&DATE(2026,6,1),MOVIMIENTOS!$B:$B,"<"&DATE(2026,7,1)) -> 0 | I6: =SUMIFS(MOVIMIENTOS!$I:$I,MOVIMIENTOS!$D:$D,"Aporte",MOVIMIENTOS!$E:$E,"Anual",MOVIMIENTOS!$J:$J,$C6,MOVIMIENTOS!$B:$B,">="&DATE(2026,7,1),MOVIMIENTOS!$B:$B,"<"&DATE(2026,8,1)) -> 0 | J6: =SUMIFS(MOVIMIENTOS!$I:$I,MOVIMIENTOS!$D:$D,"Aporte",MOVIMIENTOS!$E:$E,"Anual",MOVIMIENTOS!$J:$J,$C6,MOVIMIENTOS!$B:$B,">="&DATE(2026,8,1),MOVIMIENTOS!$B:$B,"<"&DATE(2026,9,1)) -> 0 | K6: =SUMIFS(MOVIMIENTOS!$I:$I,MOVIMIENTOS!$D:$D,"Aporte",MOVIMIENTOS!$E:$E,"Anual",MOVIMIENTOS!$J:$J,$C6,MOVIMIENTOS!$B:$B,">="&DATE(2026,9,1),MOVIMIENTOS!$B:$B,"<"&DATE(2026,10,1)) -> 0 | L6: =SUMIFS(MOVIMIENTOS!$I:$I,MOVIMIENTOS!$D:$D,"Aporte",MOVIMIENTOS!$E:$E,"Anual",MOVIMIENTOS!$J:$J,$C6,MOVIMIENTOS!$B:$B,">="&DATE(2026,10,1),MOVIMIENTOS!$B:$B,"<"&DATE(2026,11,1)) -> 0 | M6: =SUMIFS(MOVIMIENTOS!$I:$I,MOVIMIENTOS!$D:$D,"Aporte",MOVIMIENTOS!$E:$E,"Anual",MOVIMIENTOS!$J:$J,$C6,MOVIMIENTOS!$B:$B,">="&DATE(2026,11,1),MOVIMIENTOS!$B:$B,"<"&DATE(2026,12,1)) -> 0 | N6: =SUMIFS(MOVIMIENTOS!$I:$I,MOVIMIENTOS!$D:$D,"Aporte",MOVIMIENTOS!$E:$E,"Anual",MOVIMIENTOS!$J:$J,$C6,MOVIMIENTOS!$B:$B,">="&DATE(2026,12,1),MOVIMIENTOS!$B:$B,"<"&DATE(2026,13,1)) -> 0 | O6: =SUM(E6:N6) -> 3000 | P6: =SUMIFS(MOVIMIENTOS!$I:$I,MOVIMIENTOS!$D:$D,"Aporte",MOVIMIENTOS!$E:$E,"Extraordinaria",MOVIMIENTOS!$F:$F,P$4,MOVIMIENTOS!$J:$J,$C6) -> 1000 | Q6: =SUMIFS(MOVIMIENTOS!$I:$I,MOVIMIENTOS!$D:$D,"Aporte",MOVIMIENTOS!$E:$E,"Extraordinaria",MOVIMIENTOS!$F:$F,Q$4,MOVIMIENTOS!$J:$J,$C6) -> 0 | R6: =SUMIFS(MOVIMIENTOS!$I:$I,MOVIMIENTOS!$D:$D,"Aporte",MOVIMIENTOS!$E:$E,"Extraordinaria",MOVIMIENTOS!$F:$F,R$4,MOVIMIENTOS!$J:$J,$C6) -> 2000 | S6: =SUMIFS(MOVIMIENTOS!$I:$I,MOVIMIENTOS!$D:$D,"Aporte",MOVIMIENTOS!$E:$E,"Extraordinaria",MOVIMIENTOS!$F:$F,S$4,MOVIMIENTOS!$J:$J,$C6) -> 0 | T6: =SUMIFS(MOVIMIENTOS!$I:$I,MOVIMIENTOS!$D:$D,"Aporte",MOVIMIENTOS!$E:$E,"Extraordinaria",MOVIMIENTOS!$F:$F,T$4,MOVIMIENTOS!$J:$J,$C6) -> 0 | U6: =SUMIFS(MOVIMIENTOS!$I:$I,MOVIMIENTOS!$D:$D,"Aporte",MOVIMIENTOS!$E:$E,"Extraordinaria",MOVIMIENTOS!$F:$F,U$4,MOVIMIENTOS!$J:$J,$C6) -> 0 | V6: =SUMIFS(MOVIMIENTOS!$I:$I,MOVIMIENTOS!$D:$D,"Aporte",MOVIMIENTOS!$E:$E,"Extraordinaria",MOVIMIENTOS!$F:$F,V$4,MOVIMIENTOS!$J:$J,$C6) -> 0 | W6: =SUM(P6:V6) -> 3000 | X6: =O6+W6 -> 6000
A7: 3 | B7: 25172569-1 | C7: AZAGRA ABRIGO AMARO ALONSO | D7: BEATRIZ ABRIGO | E7: =SUMIFS(MOVIMIENTOS!$I:$I,MOVIMIENTOS!$D:$D,"Aporte",MOVIMIENTOS!$E:$E,"Anual",MOVIMIENTOS!$J:$J,$C7,MOVIMIENTOS!$B:$B,">="&DATE(2026,3,1),MOVIMIENTOS!$B:$B,"<"&DATE(2026,4,1)) -> 0 | F7: =SUMIFS(MOVIMIENTOS!$I:$I,MOVIMIENTOS!$D:$D,"Aporte",MOVIMIENTOS!$E:$E,"Anual",MOVIMIENTOS!$J:$J,$C7,MOVIMIENTOS!$B:$B,">="&DATE(2026,4,1),MOVIMIENTOS!$B:$B,"<"&DATE(2026,5,1)) -> 0 | G7: =SUMIFS(MOVIMIENTOS!$I:$I,MOVIMIENTOS!$D:$D,"Aporte",MOVIMIENTOS!$E:$E,"Anual",MOVIMIENTOS!$J:$J,$C7,MOVIMIENTOS!$B:$B,">="&DATE(2026,5,1),MOVIMIENTOS!$B:$B,"<"&DATE(2026,6,1)) -> 0 | H7: =SUMIFS(MOVIMIENTOS!$I:$I,MOVIMIENTOS!$D:$D,"Aporte",MOVIMIENTOS!$E:$E,"Anual",MOVIMIENTOS!$J:$J,$C7,MOVIMIENTOS!$B:$B,">="&DATE(2026,6,1),MOVIMIENTOS!$B:$B,"<"&DATE(2026,7,1)) -> 0 | I7: =SUMIFS(MOVIMIENTOS!$I:$I,MOVIMIENTOS!$D:$D,"Aporte",MOVIMIENTOS!$E:$E,"Anual",MOVIMIENTOS!$J:$J,$C7,MOVIMIENTOS!$B:$B,">="&DATE(2026,7,1),MOVIMIENTOS!$B:$B,"<"&DATE(2026,8,1)) -> 0 | J7: =SUMIFS(MOVIMIENTOS!$I:$I,MOVIMIENTOS!$D:$D,"Aporte",MOVIMIENTOS!$E:$E,"Anual",MOVIMIENTOS!$J:$J,$C7,MOVIMIENTOS!$B:$B,">="&DATE(2026,8,1),MOVIMIENTOS!$B:$B,"<"&DATE(2026,9,1)) -> 0 | K7: =SUMIFS(MOVIMIENTOS!$I:$I,MOVIMIENTOS!$D:$D,"Aporte",MOVIMIENTOS!$E:$E,"Anual",MOVIMIENTOS!$J:$J,$C7,MOVIMIENTOS!$B:$B,">="&DATE(2026,9,1),MOVIMIENTOS!$B:$B,"<"&DATE(2026,10,1)) -> 0 | L7: =SUMIFS(MOVIMIENTOS!$I:$I,MOVIMIENTOS!$D:$D,"Aporte",MOVIMIENTOS!$E:$E,"Anual",MOVIMIENTOS!$J:$J,$C7,MOVIMIENTOS!$B:$B,">="&DATE(2026,10,1),MOVIMIENTOS!$B:$B,"<"&DATE(2026,11,1)) -> 0 | M7: =SUMIFS(MOVIMIENTOS!$I:$I,MOVIMIENTOS!$D:$D,"Aporte",MOVIMIENTOS!$E:$E,"Anual",MOVIMIENTOS!$J:$J,$C7,MOVIMIENTOS!$B:$B,">="&DATE(2026,11,1),MOVIMIENTOS!$B:$B,"<"&DATE(2026,12,1)) -> 0 | N7: =SUMIFS(MOVIMIENTOS!$I:$I,MOVIMIENTOS!$D:$D,"Aporte",MOVIMIENTOS!$E:$E,"Anual",MOVIMIENTOS!$J:$J,$C7,MOVIMIENTOS!$B:$B,">="&DATE(2026,12,1),MOVIMIENTOS!$B:$B,"<"&DATE(2026,13,1)) -> 0 | O7: =SUM(E7:N7) -> 0 | P7: =SUMIFS(MOVIMIENTOS!$I:$I,MOVIMIENTOS!$D:$D,"Aporte",MOVIMIENTOS!$E:$E,"Extraordinaria",MOVIMIENTOS!$F:$F,P$4,MOVIMIENTOS!$J:$J,$C7) -> 1000 | Q7: =SUMIFS(MOVIMIENTOS!$I:$I,MOVIMIENTOS!$D:$D,"Aporte",MOVIMIENTOS!$E:$E,"Extraordinaria",MOVIMIENTOS!$F:$F,Q$4,MOVIMIENTOS!$J:$J,$C7) -> 2000 | R7: =SUMIFS(MOVIMIENTOS!$I:$I,MOVIMIENTOS!$D:$D,"Aporte",MOVIMIENTOS!$E:$E,"Extraordinaria",MOVIMIENTOS!$F:$F,R$4,MOVIMIENTOS!$J:$J,$C7) -> 2000 | S7: =SUMIFS(MOVIMIENTOS!$I:$I,MOVIMIENTOS!$D:$D,"Aporte",MOVIMIENTOS!$E:$E,"Extraordinaria",MOVIMIENTOS!$F:$F,S$4,MOVIMIENTOS!$J:$J,$C7) -> 0 | T7: =SUMIFS(MOVIMIENTOS!$I:$I,MOVIMIENTOS!$D:$D,"Aporte",MOVIMIENTOS!$E:$E,"Extraordinaria",MOVIMIENTOS!$F:$F,T$4,MOVIMIENTOS!$J:$J,$C7) -> 0 | U7: =SUMIFS(MOVIMIENTOS!$I:$I,MOVIMIENTOS!$D:$D,"Aporte",MOVIMIENTOS!$E:$E,"Extraordinaria",MOVIMIENTOS!$F:$F,U$4,MOVIMIENTOS!$J:$J,$C7) -> 1000 | V7: =SUMIFS(MOVIMIENTOS!$I:$I,MOVIMIENTOS!$D:$D,"Aporte",MOVIMIENTOS!$E:$E,"Extraordinaria",MOVIMIENTOS!$F:$F,V$4,MOVIMIENTOS!$J:$J,$C7) -> 0 | W7: =SUM(P7:V7) -> 6000 | X7: =O7+W7 -> 6000
A8: 4 | B8: 25074761-6 | C8: BECERRA CARRASCO AGUSTIN SALVADOR THOMAS | D8: ALICIA ARAYA | E8: =SUMIFS(MOVIMIENTOS!$I:$I,MOVIMIENTOS!$D:$D,"Aporte",MOVIMIENTOS!$E:$E,"Anual",MOVIMIENTOS!$J:$J,$C8,MOVIMIENTOS!$B:$B,">="&DATE(2026,3,1),MOVIMIENTOS!$B:$B,"<"&DATE(2026,4,1)) -> 3000 | F8: =SUMIFS(MOVIMIENTOS!$I:$I,MOVIMIENTOS!$D:$D,"Aporte",MOVIMIENTOS!$E:$E,"Anual",MOVIMIENTOS!$J:$J,$C8,MOVIMIENTOS!$B:$B,">="&DATE(2026,4,1),MOVIMIENTOS!$B:$B,"<"&DATE(2026,5,1)) -> 3000 | G8: =SUMIFS(MOVIMIENTOS!$I:$I,MOVIMIENTOS!$D:$D,"Aporte",MOVIMIENTOS!$E:$E,"Anual",MOVIMIENTOS!$J:$J,$C8,MOVIMIENTOS!$B:$B,">="&DATE(2026,5,1),MOVIMIENTOS!$B:$B,"<"&DATE(2026,6,1)) -> 3000 | H8: =SUMIFS(MOVIMIENTOS!$I:$I,MOVIMIENTOS!$D:$D,"Aporte",MOVIMIENTOS!$E:$E,"Anual",MOVIMIENTOS!$J:$J,$C8,MOVIMIENTOS!$B:$B,">="&DATE(2026,6,1),MOVIMIENTOS!$B:$B,"<"&DATE(2026,7,1)) -> 0 | I8: =SUMIFS(MOVIMIENTOS!$I:$I,MOVIMIENTOS!$D:$D,"Aporte",MOVIMIENTOS!$E:$E,"Anual",MOVIMIENTOS!$J:$J,$C8,MOVIMIENTOS!$B:$B,">="&DATE(2026,7,1),MOVIMIENTOS!$B:$B,"<"&DATE(2026,8,1)) -> 0 | J8: =SUMIFS(MOVIMIENTOS!$I:$I,MOVIMIENTOS!$D:$D,"Aporte",MOVIMIENTOS!$E:$E,"Anual",MOVIMIENTOS!$J:$J,$C8,MOVIMIENTOS!$B:$B,">="&DATE(2026,8,1),MOVIMIENTOS!$B:$B,"<"&DATE(2026,9,1)) -> 0 | K8: =SUMIFS(MOVIMIENTOS!$I:$I,MOVIMIENTOS!$D:$D,"Aporte",MOVIMIENTOS!$E:$E,"Anual",MOVIMIENTOS!$J:$J,$C8,MOVIMIENTOS!$B:$B,">="&DATE(2026,9,1),MOVIMIENTOS!$B:$B,"<"&DATE(2026,10,1)) -> 0 | L8: =SUMIFS(MOVIMIENTOS!$I:$I,MOVIMIENTOS!$D:$D,"Aporte",MOVIMIENTOS!$E:$E,"Anual",MOVIMIENTOS!$J:$J,$C8,MOVIMIENTOS!$B:$B,">="&DATE(2026,10,1),MOVIMIENTOS!$B:$B,"<"&DATE(2026,11,1)) -> 0 | M8: =SUMIFS(MOVIMIENTOS!$I:$I,MOVIMIENTOS!$D:$D,"Aporte",MOVIMIENTOS!$E:$E,"Anual",MOVIMIENTOS!$J:$J,$C8,MOVIMIENTOS!$B:$B,">="&DATE(2026,11,1),MOVIMIENTOS!$B:$B,"<"&DATE(2026,12,1)) -> 0 | N8: =SUMIFS(MOVIMIENTOS!$I:$I,MOVIMIENTOS!$D:$D,"Aporte",MOVIMIENTOS!$E:$E,"Anual",MOVIMIENTOS!$J:$J,$C8,MOVIMIENTOS!$B:$B,">="&DATE(2026,12,1),MOVIMIENTOS!$B:$B,"<"&DATE(2026,13,1)) -> 0 | O8: =SUM(E8:N8) -> 9000 | P8: =SUMIFS(MOVIMIENTOS!$I:$I,MOVIMIENTOS!$D:$D,"Aporte",MOVIMIENTOS!$E:$E,"Extraordinaria",MOVIMIENTOS!$F:$F,P$4,MOVIMIENTOS!$J:$J,$C8) -> 1000 | Q8: =SUMIFS(MOVIMIENTOS!$I:$I,MOVIMIENTOS!$D:$D,"Aporte",MOVIMIENTOS!$E:$E,"Extraordinaria",MOVIMIENTOS!$F:$F,Q$4,MOVIMIENTOS!$J:$J,$C8) -> 2000 | R8: =SUMIFS(MOVIMIENTOS!$I:$I,MOVIMIENTOS!$D:$D,"Aporte",MOVIMIENTOS!$E:$E,"Extraordinaria",MOVIMIENTOS!$F:$F,R$4,MOVIMIENTOS!$J:$J,$C8) -> 2000 | S8: =SUMIFS(MOVIMIENTOS!$I:$I,MOVIMIENTOS!$D:$D,"Aporte",MOVIMIENTOS!$E:$E,"Extraordinaria",MOVIMIENTOS!$F:$F,S$4,MOVIMIENTOS!$J:$J,$C8) -> 0 | T8: =SUMIFS(MOVIMIENTOS!$I:$I,MOVIMIENTOS!$D:$D,"Aporte",MOVIMIENTOS!$E:$E,"Extraordinaria",MOVIMIENTOS!$F:$F,T$4,MOVIMIENTOS!$J:$J,$C8) -> 0 | U8: =SUMIFS(MOVIMIENTOS!$I:$I,MOVIMIENTOS!$D:$D,"Aporte",MOVIMIENTOS!$E:$E,"Extraordinaria",MOVIMIENTOS!$F:$F,U$4,MOVIMIENTOS!$J:$J,$C8) -> 0 | V8: =SUMIFS(MOVIMIENTOS!$I:$I,MOVIMIENTOS!$D:$D,"Aporte",MOVIMIENTOS!$E:$E,"Extraordinaria",MOVIMIENTOS!$F:$F,V$4,MOVIMIENTOS!$J:$J,$C8) -> 0 | W8: =SUM(P8:V8) -> 5000 | X8: =O8+W8 -> 14000
C9: BERTEL MONTES GLEYMIS | E9: =SUMIFS(MOVIMIENTOS!$I:$I,MOVIMIENTOS!$D:$D,"Aporte",MOVIMIENTOS!$E:$E,"Anual",MOVIMIENTOS!$J:$J,$C9,MOVIMIENTOS!$B:$B,">="&DATE(2026,3,1),MOVIMIENTOS!$B:$B,"<"&DATE(2026,4,1)) -> 3000 | F9: =SUMIFS(MOVIMIENTOS!$I:$I,MOVIMIENTOS!$D:$D,"Aporte",MOVIMIENTOS!$E:$E,"Anual",MOVIMIENTOS!$J:$J,$C9,MOVIMIENTOS!$B:$B,">="&DATE(2026,4,1),MOVIMIENTOS!$B:$B,"<"&DATE(2026,5,1)) -> 0 | G9: =SUMIFS(MOVIMIENTOS!$I:$I,MOVIMIENTOS!$D:$D,"Aporte",MOVIMIENTOS!$E:$E,"Anual",MOVIMIENTOS!$J:$J,$C9,MOVIMIENTOS!$B:$B,">="&DATE(2026,5,1),MOVIMIENTOS!$B:$B,"<"&DATE(2026,6,1)) -> 0 | H9: =SUMIFS(MOVIMIENTOS!$I:$I,MOVIMIENTOS!$D:$D,"Aporte",MOVIMIENTOS!$E:$E,"Anual",MOVIMIENTOS!$J:$J,$C9,MOVIMIENTOS!$B:$B,">="&DATE(2026,6,1),MOVIMIENTOS!$B:$B,"<"&DATE(2026,7,1)) -> 0 | I9: =SUMIFS(MOVIMIENTOS!$I:$I,MOVIMIENTOS!$D:$D,"Aporte",MOVIMIENTOS!$E:$E,"Anual",MOVIMIENTOS!$J:$J,$C9,MOVIMIENTOS!$B:$B,">="&DATE(2026,7,1),MOVIMIENTOS!$B:$B,"<"&DATE(2026,8,1)) -> 0 | J9: =SUMIFS(MOVIMIENTOS!$I:$I,MOVIMIENTOS!$D:$D,"Aporte",MOVIMIENTOS!$E:$E,"Anual",MOVIMIENTOS!$J:$J,$C9,MOVIMIENTOS!$B:$B,">="&DATE(2026,8,1),MOVIMIENTOS!$B:$B,"<"&DATE(2026,9,1)) -> 0 | K9: =SUMIFS(MOVIMIENTOS!$I:$I,MOVIMIENTOS!$D:$D,"Aporte",MOVIMIENTOS!$E:$E,"Anual",MOVIMIENTOS!$J:$J,$C9,MOVIMIENTOS!$B:$B,">="&DATE(2026,9,1),MOVIMIENTOS!$B:$B,"<"&DATE(2026,10,1)) -> 0 | L9: =SUMIFS(MOVIMIENTOS!$I:$I,MOVIMIENTOS!$D:$D,"Aporte",MOVIMIENTOS!$E:$E,"Anual",MOVIMIENTOS!$J:$J,$C9,MOVIMIENTOS!$B:$B,">="&DATE(2026,10,1),MOVIMIENTOS!$B:$B,"<"&DATE(2026,11,1)) -> 0 | M9: =SUMIFS(MOVIMIENTOS!$I:$I,MOVIMIENTOS!$D:$D,"Aporte",MOVIMIENTOS!$E:$E,"Anual",MOVIMIENTOS!$J:$J,$C9,MOVIMIENTOS!$B:$B,">="&DATE(2026,11,1),MOVIMIENTOS!$B:$B,"<"&DATE(2026,12,1)) -> 0 | N9: =SUMIFS(MOVIMIENTOS!$I:$I,MOVIMIENTOS!$D:$D,"Aporte",MOVIMIENTOS!$E:$E,"Anual",MOVIMIENTOS!$J:$J,$C9,MOVIMIENTOS!$B:$B,">="&DATE(2026,12,1),MOVIMIENTOS!$B:$B,"<"&DATE(2026,13,1)) -> 0 | O9: =SUM(E9:N9) -> 3000 | P9: =SUMIFS(MOVIMIENTOS!$I:$I,MOVIMIENTOS!$D:$D,"Aporte",MOVIMIENTOS!$E:$E,"Extraordinaria",MOVIMIENTOS!$F:$F,P$4,MOVIMIENTOS!$J:$J,$C9) -> 0 | Q9: =SUMIFS(MOVIMIENTOS!$I:$I,MOVIMIENTOS!$D:$D,"Aporte",MOVIMIENTOS!$E:$E,"Extraordinaria",MOVIMIENTOS!$F:$F,Q$4,MOVIMIENTOS!$J:$J,$C9) -> 0 | R9: =SUMIFS(MOVIMIENTOS!$I:$I,MOVIMIENTOS!$D:$D,"Aporte",MOVIMIENTOS!$E:$E,"Extraordinaria",MOVIMIENTOS!$F:$F,R$4,MOVIMIENTOS!$J:$J,$C9) -> 0 | S9: =SUMIFS(MOVIMIENTOS!$I:$I,MOVIMIENTOS!$D:$D,"Aporte",MOVIMIENTOS!$E:$E,"Extraordinaria",MOVIMIENTOS!$F:$F,S$4,MOVIMIENTOS!$J:$J,$C9) -> 0 | T9: =SUMIFS(MOVIMIENTOS!$I:$I,MOVIMIENTOS!$D:$D,"Aporte",MOVIMIENTOS!$E:$E,"Extraordinaria",MOVIMIENTOS!$F:$F,T$4,MOVIMIENTOS!$J:$J,$C9) -> 0 | U9: =SUMIFS(MOVIMIENTOS!$I:$I,MOVIMIENTOS!$D:$D,"Aporte",MOVIMIENTOS!$E:$E,"Extraordinaria",MOVIMIENTOS!$F:$F,U$4,MOVIMIENTOS!$J:$J,$C9) -> 0 | V9: =SUMIFS(MOVIMIENTOS!$I:$I,MOVIMIENTOS!$D:$D,"Aporte",MOVIMIENTOS!$E:$E,"Extraordinaria",MOVIMIENTOS!$F:$F,V$4,MOVIMIENTOS!$J:$J,$C9) -> 0 | W9: =SUM(P9:V9) -> 0 | X9: =O9+W9 -> 3000
A10: 6 | B10: 25186502-7 | C10: CASTILLO DÍAZ NAHUEL ANDRÉS | E10: =SUMIFS(MOVIMIENTOS!$I:$I,MOVIMIENTOS!$D:$D,"Aporte",MOVIMIENTOS!$E:$E,"Anual",MOVIMIENTOS!$J:$J,$C10,MOVIMIENTOS!$B:$B,">="&DATE(2026,3,1),MOVIMIENTOS!$B:$B,"<"&DATE(2026,4,1)) -> 0 | F10: =SUMIFS(MOVIMIENTOS!$I:$I,MOVIMIENTOS!$D:$D,"Aporte",MOVIMIENTOS!$E:$E,"Anual",MOVIMIENTOS!$J:$J,$C10,MOVIMIENTOS!$B:$B,">="&DATE(2026,4,1),MOVIMIENTOS!$B:$B,"<"&DATE(2026,5,1)) -> 0 | G10: =SUMIFS(MOVIMIENTOS!$I:$I,MOVIMIENTOS!$D:$D,"Aporte",MOVIMIENTOS!$E:$E,"Anual",MOVIMIENTOS!$J:$J,$C10,MOVIMIENTOS!$B:$B,">="&DATE(2026,5,1),MOVIMIENTOS!$B:$B,"<"&DATE(2026,6,1)) -> 0 | H10: =SUMIFS(MOVIMIENTOS!$I:$I,MOVIMIENTOS!$D:$D,"Aporte",MOVIMIENTOS!$E:$E,"Anual",MOVIMIENTOS!$J:$J,$C10,MOVIMIENTOS!$B:$B,">="&DATE(2026,6,1),MOVIMIENTOS!$B:$B,"<"&DATE(2026,7,1)) -> 0 | I10: =SUMIFS(MOVIMIENTOS!$I:$I,MOVIMIENTOS!$D:$D,"Aporte",MOVIMIENTOS!$E:$E,"Anual",MOVIMIENTOS!$J:$J,$C10,MOVIMIENTOS!$B:$B,">="&DATE(2026,7,1),MOVIMIENTOS!$B:$B,"<"&DATE(2026,8,1)) -> 0 | J10: =SUMIFS(MOVIMIENTOS!$I:$I,MOVIMIENTOS!$D:$D,"Aporte",MOVIMIENTOS!$E:$E,"Anual",MOVIMIENTOS!$J:$J,$C10,MOVIMIENTOS!$B:$B,">="&DATE(2026,8,1),MOVIMIENTOS!$B:$B,"<"&DATE(2026,9,1)) -> 0 | K10: =SUMIFS(MOVIMIENTOS!$I:$I,MOVIMIENTOS!$D:$D,"Aporte",MOVIMIENTOS!$E:$E,"Anual",MOVIMIENTOS!$J:$J,$C10,MOVIMIENTOS!$B:$B,">="&DATE(2026,9,1),MOVIMIENTOS!$B:$B,"<"&DATE(2026,10,1)) -> 0 | L10: =SUMIFS(MOVIMIENTOS!$I:$I,MOVIMIENTOS!$D:$D,"Aporte",MOVIMIENTOS!$E:$E,"Anual",MOVIMIENTOS!$J:$J,$C10,MOVIMIENTOS!$B:$B,">="&DATE(2026,10,1),MOVIMIENTOS!$B:$B,"<"&DATE(2026,11,1)) -> 0 | M10: =SUMIFS(MOVIMIENTOS!$I:$I,MOVIMIENTOS!$D:$D,"Aporte",MOVIMIENTOS!$E:$E,"Anual",MOVIMIENTOS!$J:$J,$C10,MOVIMIENTOS!$B:$B,">="&DATE(2026,11,1),MOVIMIENTOS!$B:$B,"<"&DATE(2026,12,1)) -> 0 | N10: =SUMIFS(MOVIMIENTOS!$I:$I,MOVIMIENTOS!$D:$D,"Aporte",MOVIMIENTOS!$E:$E,"Anual",MOVIMIENTOS!$J:$J,$C10,MOVIMIENTOS!$B:$B,">="&DATE(2026,12,1),MOVIMIENTOS!$B:$B,"<"&DATE(2026,13,1)) -> 0 | O10: =SUM(E10:N10) -> 0 | P10: =SUMIFS(MOVIMIENTOS!$I:$I,MOVIMIENTOS!$D:$D,"Aporte",MOVIMIENTOS!$E:$E,"Extraordinaria",MOVIMIENTOS!$F:$F,P$4,MOVIMIENTOS!$J:$J,$C10) -> 0 | Q10: =SUMIFS(MOVIMIENTOS!$I:$I,MOVIMIENTOS!$D:$D,"Aporte",MOVIMIENTOS!$E:$E,"Extraordinaria",MOVIMIENTOS!$F:$F,Q$4,MOVIMIENTOS!$J:$J,$C10) -> 0 | R10: =SUMIFS(MOVIMIENTOS!$I:$I,MOVIMIENTOS!$D:$D,"Aporte",MOVIMIENTOS!$E:$E,"Extraordinaria",MOVIMIENTOS!$F:$F,R$4,MOVIMIENTOS!$J:$J,$C10) -> 0 | S10: =SUMIFS(MOVIMIENTOS!$I:$I,MOVIMIENTOS!$D:$D,"Aporte",MOVIMIENTOS!$E:$E,"Extraordinaria",MOVIMIENTOS!$F:$F,S$4,MOVIMIENTOS!$J:$J,$C10) -> 0 | T10: =SUMIFS(MOVIMIENTOS!$I:$I,MOVIMIENTOS!$D:$D,"Aporte",MOVIMIENTOS!$E:$E,"Extraordinaria",MOVIMIENTOS!$F:$F,T$4,MOVIMIENTOS!$J:$J,$C10) -> 0 | U10: =SUMIFS(MOVIMIENTOS!$I:$I,MOVIMIENTOS!$D:$D,"Aporte",MOVIMIENTOS!$E:$E,"Extraordinaria",MOVIMIENTOS!$F:$F,U$4,MOVIMIENTOS!$J:$J,$C10) -> 0 | V10: =SUMIFS(MOVIMIENTOS!$I:$I,MOVIMIENTOS!$D:$D,"Aporte",MOVIMIENTOS!$E:$E,"Extraordinaria",MOVIMIENTOS!$F:$F,V$4,MOVIMIENTOS!$J:$J,$C10) -> 0 | W10: =SUM(P10:V10) -> 0 | X10: =O10+W10 -> 0
A11: 7 | B11: 24387554-4 | C11: CASTILLO GRACIA JOSEFA ANTONIA | E11: =SUMIFS(MOVIMIENTOS!$I:$I,MOVIMIENTOS!$D:$D,"Aporte",MOVIMIENTOS!$E:$E,"Anual",MOVIMIENTOS!$J:$J,$C11,MOVIMIENTOS!$B:$B,">="&DATE(2026,3,1),MOVIMIENTOS!$B:$B,"<"&DATE(2026,4,1)) -> 3000 | F11: =SUMIFS(MOVIMIENTOS!$I:$I,MOVIMIENTOS!$D:$D,"Aporte",MOVIMIENTOS!$E:$E,"Anual",MOVIMIENTOS!$J:$J,$C11,MOVIMIENTOS!$B:$B,">="&DATE(2026,4,1),MOVIMIENTOS!$B:$B,"<"&DATE(2026,5,1)) -> 3000 | G11: =SUMIFS(MOVIMIENTOS!$I:$I,MOVIMIENTOS!$D:$D,"Aporte",MOVIMIENTOS!$E:$E,"Anual",MOVIMIENTOS!$J:$J,$C11,MOVIMIENTOS!$B:$B,">="&DATE(2026,5,1),MOVIMIENTOS!$B:$B,"<"&DATE(2026,6,1)) -> 3000 | H11: =SUMIFS(MOVIMIENTOS!$I:$I,MOVIMIENTOS!$D:$D,"Aporte",MOVIMIENTOS!$E:$E,"Anual",MOVIMIENTOS!$J:$J,$C11,MOVIMIENTOS!$B:$B,">="&DATE(2026,6,1),MOVIMIENTOS!$B:$B,"<"&DATE(2026,7,1)) -> 0 | I11: =SUMIFS(MOVIMIENTOS!$I:$I,MOVIMIENTOS!$D:$D,"Aporte",MOVIMIENTOS!$E:$E,"Anual",MOVIMIENTOS!$J:$J,$C11,MOVIMIENTOS!$B:$B,">="&DATE(2026,7,1),MOVIMIENTOS!$B:$B,"<"&DATE(2026,8,1)) -> 0 | J11: =SUMIFS(MOVIMIENTOS!$I:$I,MOVIMIENTOS!$D:$D,"Aporte",MOVIMIENTOS!$E:$E,"Anual",MOVIMIENTOS!$J:$J,$C11,MOVIMIENTOS!$B:$B,">="&DATE(2026,8,1),MOVIMIENTOS!$B:$B,"<"&DATE(2026,9,1)) -> 0 | K11: =SUMIFS(MOVIMIENTOS!$I:$I,MOVIMIENTOS!$D:$D,"Aporte",MOVIMIENTOS!$E:$E,"Anual",MOVIMIENTOS!$J:$J,$C11,MOVIMIENTOS!$B:$B,">="&DATE(2026,9,1),MOVIMIENTOS!$B:$B,"<"&DATE(2026,10,1)) -> 0 | L11: =SUMIFS(MOVIMIENTOS!$I:$I,MOVIMIENTOS!$D:$D,"Aporte",MOVIMIENTOS!$E:$E,"Anual",MOVIMIENTOS!$J:$J,$C11,MOVIMIENTOS!$B:$B,">="&DATE(2026,10,1),MOVIMIENTOS!$B:$B,"<"&DATE(2026,11,1)) -> 0 | M11: =SUMIFS(MOVIMIENTOS!$I:$I,MOVIMIENTOS!$D:$D,"Aporte",MOVIMIENTOS!$E:$E,"Anual",MOVIMIENTOS!$J:$J,$C11,MOVIMIENTOS!$B:$B,">="&DATE(2026,11,1),MOVIMIENTOS!$B:$B,"<"&DATE(2026,12,1)) -> 0 | N11: =SUMIFS(MOVIMIENTOS!$I:$I,MOVIMIENTOS!$D:$D,"Aporte",MOVIMIENTOS!$E:$E,"Anual",MOVIMIENTOS!$J:$J,$C11,MOVIMIENTOS!$B:$B,">="&DATE(2026,12,1),MOVIMIENTOS!$B:$B,"<"&DATE(2026,13,1)) -> 0 | O11: =SUM(E11:N11) -> 9000 | P11: =SUMIFS(MOVIMIENTOS!$I:$I,MOVIMIENTOS!$D:$D,"Aporte",MOVIMIENTOS!$E:$E,"Extraordinaria",MOVIMIENTOS!$F:$F,P$4,MOVIMIENTOS!$J:$J,$C11) -> 1000 | Q11: =SUMIFS(MOVIMIENTOS!$I:$I,MOVIMIENTOS!$D:$D,"Aporte",MOVIMIENTOS!$E:$E,"Extraordinaria",MOVIMIENTOS!$F:$F,Q$4,MOVIMIENTOS!$J:$J,$C11) -> 0 | R11: =SUMIFS(MOVIMIENTOS!$I:$I,MOVIMIENTOS!$D:$D,"Aporte",MOVIMIENTOS!$E:$E,"Extraordinaria",MOVIMIENTOS!$F:$F,R$4,MOVIMIENTOS!$J:$J,$C11) -> 2000 | S11: =SUMIFS(MOVIMIENTOS!$I:$I,MOVIMIENTOS!$D:$D,"Aporte",MOVIMIENTOS!$E:$E,"Extraordinaria",MOVIMIENTOS!$F:$F,S$4,MOVIMIENTOS!$J:$J,$C11) -> 0 | T11: =SUMIFS(MOVIMIENTOS!$I:$I,MOVIMIENTOS!$D:$D,"Aporte",MOVIMIENTOS!$E:$E,"Extraordinaria",MOVIMIENTOS!$F:$F,T$4,MOVIMIENTOS!$J:$J,$C11) -> 0 | U11: =SUMIFS(MOVIMIENTOS!$I:$I,MOVIMIENTOS!$D:$D,"Aporte",MOVIMIENTOS!$E:$E,"Extraordinaria",MOVIMIENTOS!$F:$F,U$4,MOVIMIENTOS!$J:$J,$C11) -> 0 | V11: =SUMIFS(MOVIMIENTOS!$I:$I,MOVIMIENTOS!$D:$D,"Aporte",MOVIMIENTOS!$E:$E,"Extraordinaria",MOVIMIENTOS!$F:$F,V$4,MOVIMIENTOS!$J:$J,$C11) -> 0 | W11: =SUM(P11:V11) -> 3000 | X11: =O11+W11 -> 12000
A12: 8 | B12: 25117099-1 | C12: CASTRO VALDERRAMA EIMY PASCALLE | D12: ANA VALDERRAMA | E12: =SUMIFS(MOVIMIENTOS!$I:$I,MOVIMIENTOS!$D:$D,"Aporte",MOVIMIENTOS!$E:$E,"Anual",MOVIMIENTOS!$J:$J,$C12,MOVIMIENTOS!$B:$B,">="&DATE(2026,3,1),MOVIMIENTOS!$B:$B,"<"&DATE(2026,4,1)) -> 3000 | F12: =SUMIFS(MOVIMIENTOS!$I:$I,MOVIMIENTOS!$D:$D,"Aporte",MOVIMIENTOS!$E:$E,"Anual",MOVIMIENTOS!$J:$J,$C12,MOVIMIENTOS!$B:$B,">="&DATE(2026,4,1),MOVIMIENTOS!$B:$B,"<"&DATE(2026,5,1)) -> 3000 | G12: =SUMIFS(MOVIMIENTOS!$I:$I,MOVIMIENTOS!$D:$D,"Aporte",MOVIMIENTOS!$E:$E,"Anual",MOVIMIENTOS!$J:$J,$C12,MOVIMIENTOS!$B:$B,">="&DATE(2026,5,1),MOVIMIENTOS!$B:$B,"<"&DATE(2026,6,1)) -> 3000 | H12: =SUMIFS(MOVIMIENTOS!$I:$I,MOVIMIENTOS!$D:$D,"Aporte",MOVIMIENTOS!$E:$E,"Anual",MOVIMIENTOS!$J:$J,$C12,MOVIMIENTOS!$B:$B,">="&DATE(2026,6,1),MOVIMIENTOS!$B:$B,"<"&DATE(2026,7,1)) -> 3000 | I12: =SUMIFS(MOVIMIENTOS!$I:$I,MOVIMIENTOS!$D:$D,"Aporte",MOVIMIENTOS!$E:$E,"Anual",MOVIMIENTOS!$J:$J,$C12,MOVIMIENTOS!$B:$B,">="&DATE(2026,7,1),MOVIMIENTOS!$B:$B,"<"&DATE(2026,8,1)) -> 3000 | J12: =SUMIFS(MOVIMIENTOS!$I:$I,MOVIMIENTOS!$D:$D,"Aporte",MOVIMIENTOS!$E:$E,"Anual",MOVIMIENTOS!$J:$J,$C12,MOVIMIENTOS!$B:$B,">="&DATE(2026,8,1),MOVIMIENTOS!$B:$B,"<"&DATE(2026,9,1)) -> 0 | K12: =SUMIFS(MOVIMIENTOS!$I:$I,MOVIMIENTOS!$D:$D,"Aporte",MOVIMIENTOS!$E:$E,"Anual",MOVIMIENTOS!$J:$J,$C12,MOVIMIENTOS!$B:$B,">="&DATE(2026,9,1),MOVIMIENTOS!$B:$B,"<"&DATE(2026,10,1)) -> 0 | L12: =SUMIFS(MOVIMIENTOS!$I:$I,MOVIMIENTOS!$D:$D,"Aporte",MOVIMIENTOS!$E:$E,"Anual",MOVIMIENTOS!$J:$J,$C12,MOVIMIENTOS!$B:$B,">="&DATE(2026,10,1),MOVIMIENTOS!$B:$B,"<"&DATE(2026,11,1)) -> 0 | M12: =SUMIFS(MOVIMIENTOS!$I:$I,MOVIMIENTOS!$D:$D,"Aporte",MOVIMIENTOS!$E:$E,"Anual",MOVIMIENTOS!$J:$J,$C12,MOVIMIENTOS!$B:$B,">="&DATE(2026,11,1),MOVIMIENTOS!$B:$B,"<"&DATE(2026,12,1)) -> 0 | N12: =SUMIFS(MOVIMIENTOS!$I:$I,MOVIMIENTOS!$D:$D,"Aporte",MOVIMIENTOS!$E:$E,"Anual",MOVIMIENTOS!$J:$J,$C12,MOVIMIENTOS!$B:$B,">="&DATE(2026,12,1),MOVIMIENTOS!$B:$B,"<"&DATE(2026,13,1)) -> 0 | O12: =SUM(E12:N12) -> 15000 | P12: =SUMIFS(MOVIMIENTOS!$I:$I,MOVIMIENTOS!$D:$D,"Aporte",MOVIMIENTOS!$E:$E,"Extraordinaria",MOVIMIENTOS!$F:$F,P$4,MOVIMIENTOS!$J:$J,$C12) -> 1000 | Q12: =SUMIFS(MOVIMIENTOS!$I:$I,MOVIMIENTOS!$D:$D,"Aporte",MOVIMIENTOS!$E:$E,"Extraordinaria",MOVIMIENTOS!$F:$F,Q$4,MOVIMIENTOS!$J:$J,$C12) -> 2000 | R12: =SUMIFS(MOVIMIENTOS!$I:$I,MOVIMIENTOS!$D:$D,"Aporte",MOVIMIENTOS!$E:$E,"Extraordinaria",MOVIMIENTOS!$F:$F,R$4,MOVIMIENTOS!$J:$J,$C12) -> 2000 | S12: =SUMIFS(MOVIMIENTOS!$I:$I,MOVIMIENTOS!$D:$D,"Aporte",MOVIMIENTOS!$E:$E,"Extraordinaria",MOVIMIENTOS!$F:$F,S$4,MOVIMIENTOS!$J:$J,$C12) -> 0 | T12: =SUMIFS(MOVIMIENTOS!$I:$I,MOVIMIENTOS!$D:$D,"Aporte",MOVIMIENTOS!$E:$E,"Extraordinaria",MOVIMIENTOS!$F:$F,T$4,MOVIMIENTOS!$J:$J,$C12) -> 0 | U12: =SUMIFS(MOVIMIENTOS!$I:$I,MOVIMIENTOS!$D:$D,"Aporte",MOVIMIENTOS!$E:$E,"Extraordinaria",MOVIMIENTOS!$F:$F,U$4,MOVIMIENTOS!$J:$J,$C12) -> 0 | V12: =SUMIFS(MOVIMIENTOS!$I:$I,MOVIMIENTOS!$D:$D,"Aporte",MOVIMIENTOS!$E:$E,"Extraordinaria",MOVIMIENTOS!$F:$F,V$4,MOVIMIENTOS!$J:$J,$C12) -> 0 | W12: =SUM(P12:V12) -> 5000 | X12: =O12+W12 -> 20000
A13: 9 | B13: 25091106-8 | C13: DONOSO MONSALVE ANGEL ISAAC | E13: =SUMIFS(MOVIMIENTOS!$I:$I,MOVIMIENTOS!$D:$D,"Aporte",MOVIMIENTOS!$E:$E,"Anual",MOVIMIENTOS!$J:$J,$C13,MOVIMIENTOS!$B:$B,">="&DATE(2026,3,1),MOVIMIENTOS!$B:$B,"<"&DATE(2026,4,1)) -> 3000 | F13: =SUMIFS(MOVIMIENTOS!$I:$I,MOVIMIENTOS!$D:$D,"Aporte",MOVIMIENTOS!$E:$E,"Anual",MOVIMIENTOS!$J:$J,$C13,MOVIMIENTOS!$B:$B,">="&DATE(2026,4,1),MOVIMIENTOS!$B:$B,"<"&DATE(2026,5,1)) -> 3000 | G13: =SUMIFS(MOVIMIENTOS!$I:$I,MOVIMIENTOS!$D:$D,"Aporte",MOVIMIENTOS!$E:$E,"Anual",MOVIMIENTOS!$J:$J,$C13,MOVIMIENTOS!$B:$B,">="&DATE(2026,5,1),MOVIMIENTOS!$B:$B,"<"&DATE(2026,6,1)) -> 3000 | H13: =SUMIFS(MOVIMIENTOS!$I:$I,MOVIMIENTOS!$D:$D,"Aporte",MOVIMIENTOS!$E:$E,"Anual",MOVIMIENTOS!$J:$J,$C13,MOVIMIENTOS!$B:$B,">="&DATE(2026,6,1),MOVIMIENTOS!$B:$B,"<"&DATE(2026,7,1)) -> 3000 | I13: =SUMIFS(MOVIMIENTOS!$I:$I,MOVIMIENTOS!$D:$D,"Aporte",MOVIMIENTOS!$E:$E,"Anual",MOVIMIENTOS!$J:$J,$C13,MOVIMIENTOS!$B:$B,">="&DATE(2026,7,1),MOVIMIENTOS!$B:$B,"<"&DATE(2026,8,1)) -> 0 | J13: =SUMIFS(MOVIMIENTOS!$I:$I,MOVIMIENTOS!$D:$D,"Aporte",MOVIMIENTOS!$E:$E,"Anual",MOVIMIENTOS!$J:$J,$C13,MOVIMIENTOS!$B:$B,">="&DATE(2026,8,1),MOVIMIENTOS!$B:$B,"<"&DATE(2026,9,1)) -> 0 | K13: =SUMIFS(MOVIMIENTOS!$I:$I,MOVIMIENTOS!$D:$D,"Aporte",MOVIMIENTOS!$E:$E,"Anual",MOVIMIENTOS!$J:$J,$C13,MOVIMIENTOS!$B:$B,">="&DATE(2026,9,1),MOVIMIENTOS!$B:$B,"<"&DATE(2026,10,1)) -> 0 | L13: =SUMIFS(MOVIMIENTOS!$I:$I,MOVIMIENTOS!$D:$D,"Aporte",MOVIMIENTOS!$E:$E,"Anual",MOVIMIENTOS!$J:$J,$C13,MOVIMIENTOS!$B:$B,">="&DATE(2026,10,1),MOVIMIENTOS!$B:$B,"<"&DATE(2026,11,1)) -> 0 | M13: =SUMIFS(MOVIMIENTOS!$I:$I,MOVIMIENTOS!$D:$D,"Aporte",MOVIMIENTOS!$E:$E,"Anual",MOVIMIENTOS!$J:$J,$C13,MOVIMIENTOS!$B:$B,">="&DATE(2026,11,1),MOVIMIENTOS!$B:$B,"<"&DATE(2026,12,1)) -> 0 | N13: =SUMIFS(MOVIMIENTOS!$I:$I,MOVIMIENTOS!$D:$D,"Aporte",MOVIMIENTOS!$E:$E,"Anual",MOVIMIENTOS!$J:$J,$C13,MOVIMIENTOS!$B:$B,">="&DATE(2026,12,1),MOVIMIENTOS!$B:$B,"<"&DATE(2026,13,1)) -> 0 | O13: =SUM(E13:N13) -> 12000 | P13: =SUMIFS(MOVIMIENTOS!$I:$I,MOVIMIENTOS!$D:$D,"Aporte",MOVIMIENTOS!$E:$E,"Extraordinaria",MOVIMIENTOS!$F:$F,P$4,MOVIMIENTOS!$J:$J,$C13) -> 1000 | Q13: =SUMIFS(MOVIMIENTOS!$I:$I,MOVIMIENTOS!$D:$D,"Aporte",MOVIMIENTOS!$E:$E,"Extraordinaria",MOVIMIENTOS!$F:$F,Q$4,MOVIMIENTOS!$J:$J,$C13) -> 2000 | R13: =SUMIFS(MOVIMIENTOS!$I:$I,MOVIMIENTOS!$D:$D,"Aporte",MOVIMIENTOS!$E:$E,"Extraordinaria",MOVIMIENTOS!$F:$F,R$4,MOVIMIENTOS!$J:$J,$C13) -> 2000 | S13: =SUMIFS(MOVIMIENTOS!$I:$I,MOVIMIENTOS!$D:$D,"Aporte",MOVIMIENTOS!$E:$E,"Extraordinaria",MOVIMIENTOS!$F:$F,S$4,MOVIMIENTOS!$J:$J,$C13) -> 0 | T13: =SUMIFS(MOVIMIENTOS!$I:$I,MOVIMIENTOS!$D:$D,"Aporte",MOVIMIENTOS!$E:$E,"Extraordinaria",MOVIMIENTOS!$F:$F,T$4,MOVIMIENTOS!$J:$J,$C13) -> 0 | U13: =SUMIFS(MOVIMIENTOS!$I:$I,MOVIMIENTOS!$D:$D,"Aporte",MOVIMIENTOS!$E:$E,"Extraordinaria",MOVIMIENTOS!$F:$F,U$4,MOVIMIENTOS!$J:$J,$C13) -> 0 | V13: =SUMIFS(MOVIMIENTOS!$I:$I,MOVIMIENTOS!$D:$D,"Aporte",MOVIMIENTOS!$E:$E,"Extraordinaria",MOVIMIENTOS!$F:$F,V$4,MOVIMIENTOS!$J:$J,$C13) -> 0 | W13: =SUM(P13:V13) -> 5000 | X13: =O13+W13 -> 17000
A14: 10 | B14: 25091116-5 | C14: DONOSO MONSALVE THOMAS IGNACIO | E14: =SUMIFS(MOVIMIENTOS!$I:$I,MOVIMIENTOS!$D:$D,"Aporte",MOVIMIENTOS!$E:$E,"Anual",MOVIMIENTOS!$J:$J,$C14,MOVIMIENTOS!$B:$B,">="&DATE(2026,3,1),MOVIMIENTOS!$B:$B,"<"&DATE(2026,4,1)) -> 3000 | F14: =SUMIFS(MOVIMIENTOS!$I:$I,MOVIMIENTOS!$D:$D,"Aporte",MOVIMIENTOS!$E:$E,"Anual",MOVIMIENTOS!$J:$J,$C14,MOVIMIENTOS!$B:$B,">="&DATE(2026,4,1),MOVIMIENTOS!$B:$B,"<"&DATE(2026,5,1)) -> 3000 | G14: =SUMIFS(MOVIMIENTOS!$I:$I,MOVIMIENTOS!$D:$D,"Aporte",MOVIMIENTOS!$E:$E,"Anual",MOVIMIENTOS!$J:$J,$C14,MOVIMIENTOS!$B:$B,">="&DATE(2026,5,1),MOVIMIENTOS!$B:$B,"<"&DATE(2026,6,1)) -> 3000 | H14: =SUMIFS(MOVIMIENTOS!$I:$I,MOVIMIENTOS!$D:$D,"Aporte",MOVIMIENTOS!$E:$E,"Anual",MOVIMIENTOS!$J:$J,$C14,MOVIMIENTOS!$B:$B,">="&DATE(2026,6,1),MOVIMIENTOS!$B:$B,"<"&DATE(2026,7,1)) -> 3000 | I14: =SUMIFS(MOVIMIENTOS!$I:$I,MOVIMIENTOS!$D:$D,"Aporte",MOVIMIENTOS!$E:$E,"Anual",MOVIMIENTOS!$J:$J,$C14,MOVIMIENTOS!$B:$B,">="&DATE(2026,7,1),MOVIMIENTOS!$B:$B,"<"&DATE(2026,8,1)) -> 0 | J14: =SUMIFS(MOVIMIENTOS!$I:$I,MOVIMIENTOS!$D:$D,"Aporte",MOVIMIENTOS!$E:$E,"Anual",MOVIMIENTOS!$J:$J,$C14,MOVIMIENTOS!$B:$B,">="&DATE(2026,8,1),MOVIMIENTOS!$B:$B,"<"&DATE(2026,9,1)) -> 0 | K14: =SUMIFS(MOVIMIENTOS!$I:$I,MOVIMIENTOS!$D:$D,"Aporte",MOVIMIENTOS!$E:$E,"Anual",MOVIMIENTOS!$J:$J,$C14,MOVIMIENTOS!$B:$B,">="&DATE(2026,9,1),MOVIMIENTOS!$B:$B,"<"&DATE(2026,10,1)) -> 0 | L14: =SUMIFS(MOVIMIENTOS!$I:$I,MOVIMIENTOS!$D:$D,"Aporte",MOVIMIENTOS!$E:$E,"Anual",MOVIMIENTOS!$J:$J,$C14,MOVIMIENTOS!$B:$B,">="&DATE(2026,10,1),MOVIMIENTOS!$B:$B,"<"&DATE(2026,11,1)) -> 0 | M14: =SUMIFS(MOVIMIENTOS!$I:$I,MOVIMIENTOS!$D:$D,"Aporte",MOVIMIENTOS!$E:$E,"Anual",MOVIMIENTOS!$J:$J,$C14,MOVIMIENTOS!$B:$B,">="&DATE(2026,11,1),MOVIMIENTOS!$B:$B,"<"&DATE(2026,12,1)) -> 0 | N14: =SUMIFS(MOVIMIENTOS!$I:$I,MOVIMIENTOS!$D:$D,"Aporte",MOVIMIENTOS!$E:$E,"Anual",MOVIMIENTOS!$J:$J,$C14,MOVIMIENTOS!$B:$B,">="&DATE(2026,12,1),MOVIMIENTOS!$B:$B,"<"&DATE(2026,13,1)) -> 0 | O14: =SUM(E14:N14) -> 12000 | P14: =SUMIFS(MOVIMIENTOS!$I:$I,MOVIMIENTOS!$D:$D,"Aporte",MOVIMIENTOS!$E:$E,"Extraordinaria",MOVIMIENTOS!$F:$F,P$4,MOVIMIENTOS!$J:$J,$C14) -> 1000 | Q14: =SUMIFS(MOVIMIENTOS!$I:$I,MOVIMIENTOS!$D:$D,"Aporte",MOVIMIENTOS!$E:$E,"Extraordinaria",MOVIMIENTOS!$F:$F,Q$4,MOVIMIENTOS!$J:$J,$C14) -> 2000 | R14: =SUMIFS(MOVIMIENTOS!$I:$I,MOVIMIENTOS!$D:$D,"Aporte",MOVIMIENTOS!$E:$E,"Extraordinaria",MOVIMIENTOS!$F:$F,R$4,MOVIMIENTOS!$J:$J,$C14) -> 2000 | S14: =SUMIFS(MOVIMIENTOS!$I:$I,MOVIMIENTOS!$D:$D,"Aporte",MOVIMIENTOS!$E:$E,"Extraordinaria",MOVIMIENTOS!$F:$F,S$4,MOVIMIENTOS!$J:$J,$C14) -> 0 | T14: =SUMIFS(MOVIMIENTOS!$I:$I,MOVIMIENTOS!$D:$D,"Aporte",MOVIMIENTOS!$E:$E,"Extraordinaria",MOVIMIENTOS!$F:$F,T$4,MOVIMIENTOS!$J:$J,$C14) -> 0 | U14: =SUMIFS(MOVIMIENTOS!$I:$I,MOVIMIENTOS!$D:$D,"Aporte",MOVIMIENTOS!$E:$E,"Extraordinaria",MOVIMIENTOS!$F:$F,U$4,MOVIMIENTOS!$J:$J,$C14) -> 0 | V14: =SUMIFS(MOVIMIENTOS!$I:$I,MOVIMIENTOS!$D:$D,"Aporte",MOVIMIENTOS!$E:$E,"Extraordinaria",MOVIMIENTOS!$F:$F,V$4,MOVIMIENTOS!$J:$J,$C14) -> 0 | W14: =SUM(P14:V14) -> 5000 | X14: =O14+W14 -> 17000
A15: 11 | B15: 24953133-2 | C15: DONOSO ZAMORA SOFÍA ELENA | D15: JENNY ZAMORA | E15: =SUMIFS(MOVIMIENTOS!$I:$I,MOVIMIENTOS!$D:$D,"Aporte",MOVIMIENTOS!$E:$E,"Anual",MOVIMIENTOS!$J:$J,$C15,MOVIMIENTOS!$B:$B,">="&DATE(2026,3,1),MOVIMIENTOS!$B:$B,"<"&DATE(2026,4,1)) -> 3000 | F15: =SUMIFS(MOVIMIENTOS!$I:$I,MOVIMIENTOS!$D:$D,"Aporte",MOVIMIENTOS!$E:$E,"Anual",MOVIMIENTOS!$J:$J,$C15,MOVIMIENTOS!$B:$B,">="&DATE(2026,4,1),MOVIMIENTOS!$B:$B,"<"&DATE(2026,5,1)) -> 3000 | G15: =SUMIFS(MOVIMIENTOS!$I:$I,MOVIMIENTOS!$D:$D,"Aporte",MOVIMIENTOS!$E:$E,"Anual",MOVIMIENTOS!$J:$J,$C15,MOVIMIENTOS!$B:$B,">="&DATE(2026,5,1),MOVIMIENTOS!$B:$B,"<"&DATE(2026,6,1)) -> 3000 | H15: =SUMIFS(MOVIMIENTOS!$I:$I,MOVIMIENTOS!$D:$D,"Aporte",MOVIMIENTOS!$E:$E,"Anual",MOVIMIENTOS!$J:$J,$C15,MOVIMIENTOS!$B:$B,">="&DATE(2026,6,1),MOVIMIENTOS!$B:$B,"<"&DATE(2026,7,1)) -> 3000 | I15: =SUMIFS(MOVIMIENTOS!$I:$I,MOVIMIENTOS!$D:$D,"Aporte",MOVIMIENTOS!$E:$E,"Anual",MOVIMIENTOS!$J:$J,$C15,MOVIMIENTOS!$B:$B,">="&DATE(2026,7,1),MOVIMIENTOS!$B:$B,"<"&DATE(2026,8,1)) -> 3000 | J15: =SUMIFS(MOVIMIENTOS!$I:$I,MOVIMIENTOS!$D:$D,"Aporte",MOVIMIENTOS!$E:$E,"Anual",MOVIMIENTOS!$J:$J,$C15,MOVIMIENTOS!$B:$B,">="&DATE(2026,8,1),MOVIMIENTOS!$B:$B,"<"&DATE(2026,9,1)) -> 0 | K15: =SUMIFS(MOVIMIENTOS!$I:$I,MOVIMIENTOS!$D:$D,"Aporte",MOVIMIENTOS!$E:$E,"Anual",MOVIMIENTOS!$J:$J,$C15,MOVIMIENTOS!$B:$B,">="&DATE(2026,9,1),MOVIMIENTOS!$B:$B,"<"&DATE(2026,10,1)) -> 0 | L15: =SUMIFS(MOVIMIENTOS!$I:$I,MOVIMIENTOS!$D:$D,"Aporte",MOVIMIENTOS!$E:$E,"Anual",MOVIMIENTOS!$J:$J,$C15,MOVIMIENTOS!$B:$B,">="&DATE(2026,10,1),MOVIMIENTOS!$B:$B,"<"&DATE(2026,11,1)) -> 0 | M15: =SUMIFS(MOVIMIENTOS!$I:$I,MOVIMIENTOS!$D:$D,"Aporte",MOVIMIENTOS!$E:$E,"Anual",MOVIMIENTOS!$J:$J,$C15,MOVIMIENTOS!$B:$B,">="&DATE(2026,11,1),MOVIMIENTOS!$B:$B,"<"&DATE(2026,12,1)) -> 0 | N15: =SUMIFS(MOVIMIENTOS!$I:$I,MOVIMIENTOS!$D:$D,"Aporte",MOVIMIENTOS!$E:$E,"Anual",MOVIMIENTOS!$J:$J,$C15,MOVIMIENTOS!$B:$B,">="&DATE(2026,12,1),MOVIMIENTOS!$B:$B,"<"&DATE(2026,13,1)) -> 0 | O15: =SUM(E15:N15) -> 15000 | P15: =SUMIFS(MOVIMIENTOS!$I:$I,MOVIMIENTOS!$D:$D,"Aporte",MOVIMIENTOS!$E:$E,"Extraordinaria",MOVIMIENTOS!$F:$F,P$4,MOVIMIENTOS!$J:$J,$C15) -> 1000 | Q15: =SUMIFS(MOVIMIENTOS!$I:$I,MOVIMIENTOS!$D:$D,"Aporte",MOVIMIENTOS!$E:$E,"Extraordinaria",MOVIMIENTOS!$F:$F,Q$4,MOVIMIENTOS!$J:$J,$C15) -> 2000 | R15: =SUMIFS(MOVIMIENTOS!$I:$I,MOVIMIENTOS!$D:$D,"Aporte",MOVIMIENTOS!$E:$E,"Extraordinaria",MOVIMIENTOS!$F:$F,R$4,MOVIMIENTOS!$J:$J,$C15) -> 2000 | S15: =SUMIFS(MOVIMIENTOS!$I:$I,MOVIMIENTOS!$D:$D,"Aporte",MOVIMIENTOS!$E:$E,"Extraordinaria",MOVIMIENTOS!$F:$F,S$4,MOVIMIENTOS!$J:$J,$C15) -> 0 | T15: =SUMIFS(MOVIMIENTOS!$I:$I,MOVIMIENTOS!$D:$D,"Aporte",MOVIMIENTOS!$E:$E,"Extraordinaria",MOVIMIENTOS!$F:$F,T$4,MOVIMIENTOS!$J:$J,$C15) -> 0 | U15: =SUMIFS(MOVIMIENTOS!$I:$I,MOVIMIENTOS!$D:$D,"Aporte",MOVIMIENTOS!$E:$E,"Extraordinaria",MOVIMIENTOS!$F:$F,U$4,MOVIMIENTOS!$J:$J,$C15) -> 1000 | V15: =SUMIFS(MOVIMIENTOS!$I:$I,MOVIMIENTOS!$D:$D,"Aporte",MOVIMIENTOS!$E:$E,"Extraordinaria",MOVIMIENTOS!$F:$F,V$4,MOVIMIENTOS!$J:$J,$C15) -> 0 | W15: =SUM(P15:V15) -> 6000 | X15: =O15+W15 -> 21000
A16: 12 | B16: 24751135-0 | C16: INOSTROZA MOLINA MATÍAS ALONSO | D16: OLGA MOLINA | E16: =SUMIFS(MOVIMIENTOS!$I:$I,MOVIMIENTOS!$D:$D,"Aporte",MOVIMIENTOS!$E:$E,"Anual",MOVIMIENTOS!$J:$J,$C16,MOVIMIENTOS!$B:$B,">="&DATE(2026,3,1),MOVIMIENTOS!$B:$B,"<"&DATE(2026,4,1)) -> 3000 | F16: =SUMIFS(MOVIMIENTOS!$I:$I,MOVIMIENTOS!$D:$D,"Aporte",MOVIMIENTOS!$E:$E,"Anual",MOVIMIENTOS!$J:$J,$C16,MOVIMIENTOS!$B:$B,">="&DATE(2026,4,1),MOVIMIENTOS!$B:$B,"<"&DATE(2026,5,1)) -> 3000 | G16: =SUMIFS(MOVIMIENTOS!$I:$I,MOVIMIENTOS!$D:$D,"Aporte",MOVIMIENTOS!$E:$E,"Anual",MOVIMIENTOS!$J:$J,$C16,MOVIMIENTOS!$B:$B,">="&DATE(2026,5,1),MOVIMIENTOS!$B:$B,"<"&DATE(2026,6,1)) -> 3000 | H16: =SUMIFS(MOVIMIENTOS!$I:$I,MOVIMIENTOS!$D:$D,"Aporte",MOVIMIENTOS!$E:$E,"Anual",MOVIMIENTOS!$J:$J,$C16,MOVIMIENTOS!$B:$B,">="&DATE(2026,6,1),MOVIMIENTOS!$B:$B,"<"&DATE(2026,7,1)) -> 3000 | I16: =SUMIFS(MOVIMIENTOS!$I:$I,MOVIMIENTOS!$D:$D,"Aporte",MOVIMIENTOS!$E:$E,"Anual",MOVIMIENTOS!$J:$J,$C16,MOVIMIENTOS!$B:$B,">="&DATE(2026,7,1),MOVIMIENTOS!$B:$B,"<"&DATE(2026,8,1)) -> 3000 | J16: =SUMIFS(MOVIMIENTOS!$I:$I,MOVIMIENTOS!$D:$D,"Aporte",MOVIMIENTOS!$E:$E,"Anual",MOVIMIENTOS!$J:$J,$C16,MOVIMIENTOS!$B:$B,">="&DATE(2026,8,1),MOVIMIENTOS!$B:$B,"<"&DATE(2026,9,1)) -> 3000 | K16: =SUMIFS(MOVIMIENTOS!$I:$I,MOVIMIENTOS!$D:$D,"Aporte",MOVIMIENTOS!$E:$E,"Anual",MOVIMIENTOS!$J:$J,$C16,MOVIMIENTOS!$B:$B,">="&DATE(2026,9,1),MOVIMIENTOS!$B:$B,"<"&DATE(2026,10,1)) -> 0 | L16: =SUMIFS(MOVIMIENTOS!$I:$I,MOVIMIENTOS!$D:$D,"Aporte",MOVIMIENTOS!$E:$E,"Anual",MOVIMIENTOS!$J:$J,$C16,MOVIMIENTOS!$B:$B,">="&DATE(2026,10,1),MOVIMIENTOS!$B:$B,"<"&DATE(2026,11,1)) -> 0 | M16: =SUMIFS(MOVIMIENTOS!$I:$I,MOVIMIENTOS!$D:$D,"Aporte",MOVIMIENTOS!$E:$E,"Anual",MOVIMIENTOS!$J:$J,$C16,MOVIMIENTOS!$B:$B,">="&DATE(2026,11,1),MOVIMIENTOS!$B:$B,"<"&DATE(2026,12,1)) -> 0 | N16: =SUMIFS(MOVIMIENTOS!$I:$I,MOVIMIENTOS!$D:$D,"Aporte",MOVIMIENTOS!$E:$E,"Anual",MOVIMIENTOS!$J:$J,$C16,MOVIMIENTOS!$B:$B,">="&DATE(2026,12,1),MOVIMIENTOS!$B:$B,"<"&DATE(2026,13,1)) -> 0 | O16: =SUM(E16:N16) -> 18000 | P16: =SUMIFS(MOVIMIENTOS!$I:$I,MOVIMIENTOS!$D:$D,"Aporte",MOVIMIENTOS!$E:$E,"Extraordinaria",MOVIMIENTOS!$F:$F,P$4,MOVIMIENTOS!$J:$J,$C16) -> 1000 | Q16: =SUMIFS(MOVIMIENTOS!$I:$I,MOVIMIENTOS!$D:$D,"Aporte",MOVIMIENTOS!$E:$E,"Extraordinaria",MOVIMIENTOS!$F:$F,Q$4,MOVIMIENTOS!$J:$J,$C16) -> 2000 | R16: =SUMIFS(MOVIMIENTOS!$I:$I,MOVIMIENTOS!$D:$D,"Aporte",MOVIMIENTOS!$E:$E,"Extraordinaria",MOVIMIENTOS!$F:$F,R$4,MOVIMIENTOS!$J:$J,$C16) -> 0 | S16: =SUMIFS(MOVIMIENTOS!$I:$I,MOVIMIENTOS!$D:$D,"Aporte",MOVIMIENTOS!$E:$E,"Extraordinaria",MOVIMIENTOS!$F:$F,S$4,MOVIMIENTOS!$J:$J,$C16) -> 0 | T16: =SUMIFS(MOVIMIENTOS!$I:$I,MOVIMIENTOS!$D:$D,"Aporte",MOVIMIENTOS!$E:$E,"Extraordinaria",MOVIMIENTOS!$F:$F,T$4,MOVIMIENTOS!$J:$J,$C16) -> 0 | U16: =SUMIFS(MOVIMIENTOS!$I:$I,MOVIMIENTOS!$D:$D,"Aporte",MOVIMIENTOS!$E:$E,"Extraordinaria",MOVIMIENTOS!$F:$F,U$4,MOVIMIENTOS!$J:$J,$C16) -> 0 | V16: =SUMIFS(MOVIMIENTOS!$I:$I,MOVIMIENTOS!$D:$D,"Aporte",MOVIMIENTOS!$E:$E,"Extraordinaria",MOVIMIENTOS!$F:$F,V$4,MOVIMIENTOS!$J:$J,$C16) -> 0 | W16: =SUM(P16:V16) -> 3000 | X16: =O16+W16 -> 21000
A17: 13 | B17: 25049508-0 | C17: ITURRIETA HERNÁNDEZ MAXIMILIANO ALEJANDRO | D17: VALERIA HERNANDEZ | E17: =SUMIFS(MOVIMIENTOS!$I:$I,MOVIMIENTOS!$D:$D,"Aporte",MOVIMIENTOS!$E:$E,"Anual",MOVIMIENTOS!$J:$J,$C17,MOVIMIENTOS!$B:$B,">="&DATE(2026,3,1),MOVIMIENTOS!$B:$B,"<"&DATE(2026,4,1)) -> 3000 | F17: =SUMIFS(MOVIMIENTOS!$I:$I,MOVIMIENTOS!$D:$D,"Aporte",MOVIMIENTOS!$E:$E,"Anual",MOVIMIENTOS!$J:$J,$C17,MOVIMIENTOS!$B:$B,">="&DATE(2026,4,1),MOVIMIENTOS!$B:$B,"<"&DATE(2026,5,1)) -> 0 | G17: =SUMIFS(MOVIMIENTOS!$I:$I,MOVIMIENTOS!$D:$D,"Aporte",MOVIMIENTOS!$E:$E,"Anual",MOVIMIENTOS!$J:$J,$C17,MOVIMIENTOS!$B:$B,">="&DATE(2026,5,1),MOVIMIENTOS!$B:$B,"<"&DATE(2026,6,1)) -> 0 | H17: =SUMIFS(MOVIMIENTOS!$I:$I,MOVIMIENTOS!$D:$D,"Aporte",MOVIMIENTOS!$E:$E,"Anual",MOVIMIENTOS!$J:$J,$C17,MOVIMIENTOS!$B:$B,">="&DATE(2026,6,1),MOVIMIENTOS!$B:$B,"<"&DATE(2026,7,1)) -> 0 | I17: =SUMIFS(MOVIMIENTOS!$I:$I,MOVIMIENTOS!$D:$D,"Aporte",MOVIMIENTOS!$E:$E,"Anual",MOVIMIENTOS!$J:$J,$C17,MOVIMIENTOS!$B:$B,">="&DATE(2026,7,1),MOVIMIENTOS!$B:$B,"<"&DATE(2026,8,1)) -> 0 | J17: =SUMIFS(MOVIMIENTOS!$I:$I,MOVIMIENTOS!$D:$D,"Aporte",MOVIMIENTOS!$E:$E,"Anual",MOVIMIENTOS!$J:$J,$C17,MOVIMIENTOS!$B:$B,">="&DATE(2026,8,1),MOVIMIENTOS!$B:$B,"<"&DATE(2026,9,1)) -> 0 | K17: =SUMIFS(MOVIMIENTOS!$I:$I,MOVIMIENTOS!$D:$D,"Aporte",MOVIMIENTOS!$E:$E,"Anual",MOVIMIENTOS!$J:$J,$C17,MOVIMIENTOS!$B:$B,">="&DATE(2026,9,1),MOVIMIENTOS!$B:$B,"<"&DATE(2026,10,1)) -> 0 | L17: =SUMIFS(MOVIMIENTOS!$I:$I,MOVIMIENTOS!$D:$D,"Aporte",MOVIMIENTOS!$E:$E,"Anual",MOVIMIENTOS!$J:$J,$C17,MOVIMIENTOS!$B:$B,">="&DATE(2026,10,1),MOVIMIENTOS!$B:$B,"<"&DATE(2026,11,1)) -> 0 | M17: =SUMIFS(MOVIMIENTOS!$I:$I,MOVIMIENTOS!$D:$D,"Aporte",MOVIMIENTOS!$E:$E,"Anual",MOVIMIENTOS!$J:$J,$C17,MOVIMIENTOS!$B:$B,">="&DATE(2026,11,1),MOVIMIENTOS!$B:$B,"<"&DATE(2026,12,1)) -> 0 | N17: =SUMIFS(MOVIMIENTOS!$I:$I,MOVIMIENTOS!$D:$D,"Aporte",MOVIMIENTOS!$E:$E,"Anual",MOVIMIENTOS!$J:$J,$C17,MOVIMIENTOS!$B:$B,">="&DATE(2026,12,1),MOVIMIENTOS!$B:$B,"<"&DATE(2026,13,1)) -> 0 | O17: =SUM(E17:N17) -> 3000 | P17: =SUMIFS(MOVIMIENTOS!$I:$I,MOVIMIENTOS!$D:$D,"Aporte",MOVIMIENTOS!$E:$E,"Extraordinaria",MOVIMIENTOS!$F:$F,P$4,MOVIMIENTOS!$J:$J,$C17) -> 1000 | Q17: =SUMIFS(MOVIMIENTOS!$I:$I,MOVIMIENTOS!$D:$D,"Aporte",MOVIMIENTOS!$E:$E,"Extraordinaria",MOVIMIENTOS!$F:$F,Q$4,MOVIMIENTOS!$J:$J,$C17) -> 2000 | R17: =SUMIFS(MOVIMIENTOS!$I:$I,MOVIMIENTOS!$D:$D,"Aporte",MOVIMIENTOS!$E:$E,"Extraordinaria",MOVIMIENTOS!$F:$F,R$4,MOVIMIENTOS!$J:$J,$C17) -> 2000 | S17: =SUMIFS(MOVIMIENTOS!$I:$I,MOVIMIENTOS!$D:$D,"Aporte",MOVIMIENTOS!$E:$E,"Extraordinaria",MOVIMIENTOS!$F:$F,S$4,MOVIMIENTOS!$J:$J,$C17) -> 0 | T17: =SUMIFS(MOVIMIENTOS!$I:$I,MOVIMIENTOS!$D:$D,"Aporte",MOVIMIENTOS!$E:$E,"Extraordinaria",MOVIMIENTOS!$F:$F,T$4,MOVIMIENTOS!$J:$J,$C17) -> 0 | U17: =SUMIFS(MOVIMIENTOS!$I:$I,MOVIMIENTOS!$D:$D,"Aporte",MOVIMIENTOS!$E:$E,"Extraordinaria",MOVIMIENTOS!$F:$F,U$4,MOVIMIENTOS!$J:$J,$C17) -> 0 | V17: =SUMIFS(MOVIMIENTOS!$I:$I,MOVIMIENTOS!$D:$D,"Aporte",MOVIMIENTOS!$E:$E,"Extraordinaria",MOVIMIENTOS!$F:$F,V$4,MOVIMIENTOS!$J:$J,$C17) -> 0 | W17: =SUM(P17:V17) -> 5000 | X17: =O17+W17 -> 8000
A18: 14 | B18: 25049482-3 | C18: ITURRIETA HERNÁNDEZ VICENTE IGNACIO | D18: VALERIA HERNANDEZ | E18: =SUMIFS(MOVIMIENTOS!$I:$I,MOVIMIENTOS!$D:$D,"Aporte",MOVIMIENTOS!$E:$E,"Anual",MOVIMIENTOS!$J:$J,$C18,MOVIMIENTOS!$B:$B,">="&DATE(2026,3,1),MOVIMIENTOS!$B:$B,"<"&DATE(2026,4,1)) -> 3000 | F18: =SUMIFS(MOVIMIENTOS!$I:$I,MOVIMIENTOS!$D:$D,"Aporte",MOVIMIENTOS!$E:$E,"Anual",MOVIMIENTOS!$J:$J,$C18,MOVIMIENTOS!$B:$B,">="&DATE(2026,4,1),MOVIMIENTOS!$B:$B,"<"&DATE(2026,5,1)) -> 0 | G18: =SUMIFS(MOVIMIENTOS!$I:$I,MOVIMIENTOS!$D:$D,"Aporte",MOVIMIENTOS!$E:$E,"Anual",MOVIMIENTOS!$J:$J,$C18,MOVIMIENTOS!$B:$B,">="&DATE(2026,5,1),MOVIMIENTOS!$B:$B,"<"&DATE(2026,6,1)) -> 0 | H18: =SUMIFS(MOVIMIENTOS!$I:$I,MOVIMIENTOS!$D:$D,"Aporte",MOVIMIENTOS!$E:$E,"Anual",MOVIMIENTOS!$J:$J,$C18,MOVIMIENTOS!$B:$B,">="&DATE(2026,6,1),MOVIMIENTOS!$B:$B,"<"&DATE(2026,7,1)) -> 0 | I18: =SUMIFS(MOVIMIENTOS!$I:$I,MOVIMIENTOS!$D:$D,"Aporte",MOVIMIENTOS!$E:$E,"Anual",MOVIMIENTOS!$J:$J,$C18,MOVIMIENTOS!$B:$B,">="&DATE(2026,7,1),MOVIMIENTOS!$B:$B,"<"&DATE(2026,8,1)) -> 0 | J18: =SUMIFS(MOVIMIENTOS!$I:$I,MOVIMIENTOS!$D:$D,"Aporte",MOVIMIENTOS!$E:$E,"Anual",MOVIMIENTOS!$J:$J,$C18,MOVIMIENTOS!$B:$B,">="&DATE(2026,8,1),MOVIMIENTOS!$B:$B,"<"&DATE(2026,9,1)) -> 0 | K18: =SUMIFS(MOVIMIENTOS!$I:$I,MOVIMIENTOS!$D:$D,"Aporte",MOVIMIENTOS!$E:$E,"Anual",MOVIMIENTOS!$J:$J,$C18,MOVIMIENTOS!$B:$B,">="&DATE(2026,9,1),MOVIMIENTOS!$B:$B,"<"&DATE(2026,10,1)) -> 0 | L18: =SUMIFS(MOVIMIENTOS!$I:$I,MOVIMIENTOS!$D:$D,"Aporte",MOVIMIENTOS!$E:$E,"Anual",MOVIMIENTOS!$J:$J,$C18,MOVIMIENTOS!$B:$B,">="&DATE(2026,10,1),MOVIMIENTOS!$B:$B,"<"&DATE(2026,11,1)) -> 0 | M18: =SUMIFS(MOVIMIENTOS!$I:$I,MOVIMIENTOS!$D:$D,"Aporte",MOVIMIENTOS!$E:$E,"Anual",MOVIMIENTOS!$J:$J,$C18,MOVIMIENTOS!$B:$B,">="&DATE(2026,11,1),MOVIMIENTOS!$B:$B,"<"&DATE(2026,12,1)) -> 0 | N18: =SUMIFS(MOVIMIENTOS!$I:$I,MOVIMIENTOS!$D:$D,"Aporte",MOVIMIENTOS!$E:$E,"Anual",MOVIMIENTOS!$J:$J,$C18,MOVIMIENTOS!$B:$B,">="&DATE(2026,12,1),MOVIMIENTOS!$B:$B,"<"&DATE(2026,13,1)) -> 0 | O18: =SUM(E18:N18) -> 3000 | P18: =SUMIFS(MOVIMIENTOS!$I:$I,MOVIMIENTOS!$D:$D,"Aporte",MOVIMIENTOS!$E:$E,"Extraordinaria",MOVIMIENTOS!$F:$F,P$4,MOVIMIENTOS!$J:$J,$C18) -> 1000 | Q18: =SUMIFS(MOVIMIENTOS!$I:$I,MOVIMIENTOS!$D:$D,"Aporte",MOVIMIENTOS!$E:$E,"Extraordinaria",MOVIMIENTOS!$F:$F,Q$4,MOVIMIENTOS!$J:$J,$C18) -> 2000 | R18: =SUMIFS(MOVIMIENTOS!$I:$I,MOVIMIENTOS!$D:$D,"Aporte",MOVIMIENTOS!$E:$E,"Extraordinaria",MOVIMIENTOS!$F:$F,R$4,MOVIMIENTOS!$J:$J,$C18) -> 2000 | S18: =SUMIFS(MOVIMIENTOS!$I:$I,MOVIMIENTOS!$D:$D,"Aporte",MOVIMIENTOS!$E:$E,"Extraordinaria",MOVIMIENTOS!$F:$F,S$4,MOVIMIENTOS!$J:$J,$C18) -> 0 | T18: =SUMIFS(MOVIMIENTOS!$I:$I,MOVIMIENTOS!$D:$D,"Aporte",MOVIMIENTOS!$E:$E,"Extraordinaria",MOVIMIENTOS!$F:$F,T$4,MOVIMIENTOS!$J:$J,$C18) -> 0 | U18: =SUMIFS(MOVIMIENTOS!$I:$I,MOVIMIENTOS!$D:$D,"Aporte",MOVIMIENTOS!$E:$E,"Extraordinaria",MOVIMIENTOS!$F:$F,U$4,MOVIMIENTOS!$J:$J,$C18) -> 0 | V18: =SUMIFS(MOVIMIENTOS!$I:$I,MOVIMIENTOS!$D:$D,"Aporte",MOVIMIENTOS!$E:$E,"Extraordinaria",MOVIMIENTOS!$F:$F,V$4,MOVIMIENTOS!$J:$J,$C18) -> 0 | W18: =SUM(P18:V18) -> 5000 | X18: =O18+W18 -> 8000
A19: 15 | B19: 25067494-5 | C19: JATIB DÍAZ ABDOLASIS MAXIMILIANO | D19: MARISOL DIAZ | E19: =SUMIFS(MOVIMIENTOS!$I:$I,MOVIMIENTOS!$D:$D,"Aporte",MOVIMIENTOS!$E:$E,"Anual",MOVIMIENTOS!$J:$J,$C19,MOVIMIENTOS!$B:$B,">="&DATE(2026,3,1),MOVIMIENTOS!$B:$B,"<"&DATE(2026,4,1)) -> 3000 | F19: =SUMIFS(MOVIMIENTOS!$I:$I,MOVIMIENTOS!$D:$D,"Aporte",MOVIMIENTOS!$E:$E,"Anual",MOVIMIENTOS!$J:$J,$C19,MOVIMIENTOS!$B:$B,">="&DATE(2026,4,1),MOVIMIENTOS!$B:$B,"<"&DATE(2026,5,1)) -> 0 | G19: =SUMIFS(MOVIMIENTOS!$I:$I,MOVIMIENTOS!$D:$D,"Aporte",MOVIMIENTOS!$E:$E,"Anual",MOVIMIENTOS!$J:$J,$C19,MOVIMIENTOS!$B:$B,">="&DATE(2026,5,1),MOVIMIENTOS!$B:$B,"<"&DATE(2026,6,1)) -> 0 | H19: =SUMIFS(MOVIMIENTOS!$I:$I,MOVIMIENTOS!$D:$D,"Aporte",MOVIMIENTOS!$E:$E,"Anual",MOVIMIENTOS!$J:$J,$C19,MOVIMIENTOS!$B:$B,">="&DATE(2026,6,1),MOVIMIENTOS!$B:$B,"<"&DATE(2026,7,1)) -> 0 | I19: =SUMIFS(MOVIMIENTOS!$I:$I,MOVIMIENTOS!$D:$D,"Aporte",MOVIMIENTOS!$E:$E,"Anual",MOVIMIENTOS!$J:$J,$C19,MOVIMIENTOS!$B:$B,">="&DATE(2026,7,1),MOVIMIENTOS!$B:$B,"<"&DATE(2026,8,1)) -> 0 | J19: =SUMIFS(MOVIMIENTOS!$I:$I,MOVIMIENTOS!$D:$D,"Aporte",MOVIMIENTOS!$E:$E,"Anual",MOVIMIENTOS!$J:$J,$C19,MOVIMIENTOS!$B:$B,">="&DATE(2026,8,1),MOVIMIENTOS!$B:$B,"<"&DATE(2026,9,1)) -> 0 | K19: =SUMIFS(MOVIMIENTOS!$I:$I,MOVIMIENTOS!$D:$D,"Aporte",MOVIMIENTOS!$E:$E,"Anual",MOVIMIENTOS!$J:$J,$C19,MOVIMIENTOS!$B:$B,">="&DATE(2026,9,1),MOVIMIENTOS!$B:$B,"<"&DATE(2026,10,1)) -> 0 | L19: =SUMIFS(MOVIMIENTOS!$I:$I,MOVIMIENTOS!$D:$D,"Aporte",MOVIMIENTOS!$E:$E,"Anual",MOVIMIENTOS!$J:$J,$C19,MOVIMIENTOS!$B:$B,">="&DATE(2026,10,1),MOVIMIENTOS!$B:$B,"<"&DATE(2026,11,1)) -> 0 | M19: =SUMIFS(MOVIMIENTOS!$I:$I,MOVIMIENTOS!$D:$D,"Aporte",MOVIMIENTOS!$E:$E,"Anual",MOVIMIENTOS!$J:$J,$C19,MOVIMIENTOS!$B:$B,">="&DATE(2026,11,1),MOVIMIENTOS!$B:$B,"<"&DATE(2026,12,1)) -> 0 | N19: =SUMIFS(MOVIMIENTOS!$I:$I,MOVIMIENTOS!$D:$D,"Aporte",MOVIMIENTOS!$E:$E,"Anual",MOVIMIENTOS!$J:$J,$C19,MOVIMIENTOS!$B:$B,">="&DATE(2026,12,1),MOVIMIENTOS!$B:$B,"<"&DATE(2026,13,1)) -> 0 | O19: =SUM(E19:N19) -> 3000 | P19: =SUMIFS(MOVIMIENTOS!$I:$I,MOVIMIENTOS!$D:$D,"Aporte",MOVIMIENTOS!$E:$E,"Extraordinaria",MOVIMIENTOS!$F:$F,P$4,MOVIMIENTOS!$J:$J,$C19) -> 1000 | Q19: =SUMIFS(MOVIMIENTOS!$I:$I,MOVIMIENTOS!$D:$D,"Aporte",MOVIMIENTOS!$E:$E,"Extraordinaria",MOVIMIENTOS!$F:$F,Q$4,MOVIMIENTOS!$J:$J,$C19) -> 2000 | R19: =SUMIFS(MOVIMIENTOS!$I:$I,MOVIMIENTOS!$D:$D,"Aporte",MOVIMIENTOS!$E:$E,"Extraordinaria",MOVIMIENTOS!$F:$F,R$4,MOVIMIENTOS!$J:$J,$C19) -> 2000 | S19: =SUMIFS(MOVIMIENTOS!$I:$I,MOVIMIENTOS!$D:$D,"Aporte",MOVIMIENTOS!$E:$E,"Extraordinaria",MOVIMIENTOS!$F:$F,S$4,MOVIMIENTOS!$J:$J,$C19) -> 0 | T19: =SUMIFS(MOVIMIENTOS!$I:$I,MOVIMIENTOS!$D:$D,"Aporte",MOVIMIENTOS!$E:$E,"Extraordinaria",MOVIMIENTOS!$F:$F,T$4,MOVIMIENTOS!$J:$J,$C19) -> 0 | U19: =SUMIFS(MOVIMIENTOS!$I:$I,MOVIMIENTOS!$D:$D,"Aporte",MOVIMIENTOS!$E:$E,"Extraordinaria",MOVIMIENTOS!$F:$F,U$4,MOVIMIENTOS!$J:$J,$C19) -> 0 | V19: =SUMIFS(MOVIMIENTOS!$I:$I,MOVIMIENTOS!$D:$D,"Aporte",MOVIMIENTOS!$E:$E,"Extraordinaria",MOVIMIENTOS!$F:$F,V$4,MOVIMIENTOS!$J:$J,$C19) -> 0 | W19: =SUM(P19:V19) -> 5000 | X19: =O19+W19 -> 8000
A20: 16 | B20: 25015009-1 | C20: MENESES YÁÑEZ ALEXANDRA MODESTA | E20: =SUMIFS(MOVIMIENTOS!$I:$I,MOVIMIENTOS!$D:$D,"Aporte",MOVIMIENTOS!$E:$E,"Anual",MOVIMIENTOS!$J:$J,$C20,MOVIMIENTOS!$B:$B,">="&DATE(2026,3,1),MOVIMIENTOS!$B:$B,"<"&DATE(2026,4,1)) -> 0 | F20: =SUMIFS(MOVIMIENTOS!$I:$I,MOVIMIENTOS!$D:$D,"Aporte",MOVIMIENTOS!$E:$E,"Anual",MOVIMIENTOS!$J:$J,$C20,MOVIMIENTOS!$B:$B,">="&DATE(2026,4,1),MOVIMIENTOS!$B:$B,"<"&DATE(2026,5,1)) -> 0 | G20: =SUMIFS(MOVIMIENTOS!$I:$I,MOVIMIENTOS!$D:$D,"Aporte",MOVIMIENTOS!$E:$E,"Anual",MOVIMIENTOS!$J:$J,$C20,MOVIMIENTOS!$B:$B,">="&DATE(2026,5,1),MOVIMIENTOS!$B:$B,"<"&DATE(2026,6,1)) -> 0 | H20: =SUMIFS(MOVIMIENTOS!$I:$I,MOVIMIENTOS!$D:$D,"Aporte",MOVIMIENTOS!$E:$E,"Anual",MOVIMIENTOS!$J:$J,$C20,MOVIMIENTOS!$B:$B,">="&DATE(2026,6,1),MOVIMIENTOS!$B:$B,"<"&DATE(2026,7,1)) -> 0 | I20: =SUMIFS(MOVIMIENTOS!$I:$I,MOVIMIENTOS!$D:$D,"Aporte",MOVIMIENTOS!$E:$E,"Anual",MOVIMIENTOS!$J:$J,$C20,MOVIMIENTOS!$B:$B,">="&DATE(2026,7,1),MOVIMIENTOS!$B:$B,"<"&DATE(2026,8,1)) -> 0 | J20: =SUMIFS(MOVIMIENTOS!$I:$I,MOVIMIENTOS!$D:$D,"Aporte",MOVIMIENTOS!$E:$E,"Anual",MOVIMIENTOS!$J:$J,$C20,MOVIMIENTOS!$B:$B,">="&DATE(2026,8,1),MOVIMIENTOS!$B:$B,"<"&DATE(2026,9,1)) -> 0 | K20: =SUMIFS(MOVIMIENTOS!$I:$I,MOVIMIENTOS!$D:$D,"Aporte",MOVIMIENTOS!$E:$E,"Anual",MOVIMIENTOS!$J:$J,$C20,MOVIMIENTOS!$B:$B,">="&DATE(2026,9,1),MOVIMIENTOS!$B:$B,"<"&DATE(2026,10,1)) -> 0 | L20: =SUMIFS(MOVIMIENTOS!$I:$I,MOVIMIENTOS!$D:$D,"Aporte",MOVIMIENTOS!$E:$E,"Anual",MOVIMIENTOS!$J:$J,$C20,MOVIMIENTOS!$B:$B,">="&DATE(2026,10,1),MOVIMIENTOS!$B:$B,"<"&DATE(2026,11,1)) -> 0 | M20: =SUMIFS(MOVIMIENTOS!$I:$I,MOVIMIENTOS!$D:$D,"Aporte",MOVIMIENTOS!$E:$E,"Anual",MOVIMIENTOS!$J:$J,$C20,MOVIMIENTOS!$B:$B,">="&DATE(2026,11,1),MOVIMIENTOS!$B:$B,"<"&DATE(2026,12,1)) -> 0 | N20: =SUMIFS(MOVIMIENTOS!$I:$I,MOVIMIENTOS!$D:$D,"Aporte",MOVIMIENTOS!$E:$E,"Anual",MOVIMIENTOS!$J:$J,$C20,MOVIMIENTOS!$B:$B,">="&DATE(2026,12,1),MOVIMIENTOS!$B:$B,"<"&DATE(2026,13,1)) -> 0 | O20: =SUM(E20:N20) -> 0 | P20: =SUMIFS(MOVIMIENTOS!$I:$I,MOVIMIENTOS!$D:$D,"Aporte",MOVIMIENTOS!$E:$E,"Extraordinaria",MOVIMIENTOS!$F:$F,P$4,MOVIMIENTOS!$J:$J,$C20) -> 1000 | Q20: =SUMIFS(MOVIMIENTOS!$I:$I,MOVIMIENTOS!$D:$D,"Aporte",MOVIMIENTOS!$E:$E,"Extraordinaria",MOVIMIENTOS!$F:$F,Q$4,MOVIMIENTOS!$J:$J,$C20) -> 2000 | R20: =SUMIFS(MOVIMIENTOS!$I:$I,MOVIMIENTOS!$D:$D,"Aporte",MOVIMIENTOS!$E:$E,"Extraordinaria",MOVIMIENTOS!$F:$F,R$4,MOVIMIENTOS!$J:$J,$C20) -> 2000 | S20: =SUMIFS(MOVIMIENTOS!$I:$I,MOVIMIENTOS!$D:$D,"Aporte",MOVIMIENTOS!$E:$E,"Extraordinaria",MOVIMIENTOS!$F:$F,S$4,MOVIMIENTOS!$J:$J,$C20) -> 0 | T20: =SUMIFS(MOVIMIENTOS!$I:$I,MOVIMIENTOS!$D:$D,"Aporte",MOVIMIENTOS!$E:$E,"Extraordinaria",MOVIMIENTOS!$F:$F,T$4,MOVIMIENTOS!$J:$J,$C20) -> 0 | U20: =SUMIFS(MOVIMIENTOS!$I:$I,MOVIMIENTOS!$D:$D,"Aporte",MOVIMIENTOS!$E:$E,"Extraordinaria",MOVIMIENTOS!$F:$F,U$4,MOVIMIENTOS!$J:$J,$C20) -> 0 | V20: =SUMIFS(MOVIMIENTOS!$I:$I,MOVIMIENTOS!$D:$D,"Aporte",MOVIMIENTOS!$E:$E,"Extraordinaria",MOVIMIENTOS!$F:$F,V$4,MOVIMIENTOS!$J:$J,$C20) -> 0 | W20: =SUM(P20:V20) -> 5000 | X20: =O20+W20 -> 5000
A21: 17 | B21: 25179616-5 | C21: MICHEA ALIAGA JOAQUÍN ELÍAS | D21: STEFANY ALIAGA | E21: =SUMIFS(MOVIMIENTOS!$I:$I,MOVIMIENTOS!$D:$D,"Aporte",MOVIMIENTOS!$E:$E,"Anual",MOVIMIENTOS!$J:$J,$C21,MOVIMIENTOS!$B:$B,">="&DATE(2026,3,1),MOVIMIENTOS!$B:$B,"<"&DATE(2026,4,1)) -> 3000 | F21: =SUMIFS(MOVIMIENTOS!$I:$I,MOVIMIENTOS!$D:$D,"Aporte",MOVIMIENTOS!$E:$E,"Anual",MOVIMIENTOS!$J:$J,$C21,MOVIMIENTOS!$B:$B,">="&DATE(2026,4,1),MOVIMIENTOS!$B:$B,"<"&DATE(2026,5,1)) -> 3000 | G21: =SUMIFS(MOVIMIENTOS!$I:$I,MOVIMIENTOS!$D:$D,"Aporte",MOVIMIENTOS!$E:$E,"Anual",MOVIMIENTOS!$J:$J,$C21,MOVIMIENTOS!$B:$B,">="&DATE(2026,5,1),MOVIMIENTOS!$B:$B,"<"&DATE(2026,6,1)) -> 3000 | H21: =SUMIFS(MOVIMIENTOS!$I:$I,MOVIMIENTOS!$D:$D,"Aporte",MOVIMIENTOS!$E:$E,"Anual",MOVIMIENTOS!$J:$J,$C21,MOVIMIENTOS!$B:$B,">="&DATE(2026,6,1),MOVIMIENTOS!$B:$B,"<"&DATE(2026,7,1)) -> 3000 | I21: =SUMIFS(MOVIMIENTOS!$I:$I,MOVIMIENTOS!$D:$D,"Aporte",MOVIMIENTOS!$E:$E,"Anual",MOVIMIENTOS!$J:$J,$C21,MOVIMIENTOS!$B:$B,">="&DATE(2026,7,1),MOVIMIENTOS!$B:$B,"<"&DATE(2026,8,1)) -> 3000 | J21: =SUMIFS(MOVIMIENTOS!$I:$I,MOVIMIENTOS!$D:$D,"Aporte",MOVIMIENTOS!$E:$E,"Anual",MOVIMIENTOS!$J:$J,$C21,MOVIMIENTOS!$B:$B,">="&DATE(2026,8,1),MOVIMIENTOS!$B:$B,"<"&DATE(2026,9,1)) -> 0 | K21: =SUMIFS(MOVIMIENTOS!$I:$I,MOVIMIENTOS!$D:$D,"Aporte",MOVIMIENTOS!$E:$E,"Anual",MOVIMIENTOS!$J:$J,$C21,MOVIMIENTOS!$B:$B,">="&DATE(2026,9,1),MOVIMIENTOS!$B:$B,"<"&DATE(2026,10,1)) -> 0 | L21: =SUMIFS(MOVIMIENTOS!$I:$I,MOVIMIENTOS!$D:$D,"Aporte",MOVIMIENTOS!$E:$E,"Anual",MOVIMIENTOS!$J:$J,$C21,MOVIMIENTOS!$B:$B,">="&DATE(2026,10,1),MOVIMIENTOS!$B:$B,"<"&DATE(2026,11,1)) -> 0 | M21: =SUMIFS(MOVIMIENTOS!$I:$I,MOVIMIENTOS!$D:$D,"Aporte",MOVIMIENTOS!$E:$E,"Anual",MOVIMIENTOS!$J:$J,$C21,MOVIMIENTOS!$B:$B,">="&DATE(2026,11,1),MOVIMIENTOS!$B:$B,"<"&DATE(2026,12,1)) -> 0 | N21: =SUMIFS(MOVIMIENTOS!$I:$I,MOVIMIENTOS!$D:$D,"Aporte",MOVIMIENTOS!$E:$E,"Anual",MOVIMIENTOS!$J:$J,$C21,MOVIMIENTOS!$B:$B,">="&DATE(2026,12,1),MOVIMIENTOS!$B:$B,"<"&DATE(2026,13,1)) -> 0 | O21: =SUM(E21:N21) -> 15000 | P21: =SUMIFS(MOVIMIENTOS!$I:$I,MOVIMIENTOS!$D:$D,"Aporte",MOVIMIENTOS!$E:$E,"Extraordinaria",MOVIMIENTOS!$F:$F,P$4,MOVIMIENTOS!$J:$J,$C21) -> 1000 | Q21: =SUMIFS(MOVIMIENTOS!$I:$I,MOVIMIENTOS!$D:$D,"Aporte",MOVIMIENTOS!$E:$E,"Extraordinaria",MOVIMIENTOS!$F:$F,Q$4,MOVIMIENTOS!$J:$J,$C21) -> 2000 | R21: =SUMIFS(MOVIMIENTOS!$I:$I,MOVIMIENTOS!$D:$D,"Aporte",MOVIMIENTOS!$E:$E,"Extraordinaria",MOVIMIENTOS!$F:$F,R$4,MOVIMIENTOS!$J:$J,$C21) -> 2000 | S21: =SUMIFS(MOVIMIENTOS!$I:$I,MOVIMIENTOS!$D:$D,"Aporte",MOVIMIENTOS!$E:$E,"Extraordinaria",MOVIMIENTOS!$F:$F,S$4,MOVIMIENTOS!$J:$J,$C21) -> 0 | T21: =SUMIFS(MOVIMIENTOS!$I:$I,MOVIMIENTOS!$D:$D,"Aporte",MOVIMIENTOS!$E:$E,"Extraordinaria",MOVIMIENTOS!$F:$F,T$4,MOVIMIENTOS!$J:$J,$C21) -> 0 | U21: =SUMIFS(MOVIMIENTOS!$I:$I,MOVIMIENTOS!$D:$D,"Aporte",MOVIMIENTOS!$E:$E,"Extraordinaria",MOVIMIENTOS!$F:$F,U$4,MOVIMIENTOS!$J:$J,$C21) -> 0 | V21: =SUMIFS(MOVIMIENTOS!$I:$I,MOVIMIENTOS!$D:$D,"Aporte",MOVIMIENTOS!$E:$E,"Extraordinaria",MOVIMIENTOS!$F:$F,V$4,MOVIMIENTOS!$J:$J,$C21) -> 0 | W21: =SUM(P21:V21) -> 5000 | X21: =O21+W21 -> 20000
A22: 18 | B22: 25026561-1 | C22: MOYA SALAS COLOMBA AYLÉN | D22: NATALIE SALAS | E22: =SUMIFS(MOVIMIENTOS!$I:$I,MOVIMIENTOS!$D:$D,"Aporte",MOVIMIENTOS!$E:$E,"Anual",MOVIMIENTOS!$J:$J,$C22,MOVIMIENTOS!$B:$B,">="&DATE(2026,3,1),MOVIMIENTOS!$B:$B,"<"&DATE(2026,4,1)) -> 3000 | F22: =SUMIFS(MOVIMIENTOS!$I:$I,MOVIMIENTOS!$D:$D,"Aporte",MOVIMIENTOS!$E:$E,"Anual",MOVIMIENTOS!$J:$J,$C22,MOVIMIENTOS!$B:$B,">="&DATE(2026,4,1),MOVIMIENTOS!$B:$B,"<"&DATE(2026,5,1)) -> 0 | G22: =SUMIFS(MOVIMIENTOS!$I:$I,MOVIMIENTOS!$D:$D,"Aporte",MOVIMIENTOS!$E:$E,"Anual",MOVIMIENTOS!$J:$J,$C22,MOVIMIENTOS!$B:$B,">="&DATE(2026,5,1),MOVIMIENTOS!$B:$B,"<"&DATE(2026,6,1)) -> 0 | H22: =SUMIFS(MOVIMIENTOS!$I:$I,MOVIMIENTOS!$D:$D,"Aporte",MOVIMIENTOS!$E:$E,"Anual",MOVIMIENTOS!$J:$J,$C22,MOVIMIENTOS!$B:$B,">="&DATE(2026,6,1),MOVIMIENTOS!$B:$B,"<"&DATE(2026,7,1)) -> 0 | I22: =SUMIFS(MOVIMIENTOS!$I:$I,MOVIMIENTOS!$D:$D,"Aporte",MOVIMIENTOS!$E:$E,"Anual",MOVIMIENTOS!$J:$J,$C22,MOVIMIENTOS!$B:$B,">="&DATE(2026,7,1),MOVIMIENTOS!$B:$B,"<"&DATE(2026,8,1)) -> 0 | J22: =SUMIFS(MOVIMIENTOS!$I:$I,MOVIMIENTOS!$D:$D,"Aporte",MOVIMIENTOS!$E:$E,"Anual",MOVIMIENTOS!$J:$J,$C22,MOVIMIENTOS!$B:$B,">="&DATE(2026,8,1),MOVIMIENTOS!$B:$B,"<"&DATE(2026,9,1)) -> 0 | K22: =SUMIFS(MOVIMIENTOS!$I:$I,MOVIMIENTOS!$D:$D,"Aporte",MOVIMIENTOS!$E:$E,"Anual",MOVIMIENTOS!$J:$J,$C22,MOVIMIENTOS!$B:$B,">="&DATE(2026,9,1),MOVIMIENTOS!$B:$B,"<"&DATE(2026,10,1)) -> 0 | L22: =SUMIFS(MOVIMIENTOS!$I:$I,MOVIMIENTOS!$D:$D,"Aporte",MOVIMIENTOS!$E:$E,"Anual",MOVIMIENTOS!$J:$J,$C22,MOVIMIENTOS!$B:$B,">="&DATE(2026,10,1),MOVIMIENTOS!$B:$B,"<"&DATE(2026,11,1)) -> 0 | M22: =SUMIFS(MOVIMIENTOS!$I:$I,MOVIMIENTOS!$D:$D,"Aporte",MOVIMIENTOS!$E:$E,"Anual",MOVIMIENTOS!$J:$J,$C22,MOVIMIENTOS!$B:$B,">="&DATE(2026,11,1),MOVIMIENTOS!$B:$B,"<"&DATE(2026,12,1)) -> 0 | N22: =SUMIFS(MOVIMIENTOS!$I:$I,MOVIMIENTOS!$D:$D,"Aporte",MOVIMIENTOS!$E:$E,"Anual",MOVIMIENTOS!$J:$J,$C22,MOVIMIENTOS!$B:$B,">="&DATE(2026,12,1),MOVIMIENTOS!$B:$B,"<"&DATE(2026,13,1)) -> 0 | O22: =SUM(E22:N22) -> 3000 | P22: =SUMIFS(MOVIMIENTOS!$I:$I,MOVIMIENTOS!$D:$D,"Aporte",MOVIMIENTOS!$E:$E,"Extraordinaria",MOVIMIENTOS!$F:$F,P$4,MOVIMIENTOS!$J:$J,$C22) -> 1000 | Q22: =SUMIFS(MOVIMIENTOS!$I:$I,MOVIMIENTOS!$D:$D,"Aporte",MOVIMIENTOS!$E:$E,"Extraordinaria",MOVIMIENTOS!$F:$F,Q$4,MOVIMIENTOS!$J:$J,$C22) -> 2000 | R22: =SUMIFS(MOVIMIENTOS!$I:$I,MOVIMIENTOS!$D:$D,"Aporte",MOVIMIENTOS!$E:$E,"Extraordinaria",MOVIMIENTOS!$F:$F,R$4,MOVIMIENTOS!$J:$J,$C22) -> 2000 | S22: =SUMIFS(MOVIMIENTOS!$I:$I,MOVIMIENTOS!$D:$D,"Aporte",MOVIMIENTOS!$E:$E,"Extraordinaria",MOVIMIENTOS!$F:$F,S$4,MOVIMIENTOS!$J:$J,$C22) -> 0 | T22: =SUMIFS(MOVIMIENTOS!$I:$I,MOVIMIENTOS!$D:$D,"Aporte",MOVIMIENTOS!$E:$E,"Extraordinaria",MOVIMIENTOS!$F:$F,T$4,MOVIMIENTOS!$J:$J,$C22) -> 0 | U22: =SUMIFS(MOVIMIENTOS!$I:$I,MOVIMIENTOS!$D:$D,"Aporte",MOVIMIENTOS!$E:$E,"Extraordinaria",MOVIMIENTOS!$F:$F,U$4,MOVIMIENTOS!$J:$J,$C22) -> 1000 | V22: =SUMIFS(MOVIMIENTOS!$I:$I,MOVIMIENTOS!$D:$D,"Aporte",MOVIMIENTOS!$E:$E,"Extraordinaria",MOVIMIENTOS!$F:$F,V$4,MOVIMIENTOS!$J:$J,$C22) -> 0 | W22: =SUM(P22:V22) -> 6000 | X22: =O22+W22 -> 9000
A23: 19 | B23: 25012737-5 | C23: MUÑOZ BECERRA AGUSTINA ISIDORA | D23: YERI | E23: =SUMIFS(MOVIMIENTOS!$I:$I,MOVIMIENTOS!$D:$D,"Aporte",MOVIMIENTOS!$E:$E,"Anual",MOVIMIENTOS!$J:$J,$C23,MOVIMIENTOS!$B:$B,">="&DATE(2026,3,1),MOVIMIENTOS!$B:$B,"<"&DATE(2026,4,1)) -> 3000 | F23: =SUMIFS(MOVIMIENTOS!$I:$I,MOVIMIENTOS!$D:$D,"Aporte",MOVIMIENTOS!$E:$E,"Anual",MOVIMIENTOS!$J:$J,$C23,MOVIMIENTOS!$B:$B,">="&DATE(2026,4,1),MOVIMIENTOS!$B:$B,"<"&DATE(2026,5,1)) -> 0 | G23: =SUMIFS(MOVIMIENTOS!$I:$I,MOVIMIENTOS!$D:$D,"Aporte",MOVIMIENTOS!$E:$E,"Anual",MOVIMIENTOS!$J:$J,$C23,MOVIMIENTOS!$B:$B,">="&DATE(2026,5,1),MOVIMIENTOS!$B:$B,"<"&DATE(2026,6,1)) -> 0 | H23: =SUMIFS(MOVIMIENTOS!$I:$I,MOVIMIENTOS!$D:$D,"Aporte",MOVIMIENTOS!$E:$E,"Anual",MOVIMIENTOS!$J:$J,$C23,MOVIMIENTOS!$B:$B,">="&DATE(2026,6,1),MOVIMIENTOS!$B:$B,"<"&DATE(2026,7,1)) -> 0 | I23: =SUMIFS(MOVIMIENTOS!$I:$I,MOVIMIENTOS!$D:$D,"Aporte",MOVIMIENTOS!$E:$E,"Anual",MOVIMIENTOS!$J:$J,$C23,MOVIMIENTOS!$B:$B,">="&DATE(2026,7,1),MOVIMIENTOS!$B:$B,"<"&DATE(2026,8,1)) -> 0 | J23: =SUMIFS(MOVIMIENTOS!$I:$I,MOVIMIENTOS!$D:$D,"Aporte",MOVIMIENTOS!$E:$E,"Anual",MOVIMIENTOS!$J:$J,$C23,MOVIMIENTOS!$B:$B,">="&DATE(2026,8,1),MOVIMIENTOS!$B:$B,"<"&DATE(2026,9,1)) -> 0 | K23: =SUMIFS(MOVIMIENTOS!$I:$I,MOVIMIENTOS!$D:$D,"Aporte",MOVIMIENTOS!$E:$E,"Anual",MOVIMIENTOS!$J:$J,$C23,MOVIMIENTOS!$B:$B,">="&DATE(2026,9,1),MOVIMIENTOS!$B:$B,"<"&DATE(2026,10,1)) -> 0 | L23: =SUMIFS(MOVIMIENTOS!$I:$I,MOVIMIENTOS!$D:$D,"Aporte",MOVIMIENTOS!$E:$E,"Anual",MOVIMIENTOS!$J:$J,$C23,MOVIMIENTOS!$B:$B,">="&DATE(2026,10,1),MOVIMIENTOS!$B:$B,"<"&DATE(2026,11,1)) -> 0 | M23: =SUMIFS(MOVIMIENTOS!$I:$I,MOVIMIENTOS!$D:$D,"Aporte",MOVIMIENTOS!$E:$E,"Anual",MOVIMIENTOS!$J:$J,$C23,MOVIMIENTOS!$B:$B,">="&DATE(2026,11,1),MOVIMIENTOS!$B:$B,"<"&DATE(2026,12,1)) -> 0 | N23: =SUMIFS(MOVIMIENTOS!$I:$I,MOVIMIENTOS!$D:$D,"Aporte",MOVIMIENTOS!$E:$E,"Anual",MOVIMIENTOS!$J:$J,$C23,MOVIMIENTOS!$B:$B,">="&DATE(2026,12,1),MOVIMIENTOS!$B:$B,"<"&DATE(2026,13,1)) -> 0 | O23: =SUM(E23:N23) -> 3000 | P23: =SUMIFS(MOVIMIENTOS!$I:$I,MOVIMIENTOS!$D:$D,"Aporte",MOVIMIENTOS!$E:$E,"Extraordinaria",MOVIMIENTOS!$F:$F,P$4,MOVIMIENTOS!$J:$J,$C23) -> 1000 | Q23: =SUMIFS(MOVIMIENTOS!$I:$I,MOVIMIENTOS!$D:$D,"Aporte",MOVIMIENTOS!$E:$E,"Extraordinaria",MOVIMIENTOS!$F:$F,Q$4,MOVIMIENTOS!$J:$J,$C23) -> 2000 | R23: =SUMIFS(MOVIMIENTOS!$I:$I,MOVIMIENTOS!$D:$D,"Aporte",MOVIMIENTOS!$E:$E,"Extraordinaria",MOVIMIENTOS!$F:$F,R$4,MOVIMIENTOS!$J:$J,$C23) -> 2000 | S23: =SUMIFS(MOVIMIENTOS!$I:$I,MOVIMIENTOS!$D:$D,"Aporte",MOVIMIENTOS!$E:$E,"Extraordinaria",MOVIMIENTOS!$F:$F,S$4,MOVIMIENTOS!$J:$J,$C23) -> 0 | T23: =SUMIFS(MOVIMIENTOS!$I:$I,MOVIMIENTOS!$D:$D,"Aporte",MOVIMIENTOS!$E:$E,"Extraordinaria",MOVIMIENTOS!$F:$F,T$4,MOVIMIENTOS!$J:$J,$C23) -> 0 | U23: =SUMIFS(MOVIMIENTOS!$I:$I,MOVIMIENTOS!$D:$D,"Aporte",MOVIMIENTOS!$E:$E,"Extraordinaria",MOVIMIENTOS!$F:$F,U$4,MOVIMIENTOS!$J:$J,$C23) -> 0 | V23: =SUMIFS(MOVIMIENTOS!$I:$I,MOVIMIENTOS!$D:$D,"Aporte",MOVIMIENTOS!$E:$E,"Extraordinaria",MOVIMIENTOS!$F:$F,V$4,MOVIMIENTOS!$J:$J,$C23) -> 0 | W23: =SUM(P23:V23) -> 5000 | X23: =O23+W23 -> 8000
A24: 20 | B24: 25276474-7 | C24: MUÑOZ NAVARRETE ANTONELLA ESTEFANÍA | D24: JANETTE NAVARRETE | E24: =SUMIFS(MOVIMIENTOS!$I:$I,MOVIMIENTOS!$D:$D,"Aporte",MOVIMIENTOS!$E:$E,"Anual",MOVIMIENTOS!$J:$J,$C24,MOVIMIENTOS!$B:$B,">="&DATE(2026,3,1),MOVIMIENTOS!$B:$B,"<"&DATE(2026,4,1)) -> 3000 | F24: =SUMIFS(MOVIMIENTOS!$I:$I,MOVIMIENTOS!$D:$D,"Aporte",MOVIMIENTOS!$E:$E,"Anual",MOVIMIENTOS!$J:$J,$C24,MOVIMIENTOS!$B:$B,">="&DATE(2026,4,1),MOVIMIENTOS!$B:$B,"<"&DATE(2026,5,1)) -> 3000 | G24: =SUMIFS(MOVIMIENTOS!$I:$I,MOVIMIENTOS!$D:$D,"Aporte",MOVIMIENTOS!$E:$E,"Anual",MOVIMIENTOS!$J:$J,$C24,MOVIMIENTOS!$B:$B,">="&DATE(2026,5,1),MOVIMIENTOS!$B:$B,"<"&DATE(2026,6,1)) -> 3000 | H24: =SUMIFS(MOVIMIENTOS!$I:$I,MOVIMIENTOS!$D:$D,"Aporte",MOVIMIENTOS!$E:$E,"Anual",MOVIMIENTOS!$J:$J,$C24,MOVIMIENTOS!$B:$B,">="&DATE(2026,6,1),MOVIMIENTOS!$B:$B,"<"&DATE(2026,7,1)) -> 0 | I24: =SUMIFS(MOVIMIENTOS!$I:$I,MOVIMIENTOS!$D:$D,"Aporte",MOVIMIENTOS!$E:$E,"Anual",MOVIMIENTOS!$J:$J,$C24,MOVIMIENTOS!$B:$B,">="&DATE(2026,7,1),MOVIMIENTOS!$B:$B,"<"&DATE(2026,8,1)) -> 0 | J24: =SUMIFS(MOVIMIENTOS!$I:$I,MOVIMIENTOS!$D:$D,"Aporte",MOVIMIENTOS!$E:$E,"Anual",MOVIMIENTOS!$J:$J,$C24,MOVIMIENTOS!$B:$B,">="&DATE(2026,8,1),MOVIMIENTOS!$B:$B,"<"&DATE(2026,9,1)) -> 0 | K24: =SUMIFS(MOVIMIENTOS!$I:$I,MOVIMIENTOS!$D:$D,"Aporte",MOVIMIENTOS!$E:$E,"Anual",MOVIMIENTOS!$J:$J,$C24,MOVIMIENTOS!$B:$B,">="&DATE(2026,9,1),MOVIMIENTOS!$B:$B,"<"&DATE(2026,10,1)) -> 0 | L24: =SUMIFS(MOVIMIENTOS!$I:$I,MOVIMIENTOS!$D:$D,"Aporte",MOVIMIENTOS!$E:$E,"Anual",MOVIMIENTOS!$J:$J,$C24,MOVIMIENTOS!$B:$B,">="&DATE(2026,10,1),MOVIMIENTOS!$B:$B,"<"&DATE(2026,11,1)) -> 0 | M24: =SUMIFS(MOVIMIENTOS!$I:$I,MOVIMIENTOS!$D:$D,"Aporte",MOVIMIENTOS!$E:$E,"Anual",MOVIMIENTOS!$J:$J,$C24,MOVIMIENTOS!$B:$B,">="&DATE(2026,11,1),MOVIMIENTOS!$B:$B,"<"&DATE(2026,12,1)) -> 0 | N24: =SUMIFS(MOVIMIENTOS!$I:$I,MOVIMIENTOS!$D:$D,"Aporte",MOVIMIENTOS!$E:$E,"Anual",MOVIMIENTOS!$J:$J,$C24,MOVIMIENTOS!$B:$B,">="&DATE(2026,12,1),MOVIMIENTOS!$B:$B,"<"&DATE(2026,13,1)) -> 0 | O24: =SUM(E24:N24) -> 9000 | P24: =SUMIFS(MOVIMIENTOS!$I:$I,MOVIMIENTOS!$D:$D,"Aporte",MOVIMIENTOS!$E:$E,"Extraordinaria",MOVIMIENTOS!$F:$F,P$4,MOVIMIENTOS!$J:$J,$C24) -> 1000 | Q24: =SUMIFS(MOVIMIENTOS!$I:$I,MOVIMIENTOS!$D:$D,"Aporte",MOVIMIENTOS!$E:$E,"Extraordinaria",MOVIMIENTOS!$F:$F,Q$4,MOVIMIENTOS!$J:$J,$C24) -> 2000 | R24: =SUMIFS(MOVIMIENTOS!$I:$I,MOVIMIENTOS!$D:$D,"Aporte",MOVIMIENTOS!$E:$E,"Extraordinaria",MOVIMIENTOS!$F:$F,R$4,MOVIMIENTOS!$J:$J,$C24) -> 2000 | S24: =SUMIFS(MOVIMIENTOS!$I:$I,MOVIMIENTOS!$D:$D,"Aporte",MOVIMIENTOS!$E:$E,"Extraordinaria",MOVIMIENTOS!$F:$F,S$4,MOVIMIENTOS!$J:$J,$C24) -> 0 | T24: =SUMIFS(MOVIMIENTOS!$I:$I,MOVIMIENTOS!$D:$D,"Aporte",MOVIMIENTOS!$E:$E,"Extraordinaria",MOVIMIENTOS!$F:$F,T$4,MOVIMIENTOS!$J:$J,$C24) -> 0 | U24: =SUMIFS(MOVIMIENTOS!$I:$I,MOVIMIENTOS!$D:$D,"Aporte",MOVIMIENTOS!$E:$E,"Extraordinaria",MOVIMIENTOS!$F:$F,U$4,MOVIMIENTOS!$J:$J,$C24) -> 0 | V24: =SUMIFS(MOVIMIENTOS!$I:$I,MOVIMIENTOS!$D:$D,"Aporte",MOVIMIENTOS!$E:$E,"Extraordinaria",MOVIMIENTOS!$F:$F,V$4,MOVIMIENTOS!$J:$J,$C24) -> 0 | W24: =SUM(P24:V24) -> 5000 | X24: =O24+W24 -> 14000
A25: 21 | B25: 25280245-2 | C25: MUÑOZ VALENZUELA BENJAMÍN IGNACIO | D25: NATALIA VALENZUELA | E25: =SUMIFS(MOVIMIENTOS!$I:$I,MOVIMIENTOS!$D:$D,"Aporte",MOVIMIENTOS!$E:$E,"Anual",MOVIMIENTOS!$J:$J,$C25,MOVIMIENTOS!$B:$B,">="&DATE(2026,3,1),MOVIMIENTOS!$B:$B,"<"&DATE(2026,4,1)) -> 3000 | F25: =SUMIFS(MOVIMIENTOS!$I:$I,MOVIMIENTOS!$D:$D,"Aporte",MOVIMIENTOS!$E:$E,"Anual",MOVIMIENTOS!$J:$J,$C25,MOVIMIENTOS!$B:$B,">="&DATE(2026,4,1),MOVIMIENTOS!$B:$B,"<"&DATE(2026,5,1)) -> 3000 | G25: =SUMIFS(MOVIMIENTOS!$I:$I,MOVIMIENTOS!$D:$D,"Aporte",MOVIMIENTOS!$E:$E,"Anual",MOVIMIENTOS!$J:$J,$C25,MOVIMIENTOS!$B:$B,">="&DATE(2026,5,1),MOVIMIENTOS!$B:$B,"<"&DATE(2026,6,1)) -> 3000 | H25: =SUMIFS(MOVIMIENTOS!$I:$I,MOVIMIENTOS!$D:$D,"Aporte",MOVIMIENTOS!$E:$E,"Anual",MOVIMIENTOS!$J:$J,$C25,MOVIMIENTOS!$B:$B,">="&DATE(2026,6,1),MOVIMIENTOS!$B:$B,"<"&DATE(2026,7,1)) -> 3000 | I25: =SUMIFS(MOVIMIENTOS!$I:$I,MOVIMIENTOS!$D:$D,"Aporte",MOVIMIENTOS!$E:$E,"Anual",MOVIMIENTOS!$J:$J,$C25,MOVIMIENTOS!$B:$B,">="&DATE(2026,7,1),MOVIMIENTOS!$B:$B,"<"&DATE(2026,8,1)) -> 0 | J25: =SUMIFS(MOVIMIENTOS!$I:$I,MOVIMIENTOS!$D:$D,"Aporte",MOVIMIENTOS!$E:$E,"Anual",MOVIMIENTOS!$J:$J,$C25,MOVIMIENTOS!$B:$B,">="&DATE(2026,8,1),MOVIMIENTOS!$B:$B,"<"&DATE(2026,9,1)) -> 0 | K25: =SUMIFS(MOVIMIENTOS!$I:$I,MOVIMIENTOS!$D:$D,"Aporte",MOVIMIENTOS!$E:$E,"Anual",MOVIMIENTOS!$J:$J,$C25,MOVIMIENTOS!$B:$B,">="&DATE(2026,9,1),MOVIMIENTOS!$B:$B,"<"&DATE(2026,10,1)) -> 0 | L25: =SUMIFS(MOVIMIENTOS!$I:$I,MOVIMIENTOS!$D:$D,"Aporte",MOVIMIENTOS!$E:$E,"Anual",MOVIMIENTOS!$J:$J,$C25,MOVIMIENTOS!$B:$B,">="&DATE(2026,10,1),MOVIMIENTOS!$B:$B,"<"&DATE(2026,11,1)) -> 0 | M25: =SUMIFS(MOVIMIENTOS!$I:$I,MOVIMIENTOS!$D:$D,"Aporte",MOVIMIENTOS!$E:$E,"Anual",MOVIMIENTOS!$J:$J,$C25,MOVIMIENTOS!$B:$B,">="&DATE(2026,11,1),MOVIMIENTOS!$B:$B,"<"&DATE(2026,12,1)) -> 0 | N25: =SUMIFS(MOVIMIENTOS!$I:$I,MOVIMIENTOS!$D:$D,"Aporte",MOVIMIENTOS!$E:$E,"Anual",MOVIMIENTOS!$J:$J,$C25,MOVIMIENTOS!$B:$B,">="&DATE(2026,12,1),MOVIMIENTOS!$B:$B,"<"&DATE(2026,13,1)) -> 0 | O25: =SUM(E25:N25) -> 12000 | P25: =SUMIFS(MOVIMIENTOS!$I:$I,MOVIMIENTOS!$D:$D,"Aporte",MOVIMIENTOS!$E:$E,"Extraordinaria",MOVIMIENTOS!$F:$F,P$4,MOVIMIENTOS!$J:$J,$C25) -> 1000 | Q25: =SUMIFS(MOVIMIENTOS!$I:$I,MOVIMIENTOS!$D:$D,"Aporte",MOVIMIENTOS!$E:$E,"Extraordinaria",MOVIMIENTOS!$F:$F,Q$4,MOVIMIENTOS!$J:$J,$C25) -> 2000 | R25: =SUMIFS(MOVIMIENTOS!$I:$I,MOVIMIENTOS!$D:$D,"Aporte",MOVIMIENTOS!$E:$E,"Extraordinaria",MOVIMIENTOS!$F:$F,R$4,MOVIMIENTOS!$J:$J,$C25) -> 2000 | S25: =SUMIFS(MOVIMIENTOS!$I:$I,MOVIMIENTOS!$D:$D,"Aporte",MOVIMIENTOS!$E:$E,"Extraordinaria",MOVIMIENTOS!$F:$F,S$4,MOVIMIENTOS!$J:$J,$C25) -> 0 | T25: =SUMIFS(MOVIMIENTOS!$I:$I,MOVIMIENTOS!$D:$D,"Aporte",MOVIMIENTOS!$E:$E,"Extraordinaria",MOVIMIENTOS!$F:$F,T$4,MOVIMIENTOS!$J:$J,$C25) -> 0 | U25: =SUMIFS(MOVIMIENTOS!$I:$I,MOVIMIENTOS!$D:$D,"Aporte",MOVIMIENTOS!$E:$E,"Extraordinaria",MOVIMIENTOS!$F:$F,U$4,MOVIMIENTOS!$J:$J,$C25) -> 0 | V25: =SUMIFS(MOVIMIENTOS!$I:$I,MOVIMIENTOS!$D:$D,"Aporte",MOVIMIENTOS!$E:$E,"Extraordinaria",MOVIMIENTOS!$F:$F,V$4,MOVIMIENTOS!$J:$J,$C25) -> 0 | W25: =SUM(P25:V25) -> 5000 | X25: =O25+W25 -> 17000
A26: 22 | B26: 25312924-7 | C26: ORELLANA IBARRA PABLO ALFONSO | E26: =SUMIFS(MOVIMIENTOS!$I:$I,MOVIMIENTOS!$D:$D,"Aporte",MOVIMIENTOS!$E:$E,"Anual",MOVIMIENTOS!$J:$J,$C26,MOVIMIENTOS!$B:$B,">="&DATE(2026,3,1),MOVIMIENTOS!$B:$B,"<"&DATE(2026,4,1)) -> 0 | F26: =SUMIFS(MOVIMIENTOS!$I:$I,MOVIMIENTOS!$D:$D,"Aporte",MOVIMIENTOS!$E:$E,"Anual",MOVIMIENTOS!$J:$J,$C26,MOVIMIENTOS!$B:$B,">="&DATE(2026,4,1),MOVIMIENTOS!$B:$B,"<"&DATE(2026,5,1)) -> 0 | G26: =SUMIFS(MOVIMIENTOS!$I:$I,MOVIMIENTOS!$D:$D,"Aporte",MOVIMIENTOS!$E:$E,"Anual",MOVIMIENTOS!$J:$J,$C26,MOVIMIENTOS!$B:$B,">="&DATE(2026,5,1),MOVIMIENTOS!$B:$B,"<"&DATE(2026,6,1)) -> 0 | H26: =SUMIFS(MOVIMIENTOS!$I:$I,MOVIMIENTOS!$D:$D,"Aporte",MOVIMIENTOS!$E:$E,"Anual",MOVIMIENTOS!$J:$J,$C26,MOVIMIENTOS!$B:$B,">="&DATE(2026,6,1),MOVIMIENTOS!$B:$B,"<"&DATE(2026,7,1)) -> 0 | I26: =SUMIFS(MOVIMIENTOS!$I:$I,MOVIMIENTOS!$D:$D,"Aporte",MOVIMIENTOS!$E:$E,"Anual",MOVIMIENTOS!$J:$J,$C26,MOVIMIENTOS!$B:$B,">="&DATE(2026,7,1),MOVIMIENTOS!$B:$B,"<"&DATE(2026,8,1)) -> 0 | J26: =SUMIFS(MOVIMIENTOS!$I:$I,MOVIMIENTOS!$D:$D,"Aporte",MOVIMIENTOS!$E:$E,"Anual",MOVIMIENTOS!$J:$J,$C26,MOVIMIENTOS!$B:$B,">="&DATE(2026,8,1),MOVIMIENTOS!$B:$B,"<"&DATE(2026,9,1)) -> 0 | K26: =SUMIFS(MOVIMIENTOS!$I:$I,MOVIMIENTOS!$D:$D,"Aporte",MOVIMIENTOS!$E:$E,"Anual",MOVIMIENTOS!$J:$J,$C26,MOVIMIENTOS!$B:$B,">="&DATE(2026,9,1),MOVIMIENTOS!$B:$B,"<"&DATE(2026,10,1)) -> 0 | L26: =SUMIFS(MOVIMIENTOS!$I:$I,MOVIMIENTOS!$D:$D,"Aporte",MOVIMIENTOS!$E:$E,"Anual",MOVIMIENTOS!$J:$J,$C26,MOVIMIENTOS!$B:$B,">="&DATE(2026,10,1),MOVIMIENTOS!$B:$B,"<"&DATE(2026,11,1)) -> 0 | M26: =SUMIFS(MOVIMIENTOS!$I:$I,MOVIMIENTOS!$D:$D,"Aporte",MOVIMIENTOS!$E:$E,"Anual",MOVIMIENTOS!$J:$J,$C26,MOVIMIENTOS!$B:$B,">="&DATE(2026,11,1),MOVIMIENTOS!$B:$B,"<"&DATE(2026,12,1)) -> 0 | N26: =SUMIFS(MOVIMIENTOS!$I:$I,MOVIMIENTOS!$D:$D,"Aporte",MOVIMIENTOS!$E:$E,"Anual",MOVIMIENTOS!$J:$J,$C26,MOVIMIENTOS!$B:$B,">="&DATE(2026,12,1),MOVIMIENTOS!$B:$B,"<"&DATE(2026,13,1)) -> 0 | O26: =SUM(E26:N26) -> 0 | P26: =SUMIFS(MOVIMIENTOS!$I:$I,MOVIMIENTOS!$D:$D,"Aporte",MOVIMIENTOS!$E:$E,"Extraordinaria",MOVIMIENTOS!$F:$F,P$4,MOVIMIENTOS!$J:$J,$C26) -> 0 | Q26: =SUMIFS(MOVIMIENTOS!$I:$I,MOVIMIENTOS!$D:$D,"Aporte",MOVIMIENTOS!$E:$E,"Extraordinaria",MOVIMIENTOS!$F:$F,Q$4,MOVIMIENTOS!$J:$J,$C26) -> 0 | R26: =SUMIFS(MOVIMIENTOS!$I:$I,MOVIMIENTOS!$D:$D,"Aporte",MOVIMIENTOS!$E:$E,"Extraordinaria",MOVIMIENTOS!$F:$F,R$4,MOVIMIENTOS!$J:$J,$C26) -> 0 | S26: =SUMIFS(MOVIMIENTOS!$I:$I,MOVIMIENTOS!$D:$D,"Aporte",MOVIMIENTOS!$E:$E,"Extraordinaria",MOVIMIENTOS!$F:$F,S$4,MOVIMIENTOS!$J:$J,$C26) -> 0 | T26: =SUMIFS(MOVIMIENTOS!$I:$I,MOVIMIENTOS!$D:$D,"Aporte",MOVIMIENTOS!$E:$E,"Extraordinaria",MOVIMIENTOS!$F:$F,T$4,MOVIMIENTOS!$J:$J,$C26) -> 0 | U26: =SUMIFS(MOVIMIENTOS!$I:$I,MOVIMIENTOS!$D:$D,"Aporte",MOVIMIENTOS!$E:$E,"Extraordinaria",MOVIMIENTOS!$F:$F,U$4,MOVIMIENTOS!$J:$J,$C26) -> 0 | V26: =SUMIFS(MOVIMIENTOS!$I:$I,MOVIMIENTOS!$D:$D,"Aporte",MOVIMIENTOS!$E:$E,"Extraordinaria",MOVIMIENTOS!$F:$F,V$4,MOVIMIENTOS!$J:$J,$C26) -> 0 | W26: =SUM(P26:V26) -> 0 | X26: =O26+W26 -> 0
A27: 23 | B27: 25006274-5 | C27: OYARCE CABELLO MONSERRAT ANTONELLA | D27: MONSERRAT OLLARCE | E27: =SUMIFS(MOVIMIENTOS!$I:$I,MOVIMIENTOS!$D:$D,"Aporte",MOVIMIENTOS!$E:$E,"Anual",MOVIMIENTOS!$J:$J,$C27,MOVIMIENTOS!$B:$B,">="&DATE(2026,3,1),MOVIMIENTOS!$B:$B,"<"&DATE(2026,4,1)) -> 3000 | F27: =SUMIFS(MOVIMIENTOS!$I:$I,MOVIMIENTOS!$D:$D,"Aporte",MOVIMIENTOS!$E:$E,"Anual",MOVIMIENTOS!$J:$J,$C27,MOVIMIENTOS!$B:$B,">="&DATE(2026,4,1),MOVIMIENTOS!$B:$B,"<"&DATE(2026,5,1)) -> 0 | G27: =SUMIFS(MOVIMIENTOS!$I:$I,MOVIMIENTOS!$D:$D,"Aporte",MOVIMIENTOS!$E:$E,"Anual",MOVIMIENTOS!$J:$J,$C27,MOVIMIENTOS!$B:$B,">="&DATE(2026,5,1),MOVIMIENTOS!$B:$B,"<"&DATE(2026,6,1)) -> 0 | H27: =SUMIFS(MOVIMIENTOS!$I:$I,MOVIMIENTOS!$D:$D,"Aporte",MOVIMIENTOS!$E:$E,"Anual",MOVIMIENTOS!$J:$J,$C27,MOVIMIENTOS!$B:$B,">="&DATE(2026,6,1),MOVIMIENTOS!$B:$B,"<"&DATE(2026,7,1)) -> 0 | I27: =SUMIFS(MOVIMIENTOS!$I:$I,MOVIMIENTOS!$D:$D,"Aporte",MOVIMIENTOS!$E:$E,"Anual",MOVIMIENTOS!$J:$J,$C27,MOVIMIENTOS!$B:$B,">="&DATE(2026,7,1),MOVIMIENTOS!$B:$B,"<"&DATE(2026,8,1)) -> 0 | J27: =SUMIFS(MOVIMIENTOS!$I:$I,MOVIMIENTOS!$D:$D,"Aporte",MOVIMIENTOS!$E:$E,"Anual",MOVIMIENTOS!$J:$J,$C27,MOVIMIENTOS!$B:$B,">="&DATE(2026,8,1),MOVIMIENTOS!$B:$B,"<"&DATE(2026,9,1)) -> 0 | K27: =SUMIFS(MOVIMIENTOS!$I:$I,MOVIMIENTOS!$D:$D,"Aporte",MOVIMIENTOS!$E:$E,"Anual",MOVIMIENTOS!$J:$J,$C27,MOVIMIENTOS!$B:$B,">="&DATE(2026,9,1),MOVIMIENTOS!$B:$B,"<"&DATE(2026,10,1)) -> 0 | L27: =SUMIFS(MOVIMIENTOS!$I:$I,MOVIMIENTOS!$D:$D,"Aporte",MOVIMIENTOS!$E:$E,"Anual",MOVIMIENTOS!$J:$J,$C27,MOVIMIENTOS!$B:$B,">="&DATE(2026,10,1),MOVIMIENTOS!$B:$B,"<"&DATE(2026,11,1)) -> 0 | M27: =SUMIFS(MOVIMIENTOS!$I:$I,MOVIMIENTOS!$D:$D,"Aporte",MOVIMIENTOS!$E:$E,"Anual",MOVIMIENTOS!$J:$J,$C27,MOVIMIENTOS!$B:$B,">="&DATE(2026,11,1),MOVIMIENTOS!$B:$B,"<"&DATE(2026,12,1)) -> 0 | N27: =SUMIFS(MOVIMIENTOS!$I:$I,MOVIMIENTOS!$D:$D,"Aporte",MOVIMIENTOS!$E:$E,"Anual",MOVIMIENTOS!$J:$J,$C27,MOVIMIENTOS!$B:$B,">="&DATE(2026,12,1),MOVIMIENTOS!$B:$B,"<"&DATE(2026,13,1)) -> 0 | O27: =SUM(E27:N27) -> 3000 | P27: =SUMIFS(MOVIMIENTOS!$I:$I,MOVIMIENTOS!$D:$D,"Aporte",MOVIMIENTOS!$E:$E,"Extraordinaria",MOVIMIENTOS!$F:$F,P$4,MOVIMIENTOS!$J:$J,$C27) -> 1000 | Q27: =SUMIFS(MOVIMIENTOS!$I:$I,MOVIMIENTOS!$D:$D,"Aporte",MOVIMIENTOS!$E:$E,"Extraordinaria",MOVIMIENTOS!$F:$F,Q$4,MOVIMIENTOS!$J:$J,$C27) -> 2000 | R27: =SUMIFS(MOVIMIENTOS!$I:$I,MOVIMIENTOS!$D:$D,"Aporte",MOVIMIENTOS!$E:$E,"Extraordinaria",MOVIMIENTOS!$F:$F,R$4,MOVIMIENTOS!$J:$J,$C27) -> 2000 | S27: =SUMIFS(MOVIMIENTOS!$I:$I,MOVIMIENTOS!$D:$D,"Aporte",MOVIMIENTOS!$E:$E,"Extraordinaria",MOVIMIENTOS!$F:$F,S$4,MOVIMIENTOS!$J:$J,$C27) -> 0 | T27: =SUMIFS(MOVIMIENTOS!$I:$I,MOVIMIENTOS!$D:$D,"Aporte",MOVIMIENTOS!$E:$E,"Extraordinaria",MOVIMIENTOS!$F:$F,T$4,MOVIMIENTOS!$J:$J,$C27) -> 0 | U27: =SUMIFS(MOVIMIENTOS!$I:$I,MOVIMIENTOS!$D:$D,"Aporte",MOVIMIENTOS!$E:$E,"Extraordinaria",MOVIMIENTOS!$F:$F,U$4,MOVIMIENTOS!$J:$J,$C27) -> 1000 | V27: =SUMIFS(MOVIMIENTOS!$I:$I,MOVIMIENTOS!$D:$D,"Aporte",MOVIMIENTOS!$E:$E,"Extraordinaria",MOVIMIENTOS!$F:$F,V$4,MOVIMIENTOS!$J:$J,$C27) -> 0 | W27: =SUM(P27:V27) -> 6000 | X27: =O27+W27 -> 9000
A28: 24 | B28: 24758384-4 | C28: PÉREZ HIGUERAS ANTONELLA NICOLE | D28: NELLY HIGUERAS | E28: =SUMIFS(MOVIMIENTOS!$I:$I,MOVIMIENTOS!$D:$D,"Aporte",MOVIMIENTOS!$E:$E,"Anual",MOVIMIENTOS!$J:$J,$C28,MOVIMIENTOS!$B:$B,">="&DATE(2026,3,1),MOVIMIENTOS!$B:$B,"<"&DATE(2026,4,1)) -> 3000 | F28: =SUMIFS(MOVIMIENTOS!$I:$I,MOVIMIENTOS!$D:$D,"Aporte",MOVIMIENTOS!$E:$E,"Anual",MOVIMIENTOS!$J:$J,$C28,MOVIMIENTOS!$B:$B,">="&DATE(2026,4,1),MOVIMIENTOS!$B:$B,"<"&DATE(2026,5,1)) -> 0 | G28: =SUMIFS(MOVIMIENTOS!$I:$I,MOVIMIENTOS!$D:$D,"Aporte",MOVIMIENTOS!$E:$E,"Anual",MOVIMIENTOS!$J:$J,$C28,MOVIMIENTOS!$B:$B,">="&DATE(2026,5,1),MOVIMIENTOS!$B:$B,"<"&DATE(2026,6,1)) -> 0 | H28: =SUMIFS(MOVIMIENTOS!$I:$I,MOVIMIENTOS!$D:$D,"Aporte",MOVIMIENTOS!$E:$E,"Anual",MOVIMIENTOS!$J:$J,$C28,MOVIMIENTOS!$B:$B,">="&DATE(2026,6,1),MOVIMIENTOS!$B:$B,"<"&DATE(2026,7,1)) -> 0 | I28: =SUMIFS(MOVIMIENTOS!$I:$I,MOVIMIENTOS!$D:$D,"Aporte",MOVIMIENTOS!$E:$E,"Anual",MOVIMIENTOS!$J:$J,$C28,MOVIMIENTOS!$B:$B,">="&DATE(2026,7,1),MOVIMIENTOS!$B:$B,"<"&DATE(2026,8,1)) -> 0 | J28: =SUMIFS(MOVIMIENTOS!$I:$I,MOVIMIENTOS!$D:$D,"Aporte",MOVIMIENTOS!$E:$E,"Anual",MOVIMIENTOS!$J:$J,$C28,MOVIMIENTOS!$B:$B,">="&DATE(2026,8,1),MOVIMIENTOS!$B:$B,"<"&DATE(2026,9,1)) -> 0 | K28: =SUMIFS(MOVIMIENTOS!$I:$I,MOVIMIENTOS!$D:$D,"Aporte",MOVIMIENTOS!$E:$E,"Anual",MOVIMIENTOS!$J:$J,$C28,MOVIMIENTOS!$B:$B,">="&DATE(2026,9,1),MOVIMIENTOS!$B:$B,"<"&DATE(2026,10,1)) -> 0 | L28: =SUMIFS(MOVIMIENTOS!$I:$I,MOVIMIENTOS!$D:$D,"Aporte",MOVIMIENTOS!$E:$E,"Anual",MOVIMIENTOS!$J:$J,$C28,MOVIMIENTOS!$B:$B,">="&DATE(2026,10,1),MOVIMIENTOS!$B:$B,"<"&DATE(2026,11,1)) -> 0 | M28: =SUMIFS(MOVIMIENTOS!$I:$I,MOVIMIENTOS!$D:$D,"Aporte",MOVIMIENTOS!$E:$E,"Anual",MOVIMIENTOS!$J:$J,$C28,MOVIMIENTOS!$B:$B,">="&DATE(2026,11,1),MOVIMIENTOS!$B:$B,"<"&DATE(2026,12,1)) -> 0 | N28: =SUMIFS(MOVIMIENTOS!$I:$I,MOVIMIENTOS!$D:$D,"Aporte",MOVIMIENTOS!$E:$E,"Anual",MOVIMIENTOS!$J:$J,$C28,MOVIMIENTOS!$B:$B,">="&DATE(2026,12,1),MOVIMIENTOS!$B:$B,"<"&DATE(2026,13,1)) -> 0 | O28: =SUM(E28:N28) -> 3000 | P28: =SUMIFS(MOVIMIENTOS!$I:$I,MOVIMIENTOS!$D:$D,"Aporte",MOVIMIENTOS!$E:$E,"Extraordinaria",MOVIMIENTOS!$F:$F,P$4,MOVIMIENTOS!$J:$J,$C28) -> 1000 | Q28: =SUMIFS(MOVIMIENTOS!$I:$I,MOVIMIENTOS!$D:$D,"Aporte",MOVIMIENTOS!$E:$E,"Extraordinaria",MOVIMIENTOS!$F:$F,Q$4,MOVIMIENTOS!$J:$J,$C28) -> 2000 | R28: =SUMIFS(MOVIMIENTOS!$I:$I,MOVIMIENTOS!$D:$D,"Aporte",MOVIMIENTOS!$E:$E,"Extraordinaria",MOVIMIENTOS!$F:$F,R$4,MOVIMIENTOS!$J:$J,$C28) -> 2000 | S28: =SUMIFS(MOVIMIENTOS!$I:$I,MOVIMIENTOS!$D:$D,"Aporte",MOVIMIENTOS!$E:$E,"Extraordinaria",MOVIMIENTOS!$F:$F,S$4,MOVIMIENTOS!$J:$J,$C28) -> 0 | T28: =SUMIFS(MOVIMIENTOS!$I:$I,MOVIMIENTOS!$D:$D,"Aporte",MOVIMIENTOS!$E:$E,"Extraordinaria",MOVIMIENTOS!$F:$F,T$4,MOVIMIENTOS!$J:$J,$C28) -> 0 | U28: =SUMIFS(MOVIMIENTOS!$I:$I,MOVIMIENTOS!$D:$D,"Aporte",MOVIMIENTOS!$E:$E,"Extraordinaria",MOVIMIENTOS!$F:$F,U$4,MOVIMIENTOS!$J:$J,$C28) -> 1000 | V28: =SUMIFS(MOVIMIENTOS!$I:$I,MOVIMIENTOS!$D:$D,"Aporte",MOVIMIENTOS!$E:$E,"Extraordinaria",MOVIMIENTOS!$F:$F,V$4,MOVIMIENTOS!$J:$J,$C28) -> 0 | W28: =SUM(P28:V28) -> 6000 | X28: =O28+W28 -> 9000
A29: 25 | B29: 25042952-5 | C29: RAMÍREZ MUÑOZ ANHAI ESPERANZA | D29: ROSA LLANOS | E29: =SUMIFS(MOVIMIENTOS!$I:$I,MOVIMIENTOS!$D:$D,"Aporte",MOVIMIENTOS!$E:$E,"Anual",MOVIMIENTOS!$J:$J,$C29,MOVIMIENTOS!$B:$B,">="&DATE(2026,3,1),MOVIMIENTOS!$B:$B,"<"&DATE(2026,4,1)) -> 3000 | F29: =SUMIFS(MOVIMIENTOS!$I:$I,MOVIMIENTOS!$D:$D,"Aporte",MOVIMIENTOS!$E:$E,"Anual",MOVIMIENTOS!$J:$J,$C29,MOVIMIENTOS!$B:$B,">="&DATE(2026,4,1),MOVIMIENTOS!$B:$B,"<"&DATE(2026,5,1)) -> 3000 | G29: =SUMIFS(MOVIMIENTOS!$I:$I,MOVIMIENTOS!$D:$D,"Aporte",MOVIMIENTOS!$E:$E,"Anual",MOVIMIENTOS!$J:$J,$C29,MOVIMIENTOS!$B:$B,">="&DATE(2026,5,1),MOVIMIENTOS!$B:$B,"<"&DATE(2026,6,1)) -> 3000 | H29: =SUMIFS(MOVIMIENTOS!$I:$I,MOVIMIENTOS!$D:$D,"Aporte",MOVIMIENTOS!$E:$E,"Anual",MOVIMIENTOS!$J:$J,$C29,MOVIMIENTOS!$B:$B,">="&DATE(2026,6,1),MOVIMIENTOS!$B:$B,"<"&DATE(2026,7,1)) -> 3000 | I29: =SUMIFS(MOVIMIENTOS!$I:$I,MOVIMIENTOS!$D:$D,"Aporte",MOVIMIENTOS!$E:$E,"Anual",MOVIMIENTOS!$J:$J,$C29,MOVIMIENTOS!$B:$B,">="&DATE(2026,7,1),MOVIMIENTOS!$B:$B,"<"&DATE(2026,8,1)) -> 3000 | J29: =SUMIFS(MOVIMIENTOS!$I:$I,MOVIMIENTOS!$D:$D,"Aporte",MOVIMIENTOS!$E:$E,"Anual",MOVIMIENTOS!$J:$J,$C29,MOVIMIENTOS!$B:$B,">="&DATE(2026,8,1),MOVIMIENTOS!$B:$B,"<"&DATE(2026,9,1)) -> 0 | K29: =SUMIFS(MOVIMIENTOS!$I:$I,MOVIMIENTOS!$D:$D,"Aporte",MOVIMIENTOS!$E:$E,"Anual",MOVIMIENTOS!$J:$J,$C29,MOVIMIENTOS!$B:$B,">="&DATE(2026,9,1),MOVIMIENTOS!$B:$B,"<"&DATE(2026,10,1)) -> 0 | L29: =SUMIFS(MOVIMIENTOS!$I:$I,MOVIMIENTOS!$D:$D,"Aporte",MOVIMIENTOS!$E:$E,"Anual",MOVIMIENTOS!$J:$J,$C29,MOVIMIENTOS!$B:$B,">="&DATE(2026,10,1),MOVIMIENTOS!$B:$B,"<"&DATE(2026,11,1)) -> 0 | M29: =SUMIFS(MOVIMIENTOS!$I:$I,MOVIMIENTOS!$D:$D,"Aporte",MOVIMIENTOS!$E:$E,"Anual",MOVIMIENTOS!$J:$J,$C29,MOVIMIENTOS!$B:$B,">="&DATE(2026,11,1),MOVIMIENTOS!$B:$B,"<"&DATE(2026,12,1)) -> 0 | N29: =SUMIFS(MOVIMIENTOS!$I:$I,MOVIMIENTOS!$D:$D,"Aporte",MOVIMIENTOS!$E:$E,"Anual",MOVIMIENTOS!$J:$J,$C29,MOVIMIENTOS!$B:$B,">="&DATE(2026,12,1),MOVIMIENTOS!$B:$B,"<"&DATE(2026,13,1)) -> 0 | O29: =SUM(E29:N29) -> 15000 | P29: =SUMIFS(MOVIMIENTOS!$I:$I,MOVIMIENTOS!$D:$D,"Aporte",MOVIMIENTOS!$E:$E,"Extraordinaria",MOVIMIENTOS!$F:$F,P$4,MOVIMIENTOS!$J:$J,$C29) -> 1000 | Q29: =SUMIFS(MOVIMIENTOS!$I:$I,MOVIMIENTOS!$D:$D,"Aporte",MOVIMIENTOS!$E:$E,"Extraordinaria",MOVIMIENTOS!$F:$F,Q$4,MOVIMIENTOS!$J:$J,$C29) -> 2000 | R29: =SUMIFS(MOVIMIENTOS!$I:$I,MOVIMIENTOS!$D:$D,"Aporte",MOVIMIENTOS!$E:$E,"Extraordinaria",MOVIMIENTOS!$F:$F,R$4,MOVIMIENTOS!$J:$J,$C29) -> 2000 | S29: =SUMIFS(MOVIMIENTOS!$I:$I,MOVIMIENTOS!$D:$D,"Aporte",MOVIMIENTOS!$E:$E,"Extraordinaria",MOVIMIENTOS!$F:$F,S$4,MOVIMIENTOS!$J:$J,$C29) -> 0 | T29: =SUMIFS(MOVIMIENTOS!$I:$I,MOVIMIENTOS!$D:$D,"Aporte",MOVIMIENTOS!$E:$E,"Extraordinaria",MOVIMIENTOS!$F:$F,T$4,MOVIMIENTOS!$J:$J,$C29) -> 0 | U29: =SUMIFS(MOVIMIENTOS!$I:$I,MOVIMIENTOS!$D:$D,"Aporte",MOVIMIENTOS!$E:$E,"Extraordinaria",MOVIMIENTOS!$F:$F,U$4,MOVIMIENTOS!$J:$J,$C29) -> 1000 | V29: =SUMIFS(MOVIMIENTOS!$I:$I,MOVIMIENTOS!$D:$D,"Aporte",MOVIMIENTOS!$E:$E,"Extraordinaria",MOVIMIENTOS!$F:$F,V$4,MOVIMIENTOS!$J:$J,$C29) -> 0 | W29: =SUM(P29:V29) -> 6000 | X29: =O29+W29 -> 21000
A30: 26 | B30: 24911564-9 | C30: REYES RODRÍGUEZ FERNANDA CATALINA | D30: YASNA RODRIGUEZ | E30: =SUMIFS(MOVIMIENTOS!$I:$I,MOVIMIENTOS!$D:$D,"Aporte",MOVIMIENTOS!$E:$E,"Anual",MOVIMIENTOS!$J:$J,$C30,MOVIMIENTOS!$B:$B,">="&DATE(2026,3,1),MOVIMIENTOS!$B:$B,"<"&DATE(2026,4,1)) -> 3000 | F30: =SUMIFS(MOVIMIENTOS!$I:$I,MOVIMIENTOS!$D:$D,"Aporte",MOVIMIENTOS!$E:$E,"Anual",MOVIMIENTOS!$J:$J,$C30,MOVIMIENTOS!$B:$B,">="&DATE(2026,4,1),MOVIMIENTOS!$B:$B,"<"&DATE(2026,5,1)) -> 3000 | G30: =SUMIFS(MOVIMIENTOS!$I:$I,MOVIMIENTOS!$D:$D,"Aporte",MOVIMIENTOS!$E:$E,"Anual",MOVIMIENTOS!$J:$J,$C30,MOVIMIENTOS!$B:$B,">="&DATE(2026,5,1),MOVIMIENTOS!$B:$B,"<"&DATE(2026,6,1)) -> 3000 | H30: =SUMIFS(MOVIMIENTOS!$I:$I,MOVIMIENTOS!$D:$D,"Aporte",MOVIMIENTOS!$E:$E,"Anual",MOVIMIENTOS!$J:$J,$C30,MOVIMIENTOS!$B:$B,">="&DATE(2026,6,1),MOVIMIENTOS!$B:$B,"<"&DATE(2026,7,1)) -> 3000 | I30: =SUMIFS(MOVIMIENTOS!$I:$I,MOVIMIENTOS!$D:$D,"Aporte",MOVIMIENTOS!$E:$E,"Anual",MOVIMIENTOS!$J:$J,$C30,MOVIMIENTOS!$B:$B,">="&DATE(2026,7,1),MOVIMIENTOS!$B:$B,"<"&DATE(2026,8,1)) -> 3000 | J30: =SUMIFS(MOVIMIENTOS!$I:$I,MOVIMIENTOS!$D:$D,"Aporte",MOVIMIENTOS!$E:$E,"Anual",MOVIMIENTOS!$J:$J,$C30,MOVIMIENTOS!$B:$B,">="&DATE(2026,8,1),MOVIMIENTOS!$B:$B,"<"&DATE(2026,9,1)) -> 3000 | K30: =SUMIFS(MOVIMIENTOS!$I:$I,MOVIMIENTOS!$D:$D,"Aporte",MOVIMIENTOS!$E:$E,"Anual",MOVIMIENTOS!$J:$J,$C30,MOVIMIENTOS!$B:$B,">="&DATE(2026,9,1),MOVIMIENTOS!$B:$B,"<"&DATE(2026,10,1)) -> 0 | L30: =SUMIFS(MOVIMIENTOS!$I:$I,MOVIMIENTOS!$D:$D,"Aporte",MOVIMIENTOS!$E:$E,"Anual",MOVIMIENTOS!$J:$J,$C30,MOVIMIENTOS!$B:$B,">="&DATE(2026,10,1),MOVIMIENTOS!$B:$B,"<"&DATE(2026,11,1)) -> 0 | M30: =SUMIFS(MOVIMIENTOS!$I:$I,MOVIMIENTOS!$D:$D,"Aporte",MOVIMIENTOS!$E:$E,"Anual",MOVIMIENTOS!$J:$J,$C30,MOVIMIENTOS!$B:$B,">="&DATE(2026,11,1),MOVIMIENTOS!$B:$B,"<"&DATE(2026,12,1)) -> 0 | N30: =SUMIFS(MOVIMIENTOS!$I:$I,MOVIMIENTOS!$D:$D,"Aporte",MOVIMIENTOS!$E:$E,"Anual",MOVIMIENTOS!$J:$J,$C30,MOVIMIENTOS!$B:$B,">="&DATE(2026,12,1),MOVIMIENTOS!$B:$B,"<"&DATE(2026,13,1)) -> 0 | O30: =SUM(E30:N30) -> 18000 | P30: =SUMIFS(MOVIMIENTOS!$I:$I,MOVIMIENTOS!$D:$D,"Aporte",MOVIMIENTOS!$E:$E,"Extraordinaria",MOVIMIENTOS!$F:$F,P$4,MOVIMIENTOS!$J:$J,$C30) -> 1000 | Q30: =SUMIFS(MOVIMIENTOS!$I:$I,MOVIMIENTOS!$D:$D,"Aporte",MOVIMIENTOS!$E:$E,"Extraordinaria",MOVIMIENTOS!$F:$F,Q$4,MOVIMIENTOS!$J:$J,$C30) -> 2000 | R30: =SUMIFS(MOVIMIENTOS!$I:$I,MOVIMIENTOS!$D:$D,"Aporte",MOVIMIENTOS!$E:$E,"Extraordinaria",MOVIMIENTOS!$F:$F,R$4,MOVIMIENTOS!$J:$J,$C30) -> 0 | S30: =SUMIFS(MOVIMIENTOS!$I:$I,MOVIMIENTOS!$D:$D,"Aporte",MOVIMIENTOS!$E:$E,"Extraordinaria",MOVIMIENTOS!$F:$F,S$4,MOVIMIENTOS!$J:$J,$C30) -> 0 | T30: =SUMIFS(MOVIMIENTOS!$I:$I,MOVIMIENTOS!$D:$D,"Aporte",MOVIMIENTOS!$E:$E,"Extraordinaria",MOVIMIENTOS!$F:$F,T$4,MOVIMIENTOS!$J:$J,$C30) -> 0 | U30: =SUMIFS(MOVIMIENTOS!$I:$I,MOVIMIENTOS!$D:$D,"Aporte",MOVIMIENTOS!$E:$E,"Extraordinaria",MOVIMIENTOS!$F:$F,U$4,MOVIMIENTOS!$J:$J,$C30) -> 0 | V30: =SUMIFS(MOVIMIENTOS!$I:$I,MOVIMIENTOS!$D:$D,"Aporte",MOVIMIENTOS!$E:$E,"Extraordinaria",MOVIMIENTOS!$F:$F,V$4,MOVIMIENTOS!$J:$J,$C30) -> 0 | W30: =SUM(P30:V30) -> 3000 | X30: =O30+W30 -> 21000
A31: 27 | B31: 25255361-0 | C31: RIVERA AVENDAÑO BERTA AMPARO | D31: BLANCA AVENDAÑO | E31: =SUMIFS(MOVIMIENTOS!$I:$I,MOVIMIENTOS!$D:$D,"Aporte",MOVIMIENTOS!$E:$E,"Anual",MOVIMIENTOS!$J:$J,$C31,MOVIMIENTOS!$B:$B,">="&DATE(2026,3,1),MOVIMIENTOS!$B:$B,"<"&DATE(2026,4,1)) -> 3000 | F31: =SUMIFS(MOVIMIENTOS!$I:$I,MOVIMIENTOS!$D:$D,"Aporte",MOVIMIENTOS!$E:$E,"Anual",MOVIMIENTOS!$J:$J,$C31,MOVIMIENTOS!$B:$B,">="&DATE(2026,4,1),MOVIMIENTOS!$B:$B,"<"&DATE(2026,5,1)) -> 3000 | G31: =SUMIFS(MOVIMIENTOS!$I:$I,MOVIMIENTOS!$D:$D,"Aporte",MOVIMIENTOS!$E:$E,"Anual",MOVIMIENTOS!$J:$J,$C31,MOVIMIENTOS!$B:$B,">="&DATE(2026,5,1),MOVIMIENTOS!$B:$B,"<"&DATE(2026,6,1)) -> 3000 | H31: =SUMIFS(MOVIMIENTOS!$I:$I,MOVIMIENTOS!$D:$D,"Aporte",MOVIMIENTOS!$E:$E,"Anual",MOVIMIENTOS!$J:$J,$C31,MOVIMIENTOS!$B:$B,">="&DATE(2026,6,1),MOVIMIENTOS!$B:$B,"<"&DATE(2026,7,1)) -> 3000 | I31: =SUMIFS(MOVIMIENTOS!$I:$I,MOVIMIENTOS!$D:$D,"Aporte",MOVIMIENTOS!$E:$E,"Anual",MOVIMIENTOS!$J:$J,$C31,MOVIMIENTOS!$B:$B,">="&DATE(2026,7,1),MOVIMIENTOS!$B:$B,"<"&DATE(2026,8,1)) -> 3000 | J31: =SUMIFS(MOVIMIENTOS!$I:$I,MOVIMIENTOS!$D:$D,"Aporte",MOVIMIENTOS!$E:$E,"Anual",MOVIMIENTOS!$J:$J,$C31,MOVIMIENTOS!$B:$B,">="&DATE(2026,8,1),MOVIMIENTOS!$B:$B,"<"&DATE(2026,9,1)) -> 3000 | K31: =SUMIFS(MOVIMIENTOS!$I:$I,MOVIMIENTOS!$D:$D,"Aporte",MOVIMIENTOS!$E:$E,"Anual",MOVIMIENTOS!$J:$J,$C31,MOVIMIENTOS!$B:$B,">="&DATE(2026,9,1),MOVIMIENTOS!$B:$B,"<"&DATE(2026,10,1)) -> 3000 | L31: =SUMIFS(MOVIMIENTOS!$I:$I,MOVIMIENTOS!$D:$D,"Aporte",MOVIMIENTOS!$E:$E,"Anual",MOVIMIENTOS!$J:$J,$C31,MOVIMIENTOS!$B:$B,">="&DATE(2026,10,1),MOVIMIENTOS!$B:$B,"<"&DATE(2026,11,1)) -> 3000 | M31: =SUMIFS(MOVIMIENTOS!$I:$I,MOVIMIENTOS!$D:$D,"Aporte",MOVIMIENTOS!$E:$E,"Anual",MOVIMIENTOS!$J:$J,$C31,MOVIMIENTOS!$B:$B,">="&DATE(2026,11,1),MOVIMIENTOS!$B:$B,"<"&DATE(2026,12,1)) -> 3000 | N31: =SUMIFS(MOVIMIENTOS!$I:$I,MOVIMIENTOS!$D:$D,"Aporte",MOVIMIENTOS!$E:$E,"Anual",MOVIMIENTOS!$J:$J,$C31,MOVIMIENTOS!$B:$B,">="&DATE(2026,12,1),MOVIMIENTOS!$B:$B,"<"&DATE(2026,13,1)) -> 3000 | O31: =SUM(E31:N31) -> 30000 | P31: =SUMIFS(MOVIMIENTOS!$I:$I,MOVIMIENTOS!$D:$D,"Aporte",MOVIMIENTOS!$E:$E,"Extraordinaria",MOVIMIENTOS!$F:$F,P$4,MOVIMIENTOS!$J:$J,$C31) -> 1000 | Q31: =SUMIFS(MOVIMIENTOS!$I:$I,MOVIMIENTOS!$D:$D,"Aporte",MOVIMIENTOS!$E:$E,"Extraordinaria",MOVIMIENTOS!$F:$F,Q$4,MOVIMIENTOS!$J:$J,$C31) -> 2000 | R31: =SUMIFS(MOVIMIENTOS!$I:$I,MOVIMIENTOS!$D:$D,"Aporte",MOVIMIENTOS!$E:$E,"Extraordinaria",MOVIMIENTOS!$F:$F,R$4,MOVIMIENTOS!$J:$J,$C31) -> 2000 | S31: =SUMIFS(MOVIMIENTOS!$I:$I,MOVIMIENTOS!$D:$D,"Aporte",MOVIMIENTOS!$E:$E,"Extraordinaria",MOVIMIENTOS!$F:$F,S$4,MOVIMIENTOS!$J:$J,$C31) -> 0 | T31: =SUMIFS(MOVIMIENTOS!$I:$I,MOVIMIENTOS!$D:$D,"Aporte",MOVIMIENTOS!$E:$E,"Extraordinaria",MOVIMIENTOS!$F:$F,T$4,MOVIMIENTOS!$J:$J,$C31) -> 0 | U31: =SUMIFS(MOVIMIENTOS!$I:$I,MOVIMIENTOS!$D:$D,"Aporte",MOVIMIENTOS!$E:$E,"Extraordinaria",MOVIMIENTOS!$F:$F,U$4,MOVIMIENTOS!$J:$J,$C31) -> 0 | V31: =SUMIFS(MOVIMIENTOS!$I:$I,MOVIMIENTOS!$D:$D,"Aporte",MOVIMIENTOS!$E:$E,"Extraordinaria",MOVIMIENTOS!$F:$F,V$4,MOVIMIENTOS!$J:$J,$C31) -> 0 | W31: =SUM(P31:V31) -> 5000 | X31: =O31+W31 -> 35000
A32: 28 | B32: 24973619-8 | C32: RUBIO REYES JOSÉ ALONSO | E32: =SUMIFS(MOVIMIENTOS!$I:$I,MOVIMIENTOS!$D:$D,"Aporte",MOVIMIENTOS!$E:$E,"Anual",MOVIMIENTOS!$J:$J,$C32,MOVIMIENTOS!$B:$B,">="&DATE(2026,3,1),MOVIMIENTOS!$B:$B,"<"&DATE(2026,4,1)) -> 0 | F32: =SUMIFS(MOVIMIENTOS!$I:$I,MOVIMIENTOS!$D:$D,"Aporte",MOVIMIENTOS!$E:$E,"Anual",MOVIMIENTOS!$J:$J,$C32,MOVIMIENTOS!$B:$B,">="&DATE(2026,4,1),MOVIMIENTOS!$B:$B,"<"&DATE(2026,5,1)) -> 0 | G32: =SUMIFS(MOVIMIENTOS!$I:$I,MOVIMIENTOS!$D:$D,"Aporte",MOVIMIENTOS!$E:$E,"Anual",MOVIMIENTOS!$J:$J,$C32,MOVIMIENTOS!$B:$B,">="&DATE(2026,5,1),MOVIMIENTOS!$B:$B,"<"&DATE(2026,6,1)) -> 0 | H32: =SUMIFS(MOVIMIENTOS!$I:$I,MOVIMIENTOS!$D:$D,"Aporte",MOVIMIENTOS!$E:$E,"Anual",MOVIMIENTOS!$J:$J,$C32,MOVIMIENTOS!$B:$B,">="&DATE(2026,6,1),MOVIMIENTOS!$B:$B,"<"&DATE(2026,7,1)) -> 0 | I32: =SUMIFS(MOVIMIENTOS!$I:$I,MOVIMIENTOS!$D:$D,"Aporte",MOVIMIENTOS!$E:$E,"Anual",MOVIMIENTOS!$J:$J,$C32,MOVIMIENTOS!$B:$B,">="&DATE(2026,7,1),MOVIMIENTOS!$B:$B,"<"&DATE(2026,8,1)) -> 0 | J32: =SUMIFS(MOVIMIENTOS!$I:$I,MOVIMIENTOS!$D:$D,"Aporte",MOVIMIENTOS!$E:$E,"Anual",MOVIMIENTOS!$J:$J,$C32,MOVIMIENTOS!$B:$B,">="&DATE(2026,8,1),MOVIMIENTOS!$B:$B,"<"&DATE(2026,9,1)) -> 0 | K32: =SUMIFS(MOVIMIENTOS!$I:$I,MOVIMIENTOS!$D:$D,"Aporte",MOVIMIENTOS!$E:$E,"Anual",MOVIMIENTOS!$J:$J,$C32,MOVIMIENTOS!$B:$B,">="&DATE(2026,9,1),MOVIMIENTOS!$B:$B,"<"&DATE(2026,10,1)) -> 0 | L32: =SUMIFS(MOVIMIENTOS!$I:$I,MOVIMIENTOS!$D:$D,"Aporte",MOVIMIENTOS!$E:$E,"Anual",MOVIMIENTOS!$J:$J,$C32,MOVIMIENTOS!$B:$B,">="&DATE(2026,10,1),MOVIMIENTOS!$B:$B,"<"&DATE(2026,11,1)) -> 0 | M32: =SUMIFS(MOVIMIENTOS!$I:$I,MOVIMIENTOS!$D:$D,"Aporte",MOVIMIENTOS!$E:$E,"Anual",MOVIMIENTOS!$J:$J,$C32,MOVIMIENTOS!$B:$B,">="&DATE(2026,11,1),MOVIMIENTOS!$B:$B,"<"&DATE(2026,12,1)) -> 0 | N32: =SUMIFS(MOVIMIENTOS!$I:$I,MOVIMIENTOS!$D:$D,"Aporte",MOVIMIENTOS!$E:$E,"Anual",MOVIMIENTOS!$J:$J,$C32,MOVIMIENTOS!$B:$B,">="&DATE(2026,12,1),MOVIMIENTOS!$B:$B,"<"&DATE(2026,13,1)) -> 0 | O32: =SUM(E32:N32) -> 0 | P32: =SUMIFS(MOVIMIENTOS!$I:$I,MOVIMIENTOS!$D:$D,"Aporte",MOVIMIENTOS!$E:$E,"Extraordinaria",MOVIMIENTOS!$F:$F,P$4,MOVIMIENTOS!$J:$J,$C32) -> 1000 | Q32: =SUMIFS(MOVIMIENTOS!$I:$I,MOVIMIENTOS!$D:$D,"Aporte",MOVIMIENTOS!$E:$E,"Extraordinaria",MOVIMIENTOS!$F:$F,Q$4,MOVIMIENTOS!$J:$J,$C32) -> 2000 | R32: =SUMIFS(MOVIMIENTOS!$I:$I,MOVIMIENTOS!$D:$D,"Aporte",MOVIMIENTOS!$E:$E,"Extraordinaria",MOVIMIENTOS!$F:$F,R$4,MOVIMIENTOS!$J:$J,$C32) -> 2000 | S32: =SUMIFS(MOVIMIENTOS!$I:$I,MOVIMIENTOS!$D:$D,"Aporte",MOVIMIENTOS!$E:$E,"Extraordinaria",MOVIMIENTOS!$F:$F,S$4,MOVIMIENTOS!$J:$J,$C32) -> 0 | T32: =SUMIFS(MOVIMIENTOS!$I:$I,MOVIMIENTOS!$D:$D,"Aporte",MOVIMIENTOS!$E:$E,"Extraordinaria",MOVIMIENTOS!$F:$F,T$4,MOVIMIENTOS!$J:$J,$C32) -> 0 | U32: =SUMIFS(MOVIMIENTOS!$I:$I,MOVIMIENTOS!$D:$D,"Aporte",MOVIMIENTOS!$E:$E,"Extraordinaria",MOVIMIENTOS!$F:$F,U$4,MOVIMIENTOS!$J:$J,$C32) -> 0 | V32: =SUMIFS(MOVIMIENTOS!$I:$I,MOVIMIENTOS!$D:$D,"Aporte",MOVIMIENTOS!$E:$E,"Extraordinaria",MOVIMIENTOS!$F:$F,V$4,MOVIMIENTOS!$J:$J,$C32) -> 0 | W32: =SUM(P32:V32) -> 5000 | X32: =O32+W32 -> 5000
A33: 29 | B33: 28939190-8 | C33: SANCHEZ ZAMBRANO MIULER DAVID | D33: YERKA ZAMBRANO | E33: =SUMIFS(MOVIMIENTOS!$I:$I,MOVIMIENTOS!$D:$D,"Aporte",MOVIMIENTOS!$E:$E,"Anual",MOVIMIENTOS!$J:$J,$C33,MOVIMIENTOS!$B:$B,">="&DATE(2026,3,1),MOVIMIENTOS!$B:$B,"<"&DATE(2026,4,1)) -> 3000 | F33: =SUMIFS(MOVIMIENTOS!$I:$I,MOVIMIENTOS!$D:$D,"Aporte",MOVIMIENTOS!$E:$E,"Anual",MOVIMIENTOS!$J:$J,$C33,MOVIMIENTOS!$B:$B,">="&DATE(2026,4,1),MOVIMIENTOS!$B:$B,"<"&DATE(2026,5,1)) -> 3000 | G33: =SUMIFS(MOVIMIENTOS!$I:$I,MOVIMIENTOS!$D:$D,"Aporte",MOVIMIENTOS!$E:$E,"Anual",MOVIMIENTOS!$J:$J,$C33,MOVIMIENTOS!$B:$B,">="&DATE(2026,5,1),MOVIMIENTOS!$B:$B,"<"&DATE(2026,6,1)) -> 3000 | H33: =SUMIFS(MOVIMIENTOS!$I:$I,MOVIMIENTOS!$D:$D,"Aporte",MOVIMIENTOS!$E:$E,"Anual",MOVIMIENTOS!$J:$J,$C33,MOVIMIENTOS!$B:$B,">="&DATE(2026,6,1),MOVIMIENTOS!$B:$B,"<"&DATE(2026,7,1)) -> 0 | I33: =SUMIFS(MOVIMIENTOS!$I:$I,MOVIMIENTOS!$D:$D,"Aporte",MOVIMIENTOS!$E:$E,"Anual",MOVIMIENTOS!$J:$J,$C33,MOVIMIENTOS!$B:$B,">="&DATE(2026,7,1),MOVIMIENTOS!$B:$B,"<"&DATE(2026,8,1)) -> 0 | J33: =SUMIFS(MOVIMIENTOS!$I:$I,MOVIMIENTOS!$D:$D,"Aporte",MOVIMIENTOS!$E:$E,"Anual",MOVIMIENTOS!$J:$J,$C33,MOVIMIENTOS!$B:$B,">="&DATE(2026,8,1),MOVIMIENTOS!$B:$B,"<"&DATE(2026,9,1)) -> 0 | K33: =SUMIFS(MOVIMIENTOS!$I:$I,MOVIMIENTOS!$D:$D,"Aporte",MOVIMIENTOS!$E:$E,"Anual",MOVIMIENTOS!$J:$J,$C33,MOVIMIENTOS!$B:$B,">="&DATE(2026,9,1),MOVIMIENTOS!$B:$B,"<"&DATE(2026,10,1)) -> 0 | L33: =SUMIFS(MOVIMIENTOS!$I:$I,MOVIMIENTOS!$D:$D,"Aporte",MOVIMIENTOS!$E:$E,"Anual",MOVIMIENTOS!$J:$J,$C33,MOVIMIENTOS!$B:$B,">="&DATE(2026,10,1),MOVIMIENTOS!$B:$B,"<"&DATE(2026,11,1)) -> 0 | M33: =SUMIFS(MOVIMIENTOS!$I:$I,MOVIMIENTOS!$D:$D,"Aporte",MOVIMIENTOS!$E:$E,"Anual",MOVIMIENTOS!$J:$J,$C33,MOVIMIENTOS!$B:$B,">="&DATE(2026,11,1),MOVIMIENTOS!$B:$B,"<"&DATE(2026,12,1)) -> 0 | N33: =SUMIFS(MOVIMIENTOS!$I:$I,MOVIMIENTOS!$D:$D,"Aporte",MOVIMIENTOS!$E:$E,"Anual",MOVIMIENTOS!$J:$J,$C33,MOVIMIENTOS!$B:$B,">="&DATE(2026,12,1),MOVIMIENTOS!$B:$B,"<"&DATE(2026,13,1)) -> 0 | O33: =SUM(E33:N33) -> 9000 | P33: =SUMIFS(MOVIMIENTOS!$I:$I,MOVIMIENTOS!$D:$D,"Aporte",MOVIMIENTOS!$E:$E,"Extraordinaria",MOVIMIENTOS!$F:$F,P$4,MOVIMIENTOS!$J:$J,$C33) -> 1000 | Q33: =SUMIFS(MOVIMIENTOS!$I:$I,MOVIMIENTOS!$D:$D,"Aporte",MOVIMIENTOS!$E:$E,"Extraordinaria",MOVIMIENTOS!$F:$F,Q$4,MOVIMIENTOS!$J:$J,$C33) -> 2000 | R33: =SUMIFS(MOVIMIENTOS!$I:$I,MOVIMIENTOS!$D:$D,"Aporte",MOVIMIENTOS!$E:$E,"Extraordinaria",MOVIMIENTOS!$F:$F,R$4,MOVIMIENTOS!$J:$J,$C33) -> 2000 | S33: =SUMIFS(MOVIMIENTOS!$I:$I,MOVIMIENTOS!$D:$D,"Aporte",MOVIMIENTOS!$E:$E,"Extraordinaria",MOVIMIENTOS!$F:$F,S$4,MOVIMIENTOS!$J:$J,$C33) -> 0 | T33: =SUMIFS(MOVIMIENTOS!$I:$I,MOVIMIENTOS!$D:$D,"Aporte",MOVIMIENTOS!$E:$E,"Extraordinaria",MOVIMIENTOS!$F:$F,T$4,MOVIMIENTOS!$J:$J,$C33) -> 0 | U33: =SUMIFS(MOVIMIENTOS!$I:$I,MOVIMIENTOS!$D:$D,"Aporte",MOVIMIENTOS!$E:$E,"Extraordinaria",MOVIMIENTOS!$F:$F,U$4,MOVIMIENTOS!$J:$J,$C33) -> 0 | V33: =SUMIFS(MOVIMIENTOS!$I:$I,MOVIMIENTOS!$D:$D,"Aporte",MOVIMIENTOS!$E:$E,"Extraordinaria",MOVIMIENTOS!$F:$F,V$4,MOVIMIENTOS!$J:$J,$C33) -> 0 | W33: =SUM(P33:V33) -> 5000 | X33: =O33+W33 -> 14000
A34: 30 | B34: 25033740-K | C34: SOTO URZÚA COLOMBA JANÍS | D34: MABEL URZUA | E34: =SUMIFS(MOVIMIENTOS!$I:$I,MOVIMIENTOS!$D:$D,"Aporte",MOVIMIENTOS!$E:$E,"Anual",MOVIMIENTOS!$J:$J,$C34,MOVIMIENTOS!$B:$B,">="&DATE(2026,3,1),MOVIMIENTOS!$B:$B,"<"&DATE(2026,4,1)) -> 3000 | F34: =SUMIFS(MOVIMIENTOS!$I:$I,MOVIMIENTOS!$D:$D,"Aporte",MOVIMIENTOS!$E:$E,"Anual",MOVIMIENTOS!$J:$J,$C34,MOVIMIENTOS!$B:$B,">="&DATE(2026,4,1),MOVIMIENTOS!$B:$B,"<"&DATE(2026,5,1)) -> 3000 | G34: =SUMIFS(MOVIMIENTOS!$I:$I,MOVIMIENTOS!$D:$D,"Aporte",MOVIMIENTOS!$E:$E,"Anual",MOVIMIENTOS!$J:$J,$C34,MOVIMIENTOS!$B:$B,">="&DATE(2026,5,1),MOVIMIENTOS!$B:$B,"<"&DATE(2026,6,1)) -> 3000 | H34: =SUMIFS(MOVIMIENTOS!$I:$I,MOVIMIENTOS!$D:$D,"Aporte",MOVIMIENTOS!$E:$E,"Anual",MOVIMIENTOS!$J:$J,$C34,MOVIMIENTOS!$B:$B,">="&DATE(2026,6,1),MOVIMIENTOS!$B:$B,"<"&DATE(2026,7,1)) -> 3000 | I34: =SUMIFS(MOVIMIENTOS!$I:$I,MOVIMIENTOS!$D:$D,"Aporte",MOVIMIENTOS!$E:$E,"Anual",MOVIMIENTOS!$J:$J,$C34,MOVIMIENTOS!$B:$B,">="&DATE(2026,7,1),MOVIMIENTOS!$B:$B,"<"&DATE(2026,8,1)) -> 3000 | J34: =SUMIFS(MOVIMIENTOS!$I:$I,MOVIMIENTOS!$D:$D,"Aporte",MOVIMIENTOS!$E:$E,"Anual",MOVIMIENTOS!$J:$J,$C34,MOVIMIENTOS!$B:$B,">="&DATE(2026,8,1),MOVIMIENTOS!$B:$B,"<"&DATE(2026,9,1)) -> 0 | K34: =SUMIFS(MOVIMIENTOS!$I:$I,MOVIMIENTOS!$D:$D,"Aporte",MOVIMIENTOS!$E:$E,"Anual",MOVIMIENTOS!$J:$J,$C34,MOVIMIENTOS!$B:$B,">="&DATE(2026,9,1),MOVIMIENTOS!$B:$B,"<"&DATE(2026,10,1)) -> 0 | L34: =SUMIFS(MOVIMIENTOS!$I:$I,MOVIMIENTOS!$D:$D,"Aporte",MOVIMIENTOS!$E:$E,"Anual",MOVIMIENTOS!$J:$J,$C34,MOVIMIENTOS!$B:$B,">="&DATE(2026,10,1),MOVIMIENTOS!$B:$B,"<"&DATE(2026,11,1)) -> 0 | M34: =SUMIFS(MOVIMIENTOS!$I:$I,MOVIMIENTOS!$D:$D,"Aporte",MOVIMIENTOS!$E:$E,"Anual",MOVIMIENTOS!$J:$J,$C34,MOVIMIENTOS!$B:$B,">="&DATE(2026,11,1),MOVIMIENTOS!$B:$B,"<"&DATE(2026,12,1)) -> 0 | N34: =SUMIFS(MOVIMIENTOS!$I:$I,MOVIMIENTOS!$D:$D,"Aporte",MOVIMIENTOS!$E:$E,"Anual",MOVIMIENTOS!$J:$J,$C34,MOVIMIENTOS!$B:$B,">="&DATE(2026,12,1),MOVIMIENTOS!$B:$B,"<"&DATE(2026,13,1)) -> 0 | O34: =SUM(E34:N34) -> 15000 | P34: =SUMIFS(MOVIMIENTOS!$I:$I,MOVIMIENTOS!$D:$D,"Aporte",MOVIMIENTOS!$E:$E,"Extraordinaria",MOVIMIENTOS!$F:$F,P$4,MOVIMIENTOS!$J:$J,$C34) -> 1000 | Q34: =SUMIFS(MOVIMIENTOS!$I:$I,MOVIMIENTOS!$D:$D,"Aporte",MOVIMIENTOS!$E:$E,"Extraordinaria",MOVIMIENTOS!$F:$F,Q$4,MOVIMIENTOS!$J:$J,$C34) -> 2000 | R34: =SUMIFS(MOVIMIENTOS!$I:$I,MOVIMIENTOS!$D:$D,"Aporte",MOVIMIENTOS!$E:$E,"Extraordinaria",MOVIMIENTOS!$F:$F,R$4,MOVIMIENTOS!$J:$J,$C34) -> 2000 | S34: =SUMIFS(MOVIMIENTOS!$I:$I,MOVIMIENTOS!$D:$D,"Aporte",MOVIMIENTOS!$E:$E,"Extraordinaria",MOVIMIENTOS!$F:$F,S$4,MOVIMIENTOS!$J:$J,$C34) -> 0 | T34: =SUMIFS(MOVIMIENTOS!$I:$I,MOVIMIENTOS!$D:$D,"Aporte",MOVIMIENTOS!$E:$E,"Extraordinaria",MOVIMIENTOS!$F:$F,T$4,MOVIMIENTOS!$J:$J,$C34) -> 0 | U34: =SUMIFS(MOVIMIENTOS!$I:$I,MOVIMIENTOS!$D:$D,"Aporte",MOVIMIENTOS!$E:$E,"Extraordinaria",MOVIMIENTOS!$F:$F,U$4,MOVIMIENTOS!$J:$J,$C34) -> 0 | V34: =SUMIFS(MOVIMIENTOS!$I:$I,MOVIMIENTOS!$D:$D,"Aporte",MOVIMIENTOS!$E:$E,"Extraordinaria",MOVIMIENTOS!$F:$F,V$4,MOVIMIENTOS!$J:$J,$C34) -> 0 | W34: =SUM(P34:V34) -> 5000 | X34: =O34+W34 -> 20000
A35: 31 | B35: 25001015-K | C35: UNZUETA GONZÁLEZ JESÚS VINKO ALEJANDRO | E35: =SUMIFS(MOVIMIENTOS!$I:$I,MOVIMIENTOS!$D:$D,"Aporte",MOVIMIENTOS!$E:$E,"Anual",MOVIMIENTOS!$J:$J,$C35,MOVIMIENTOS!$B:$B,">="&DATE(2026,3,1),MOVIMIENTOS!$B:$B,"<"&DATE(2026,4,1)) -> 0 | F35: =SUMIFS(MOVIMIENTOS!$I:$I,MOVIMIENTOS!$D:$D,"Aporte",MOVIMIENTOS!$E:$E,"Anual",MOVIMIENTOS!$J:$J,$C35,MOVIMIENTOS!$B:$B,">="&DATE(2026,4,1),MOVIMIENTOS!$B:$B,"<"&DATE(2026,5,1)) -> 0 | G35: =SUMIFS(MOVIMIENTOS!$I:$I,MOVIMIENTOS!$D:$D,"Aporte",MOVIMIENTOS!$E:$E,"Anual",MOVIMIENTOS!$J:$J,$C35,MOVIMIENTOS!$B:$B,">="&DATE(2026,5,1),MOVIMIENTOS!$B:$B,"<"&DATE(2026,6,1)) -> 0 | H35: =SUMIFS(MOVIMIENTOS!$I:$I,MOVIMIENTOS!$D:$D,"Aporte",MOVIMIENTOS!$E:$E,"Anual",MOVIMIENTOS!$J:$J,$C35,MOVIMIENTOS!$B:$B,">="&DATE(2026,6,1),MOVIMIENTOS!$B:$B,"<"&DATE(2026,7,1)) -> 0 | I35: =SUMIFS(MOVIMIENTOS!$I:$I,MOVIMIENTOS!$D:$D,"Aporte",MOVIMIENTOS!$E:$E,"Anual",MOVIMIENTOS!$J:$J,$C35,MOVIMIENTOS!$B:$B,">="&DATE(2026,7,1),MOVIMIENTOS!$B:$B,"<"&DATE(2026,8,1)) -> 0 | J35: =SUMIFS(MOVIMIENTOS!$I:$I,MOVIMIENTOS!$D:$D,"Aporte",MOVIMIENTOS!$E:$E,"Anual",MOVIMIENTOS!$J:$J,$C35,MOVIMIENTOS!$B:$B,">="&DATE(2026,8,1),MOVIMIENTOS!$B:$B,"<"&DATE(2026,9,1)) -> 0 | K35: =SUMIFS(MOVIMIENTOS!$I:$I,MOVIMIENTOS!$D:$D,"Aporte",MOVIMIENTOS!$E:$E,"Anual",MOVIMIENTOS!$J:$J,$C35,MOVIMIENTOS!$B:$B,">="&DATE(2026,9,1),MOVIMIENTOS!$B:$B,"<"&DATE(2026,10,1)) -> 0 | L35: =SUMIFS(MOVIMIENTOS!$I:$I,MOVIMIENTOS!$D:$D,"Aporte",MOVIMIENTOS!$E:$E,"Anual",MOVIMIENTOS!$J:$J,$C35,MOVIMIENTOS!$B:$B,">="&DATE(2026,10,1),MOVIMIENTOS!$B:$B,"<"&DATE(2026,11,1)) -> 0 | M35: =SUMIFS(MOVIMIENTOS!$I:$I,MOVIMIENTOS!$D:$D,"Aporte",MOVIMIENTOS!$E:$E,"Anual",MOVIMIENTOS!$J:$J,$C35,MOVIMIENTOS!$B:$B,">="&DATE(2026,11,1),MOVIMIENTOS!$B:$B,"<"&DATE(2026,12,1)) -> 0 | N35: =SUMIFS(MOVIMIENTOS!$I:$I,MOVIMIENTOS!$D:$D,"Aporte",MOVIMIENTOS!$E:$E,"Anual",MOVIMIENTOS!$J:$J,$C35,MOVIMIENTOS!$B:$B,">="&DATE(2026,12,1),MOVIMIENTOS!$B:$B,"<"&DATE(2026,13,1)) -> 0 | O35: =SUM(E35:N35) -> 0 | P35: =SUMIFS(MOVIMIENTOS!$I:$I,MOVIMIENTOS!$D:$D,"Aporte",MOVIMIENTOS!$E:$E,"Extraordinaria",MOVIMIENTOS!$F:$F,P$4,MOVIMIENTOS!$J:$J,$C35) -> 0 | Q35: =SUMIFS(MOVIMIENTOS!$I:$I,MOVIMIENTOS!$D:$D,"Aporte",MOVIMIENTOS!$E:$E,"Extraordinaria",MOVIMIENTOS!$F:$F,Q$4,MOVIMIENTOS!$J:$J,$C35) -> 0 | R35: =SUMIFS(MOVIMIENTOS!$I:$I,MOVIMIENTOS!$D:$D,"Aporte",MOVIMIENTOS!$E:$E,"Extraordinaria",MOVIMIENTOS!$F:$F,R$4,MOVIMIENTOS!$J:$J,$C35) -> 0 | S35: =SUMIFS(MOVIMIENTOS!$I:$I,MOVIMIENTOS!$D:$D,"Aporte",MOVIMIENTOS!$E:$E,"Extraordinaria",MOVIMIENTOS!$F:$F,S$4,MOVIMIENTOS!$J:$J,$C35) -> 0 | T35: =SUMIFS(MOVIMIENTOS!$I:$I,MOVIMIENTOS!$D:$D,"Aporte",MOVIMIENTOS!$E:$E,"Extraordinaria",MOVIMIENTOS!$F:$F,T$4,MOVIMIENTOS!$J:$J,$C35) -> 0 | U35: =SUMIFS(MOVIMIENTOS!$I:$I,MOVIMIENTOS!$D:$D,"Aporte",MOVIMIENTOS!$E:$E,"Extraordinaria",MOVIMIENTOS!$F:$F,U$4,MOVIMIENTOS!$J:$J,$C35) -> 0 | V35: =SUMIFS(MOVIMIENTOS!$I:$I,MOVIMIENTOS!$D:$D,"Aporte",MOVIMIENTOS!$E:$E,"Extraordinaria",MOVIMIENTOS!$F:$F,V$4,MOVIMIENTOS!$J:$J,$C35) -> 0 | W35: =SUM(P35:V35) -> 0 | X35: =O35+W35 -> 0
A36: 32 | C36: VALDÉS ORMAZÁBAL LAURA FRANCISCA RAYEN | E36: =SUMIFS(MOVIMIENTOS!$I:$I,MOVIMIENTOS!$D:$D,"Aporte",MOVIMIENTOS!$E:$E,"Anual",MOVIMIENTOS!$J:$J,$C36,MOVIMIENTOS!$B:$B,">="&DATE(2026,3,1),MOVIMIENTOS!$B:$B,"<"&DATE(2026,4,1)) -> 3000 | F36: =SUMIFS(MOVIMIENTOS!$I:$I,MOVIMIENTOS!$D:$D,"Aporte",MOVIMIENTOS!$E:$E,"Anual",MOVIMIENTOS!$J:$J,$C36,MOVIMIENTOS!$B:$B,">="&DATE(2026,4,1),MOVIMIENTOS!$B:$B,"<"&DATE(2026,5,1)) -> 3000 | G36: =SUMIFS(MOVIMIENTOS!$I:$I,MOVIMIENTOS!$D:$D,"Aporte",MOVIMIENTOS!$E:$E,"Anual",MOVIMIENTOS!$J:$J,$C36,MOVIMIENTOS!$B:$B,">="&DATE(2026,5,1),MOVIMIENTOS!$B:$B,"<"&DATE(2026,6,1)) -> 3000 | H36: =SUMIFS(MOVIMIENTOS!$I:$I,MOVIMIENTOS!$D:$D,"Aporte",MOVIMIENTOS!$E:$E,"Anual",MOVIMIENTOS!$J:$J,$C36,MOVIMIENTOS!$B:$B,">="&DATE(2026,6,1),MOVIMIENTOS!$B:$B,"<"&DATE(2026,7,1)) -> 3000 | I36: =SUMIFS(MOVIMIENTOS!$I:$I,MOVIMIENTOS!$D:$D,"Aporte",MOVIMIENTOS!$E:$E,"Anual",MOVIMIENTOS!$J:$J,$C36,MOVIMIENTOS!$B:$B,">="&DATE(2026,7,1),MOVIMIENTOS!$B:$B,"<"&DATE(2026,8,1)) -> 0 | J36: =SUMIFS(MOVIMIENTOS!$I:$I,MOVIMIENTOS!$D:$D,"Aporte",MOVIMIENTOS!$E:$E,"Anual",MOVIMIENTOS!$J:$J,$C36,MOVIMIENTOS!$B:$B,">="&DATE(2026,8,1),MOVIMIENTOS!$B:$B,"<"&DATE(2026,9,1)) -> 0 | K36: =SUMIFS(MOVIMIENTOS!$I:$I,MOVIMIENTOS!$D:$D,"Aporte",MOVIMIENTOS!$E:$E,"Anual",MOVIMIENTOS!$J:$J,$C36,MOVIMIENTOS!$B:$B,">="&DATE(2026,9,1),MOVIMIENTOS!$B:$B,"<"&DATE(2026,10,1)) -> 0 | L36: =SUMIFS(MOVIMIENTOS!$I:$I,MOVIMIENTOS!$D:$D,"Aporte",MOVIMIENTOS!$E:$E,"Anual",MOVIMIENTOS!$J:$J,$C36,MOVIMIENTOS!$B:$B,">="&DATE(2026,10,1),MOVIMIENTOS!$B:$B,"<"&DATE(2026,11,1)) -> 0 | M36: =SUMIFS(MOVIMIENTOS!$I:$I,MOVIMIENTOS!$D:$D,"Aporte",MOVIMIENTOS!$E:$E,"Anual",MOVIMIENTOS!$J:$J,$C36,MOVIMIENTOS!$B:$B,">="&DATE(2026,11,1),MOVIMIENTOS!$B:$B,"<"&DATE(2026,12,1)) -> 0 | N36: =SUMIFS(MOVIMIENTOS!$I:$I,MOVIMIENTOS!$D:$D,"Aporte",MOVIMIENTOS!$E:$E,"Anual",MOVIMIENTOS!$J:$J,$C36,MOVIMIENTOS!$B:$B,">="&DATE(2026,12,1),MOVIMIENTOS!$B:$B,"<"&DATE(2026,13,1)) -> 0 | O36: =SUM(E36:N36) -> 12000 | P36: =SUMIFS(MOVIMIENTOS!$I:$I,MOVIMIENTOS!$D:$D,"Aporte",MOVIMIENTOS!$E:$E,"Extraordinaria",MOVIMIENTOS!$F:$F,P$4,MOVIMIENTOS!$J:$J,$C36) -> 1000 | Q36: =SUMIFS(MOVIMIENTOS!$I:$I,MOVIMIENTOS!$D:$D,"Aporte",MOVIMIENTOS!$E:$E,"Extraordinaria",MOVIMIENTOS!$F:$F,Q$4,MOVIMIENTOS!$J:$J,$C36) -> 2000 | R36: =SUMIFS(MOVIMIENTOS!$I:$I,MOVIMIENTOS!$D:$D,"Aporte",MOVIMIENTOS!$E:$E,"Extraordinaria",MOVIMIENTOS!$F:$F,R$4,MOVIMIENTOS!$J:$J,$C36) -> 2000 | S36: =SUMIFS(MOVIMIENTOS!$I:$I,MOVIMIENTOS!$D:$D,"Aporte",MOVIMIENTOS!$E:$E,"Extraordinaria",MOVIMIENTOS!$F:$F,S$4,MOVIMIENTOS!$J:$J,$C36) -> 0 | T36: =SUMIFS(MOVIMIENTOS!$I:$I,MOVIMIENTOS!$D:$D,"Aporte",MOVIMIENTOS!$E:$E,"Extraordinaria",MOVIMIENTOS!$F:$F,T$4,MOVIMIENTOS!$J:$J,$C36) -> 0 | U36: =SUMIFS(MOVIMIENTOS!$I:$I,MOVIMIENTOS!$D:$D,"Aporte",MOVIMIENTOS!$E:$E,"Extraordinaria",MOVIMIENTOS!$F:$F,U$4,MOVIMIENTOS!$J:$J,$C36) -> 0 | V36: =SUMIFS(MOVIMIENTOS!$I:$I,MOVIMIENTOS!$D:$D,"Aporte",MOVIMIENTOS!$E:$E,"Extraordinaria",MOVIMIENTOS!$F:$F,V$4,MOVIMIENTOS!$J:$J,$C36) -> 0 | W36: =SUM(P36:V36) -> 5000 | X36: =O36+W36 -> 17000
A37: 33 | C37: VÁSQUEZ BRAVO RAÚL FELICIANO | D37: LUZMENIA BRAVO | E37: =SUMIFS(MOVIMIENTOS!$I:$I,MOVIMIENTOS!$D:$D,"Aporte",MOVIMIENTOS!$E:$E,"Anual",MOVIMIENTOS!$J:$J,$C37,MOVIMIENTOS!$B:$B,">="&DATE(2026,3,1),MOVIMIENTOS!$B:$B,"<"&DATE(2026,4,1)) -> 3000 | F37: =SUMIFS(MOVIMIENTOS!$I:$I,MOVIMIENTOS!$D:$D,"Aporte",MOVIMIENTOS!$E:$E,"Anual",MOVIMIENTOS!$J:$J,$C37,MOVIMIENTOS!$B:$B,">="&DATE(2026,4,1),MOVIMIENTOS!$B:$B,"<"&DATE(2026,5,1)) -> 3000 | G37: =SUMIFS(MOVIMIENTOS!$I:$I,MOVIMIENTOS!$D:$D,"Aporte",MOVIMIENTOS!$E:$E,"Anual",MOVIMIENTOS!$J:$J,$C37,MOVIMIENTOS!$B:$B,">="&DATE(2026,5,1),MOVIMIENTOS!$B:$B,"<"&DATE(2026,6,1)) -> 3000 | H37: =SUMIFS(MOVIMIENTOS!$I:$I,MOVIMIENTOS!$D:$D,"Aporte",MOVIMIENTOS!$E:$E,"Anual",MOVIMIENTOS!$J:$J,$C37,MOVIMIENTOS!$B:$B,">="&DATE(2026,6,1),MOVIMIENTOS!$B:$B,"<"&DATE(2026,7,1)) -> 3000 | I37: =SUMIFS(MOVIMIENTOS!$I:$I,MOVIMIENTOS!$D:$D,"Aporte",MOVIMIENTOS!$E:$E,"Anual",MOVIMIENTOS!$J:$J,$C37,MOVIMIENTOS!$B:$B,">="&DATE(2026,7,1),MOVIMIENTOS!$B:$B,"<"&DATE(2026,8,1)) -> 0 | J37: =SUMIFS(MOVIMIENTOS!$I:$I,MOVIMIENTOS!$D:$D,"Aporte",MOVIMIENTOS!$E:$E,"Anual",MOVIMIENTOS!$J:$J,$C37,MOVIMIENTOS!$B:$B,">="&DATE(2026,8,1),MOVIMIENTOS!$B:$B,"<"&DATE(2026,9,1)) -> 0 | K37: =SUMIFS(MOVIMIENTOS!$I:$I,MOVIMIENTOS!$D:$D,"Aporte",MOVIMIENTOS!$E:$E,"Anual",MOVIMIENTOS!$J:$J,$C37,MOVIMIENTOS!$B:$B,">="&DATE(2026,9,1),MOVIMIENTOS!$B:$B,"<"&DATE(2026,10,1)) -> 0 | L37: =SUMIFS(MOVIMIENTOS!$I:$I,MOVIMIENTOS!$D:$D,"Aporte",MOVIMIENTOS!$E:$E,"Anual",MOVIMIENTOS!$J:$J,$C37,MOVIMIENTOS!$B:$B,">="&DATE(2026,10,1),MOVIMIENTOS!$B:$B,"<"&DATE(2026,11,1)) -> 0 | M37: =SUMIFS(MOVIMIENTOS!$I:$I,MOVIMIENTOS!$D:$D,"Aporte",MOVIMIENTOS!$E:$E,"Anual",MOVIMIENTOS!$J:$J,$C37,MOVIMIENTOS!$B:$B,">="&DATE(2026,11,1),MOVIMIENTOS!$B:$B,"<"&DATE(2026,12,1)) -> 0 | N37: =SUMIFS(MOVIMIENTOS!$I:$I,MOVIMIENTOS!$D:$D,"Aporte",MOVIMIENTOS!$E:$E,"Anual",MOVIMIENTOS!$J:$J,$C37,MOVIMIENTOS!$B:$B,">="&DATE(2026,12,1),MOVIMIENTOS!$B:$B,"<"&DATE(2026,13,1)) -> 0 | O37: =SUM(E37:N37) -> 12000 | P37: =SUMIFS(MOVIMIENTOS!$I:$I,MOVIMIENTOS!$D:$D,"Aporte",MOVIMIENTOS!$E:$E,"Extraordinaria",MOVIMIENTOS!$F:$F,P$4,MOVIMIENTOS!$J:$J,$C37) -> 1000 | Q37: =SUMIFS(MOVIMIENTOS!$I:$I,MOVIMIENTOS!$D:$D,"Aporte",MOVIMIENTOS!$E:$E,"Extraordinaria",MOVIMIENTOS!$F:$F,Q$4,MOVIMIENTOS!$J:$J,$C37) -> 2000 | R37: =SUMIFS(MOVIMIENTOS!$I:$I,MOVIMIENTOS!$D:$D,"Aporte",MOVIMIENTOS!$E:$E,"Extraordinaria",MOVIMIENTOS!$F:$F,R$4,MOVIMIENTOS!$J:$J,$C37) -> 0 | S37: =SUMIFS(MOVIMIENTOS!$I:$I,MOVIMIENTOS!$D:$D,"Aporte",MOVIMIENTOS!$E:$E,"Extraordinaria",MOVIMIENTOS!$F:$F,S$4,MOVIMIENTOS!$J:$J,$C37) -> 0 | T37: =SUMIFS(MOVIMIENTOS!$I:$I,MOVIMIENTOS!$D:$D,"Aporte",MOVIMIENTOS!$E:$E,"Extraordinaria",MOVIMIENTOS!$F:$F,T$4,MOVIMIENTOS!$J:$J,$C37) -> 0 | U37: =SUMIFS(MOVIMIENTOS!$I:$I,MOVIMIENTOS!$D:$D,"Aporte",MOVIMIENTOS!$E:$E,"Extraordinaria",MOVIMIENTOS!$F:$F,U$4,MOVIMIENTOS!$J:$J,$C37) -> 1000 | V37: =SUMIFS(MOVIMIENTOS!$I:$I,MOVIMIENTOS!$D:$D,"Aporte",MOVIMIENTOS!$E:$E,"Extraordinaria",MOVIMIENTOS!$F:$F,V$4,MOVIMIENTOS!$J:$J,$C37) -> 0 | W37: =SUM(P37:V37) -> 4000 | X37: =O37+W37 -> 16000
A38: 34 | C38: GIANELA FLORES | D38: JANIS OYARCE | E38: =SUMIFS(MOVIMIENTOS!$I:$I,MOVIMIENTOS!$D:$D,"Aporte",MOVIMIENTOS!$E:$E,"Anual",MOVIMIENTOS!$J:$J,$C38,MOVIMIENTOS!$B:$B,">="&DATE(2026,3,1),MOVIMIENTOS!$B:$B,"<"&DATE(2026,4,1)) -> 0 | F38: =SUMIFS(MOVIMIENTOS!$I:$I,MOVIMIENTOS!$D:$D,"Aporte",MOVIMIENTOS!$E:$E,"Anual",MOVIMIENTOS!$J:$J,$C38,MOVIMIENTOS!$B:$B,">="&DATE(2026,4,1),MOVIMIENTOS!$B:$B,"<"&DATE(2026,5,1)) -> 0 | G38: =SUMIFS(MOVIMIENTOS!$I:$I,MOVIMIENTOS!$D:$D,"Aporte",MOVIMIENTOS!$E:$E,"Anual",MOVIMIENTOS!$J:$J,$C38,MOVIMIENTOS!$B:$B,">="&DATE(2026,5,1),MOVIMIENTOS!$B:$B,"<"&DATE(2026,6,1)) -> 0 | H38: =SUMIFS(MOVIMIENTOS!$I:$I,MOVIMIENTOS!$D:$D,"Aporte",MOVIMIENTOS!$E:$E,"Anual",MOVIMIENTOS!$J:$J,$C38,MOVIMIENTOS!$B:$B,">="&DATE(2026,6,1),MOVIMIENTOS!$B:$B,"<"&DATE(2026,7,1)) -> 0 | I38: =SUMIFS(MOVIMIENTOS!$I:$I,MOVIMIENTOS!$D:$D,"Aporte",MOVIMIENTOS!$E:$E,"Anual",MOVIMIENTOS!$J:$J,$C38,MOVIMIENTOS!$B:$B,">="&DATE(2026,7,1),MOVIMIENTOS!$B:$B,"<"&DATE(2026,8,1)) -> 0 | J38: =SUMIFS(MOVIMIENTOS!$I:$I,MOVIMIENTOS!$D:$D,"Aporte",MOVIMIENTOS!$E:$E,"Anual",MOVIMIENTOS!$J:$J,$C38,MOVIMIENTOS!$B:$B,">="&DATE(2026,8,1),MOVIMIENTOS!$B:$B,"<"&DATE(2026,9,1)) -> 0 | K38: =SUMIFS(MOVIMIENTOS!$I:$I,MOVIMIENTOS!$D:$D,"Aporte",MOVIMIENTOS!$E:$E,"Anual",MOVIMIENTOS!$J:$J,$C38,MOVIMIENTOS!$B:$B,">="&DATE(2026,9,1),MOVIMIENTOS!$B:$B,"<"&DATE(2026,10,1)) -> 0 | L38: =SUMIFS(MOVIMIENTOS!$I:$I,MOVIMIENTOS!$D:$D,"Aporte",MOVIMIENTOS!$E:$E,"Anual",MOVIMIENTOS!$J:$J,$C38,MOVIMIENTOS!$B:$B,">="&DATE(2026,10,1),MOVIMIENTOS!$B:$B,"<"&DATE(2026,11,1)) -> 0 | M38: =SUMIFS(MOVIMIENTOS!$I:$I,MOVIMIENTOS!$D:$D,"Aporte",MOVIMIENTOS!$E:$E,"Anual",MOVIMIENTOS!$J:$J,$C38,MOVIMIENTOS!$B:$B,">="&DATE(2026,11,1),MOVIMIENTOS!$B:$B,"<"&DATE(2026,12,1)) -> 0 | N38: =SUMIFS(MOVIMIENTOS!$I:$I,MOVIMIENTOS!$D:$D,"Aporte",MOVIMIENTOS!$E:$E,"Anual",MOVIMIENTOS!$J:$J,$C38,MOVIMIENTOS!$B:$B,">="&DATE(2026,12,1),MOVIMIENTOS!$B:$B,"<"&DATE(2026,13,1)) -> 0 | O38: =SUM(E38:N38) -> 0 | P38: =SUMIFS(MOVIMIENTOS!$I:$I,MOVIMIENTOS!$D:$D,"Aporte",MOVIMIENTOS!$E:$E,"Extraordinaria",MOVIMIENTOS!$F:$F,P$4,MOVIMIENTOS!$J:$J,$C38) -> 1000 | Q38: =SUMIFS(MOVIMIENTOS!$I:$I,MOVIMIENTOS!$D:$D,"Aporte",MOVIMIENTOS!$E:$E,"Extraordinaria",MOVIMIENTOS!$F:$F,Q$4,MOVIMIENTOS!$J:$J,$C38) -> 2000 | R38: =SUMIFS(MOVIMIENTOS!$I:$I,MOVIMIENTOS!$D:$D,"Aporte",MOVIMIENTOS!$E:$E,"Extraordinaria",MOVIMIENTOS!$F:$F,R$4,MOVIMIENTOS!$J:$J,$C38) -> 2000 | S38: =SUMIFS(MOVIMIENTOS!$I:$I,MOVIMIENTOS!$D:$D,"Aporte",MOVIMIENTOS!$E:$E,"Extraordinaria",MOVIMIENTOS!$F:$F,S$4,MOVIMIENTOS!$J:$J,$C38) -> 0 | T38: =SUMIFS(MOVIMIENTOS!$I:$I,MOVIMIENTOS!$D:$D,"Aporte",MOVIMIENTOS!$E:$E,"Extraordinaria",MOVIMIENTOS!$F:$F,T$4,MOVIMIENTOS!$J:$J,$C38) -> 0 | U38: =SUMIFS(MOVIMIENTOS!$I:$I,MOVIMIENTOS!$D:$D,"Aporte",MOVIMIENTOS!$E:$E,"Extraordinaria",MOVIMIENTOS!$F:$F,U$4,MOVIMIENTOS!$J:$J,$C38) -> 1500 | V38: =SUMIFS(MOVIMIENTOS!$I:$I,MOVIMIENTOS!$D:$D,"Aporte",MOVIMIENTOS!$E:$E,"Extraordinaria",MOVIMIENTOS!$F:$F,V$4,MOVIMIENTOS!$J:$J,$C38) -> 0 | W38: =SUM(P38:V38) -> 6500 | X38: =O38+W38 -> 6500
A39: 35 | C39: LUEIZA BELTRAN JUAN PABLO | D39: FABIOLA BELTRAN | E39: =SUMIFS(MOVIMIENTOS!$I:$I,MOVIMIENTOS!$D:$D,"Aporte",MOVIMIENTOS!$E:$E,"Anual",MOVIMIENTOS!$J:$J,$C39,MOVIMIENTOS!$B:$B,">="&DATE(2026,3,1),MOVIMIENTOS!$B:$B,"<"&DATE(2026,4,1)) -> 0 | F39: =SUMIFS(MOVIMIENTOS!$I:$I,MOVIMIENTOS!$D:$D,"Aporte",MOVIMIENTOS!$E:$E,"Anual",MOVIMIENTOS!$J:$J,$C39,MOVIMIENTOS!$B:$B,">="&DATE(2026,4,1),MOVIMIENTOS!$B:$B,"<"&DATE(2026,5,1)) -> 0 | G39: =SUMIFS(MOVIMIENTOS!$I:$I,MOVIMIENTOS!$D:$D,"Aporte",MOVIMIENTOS!$E:$E,"Anual",MOVIMIENTOS!$J:$J,$C39,MOVIMIENTOS!$B:$B,">="&DATE(2026,5,1),MOVIMIENTOS!$B:$B,"<"&DATE(2026,6,1)) -> 0 | H39: =SUMIFS(MOVIMIENTOS!$I:$I,MOVIMIENTOS!$D:$D,"Aporte",MOVIMIENTOS!$E:$E,"Anual",MOVIMIENTOS!$J:$J,$C39,MOVIMIENTOS!$B:$B,">="&DATE(2026,6,1),MOVIMIENTOS!$B:$B,"<"&DATE(2026,7,1)) -> 0 | I39: =SUMIFS(MOVIMIENTOS!$I:$I,MOVIMIENTOS!$D:$D,"Aporte",MOVIMIENTOS!$E:$E,"Anual",MOVIMIENTOS!$J:$J,$C39,MOVIMIENTOS!$B:$B,">="&DATE(2026,7,1),MOVIMIENTOS!$B:$B,"<"&DATE(2026,8,1)) -> 0 | J39: =SUMIFS(MOVIMIENTOS!$I:$I,MOVIMIENTOS!$D:$D,"Aporte",MOVIMIENTOS!$E:$E,"Anual",MOVIMIENTOS!$J:$J,$C39,MOVIMIENTOS!$B:$B,">="&DATE(2026,8,1),MOVIMIENTOS!$B:$B,"<"&DATE(2026,9,1)) -> 0 | K39: =SUMIFS(MOVIMIENTOS!$I:$I,MOVIMIENTOS!$D:$D,"Aporte",MOVIMIENTOS!$E:$E,"Anual",MOVIMIENTOS!$J:$J,$C39,MOVIMIENTOS!$B:$B,">="&DATE(2026,9,1),MOVIMIENTOS!$B:$B,"<"&DATE(2026,10,1)) -> 0 | L39: =SUMIFS(MOVIMIENTOS!$I:$I,MOVIMIENTOS!$D:$D,"Aporte",MOVIMIENTOS!$E:$E,"Anual",MOVIMIENTOS!$J:$J,$C39,MOVIMIENTOS!$B:$B,">="&DATE(2026,10,1),MOVIMIENTOS!$B:$B,"<"&DATE(2026,11,1)) -> 0 | M39: =SUMIFS(MOVIMIENTOS!$I:$I,MOVIMIENTOS!$D:$D,"Aporte",MOVIMIENTOS!$E:$E,"Anual",MOVIMIENTOS!$J:$J,$C39,MOVIMIENTOS!$B:$B,">="&DATE(2026,11,1),MOVIMIENTOS!$B:$B,"<"&DATE(2026,12,1)) -> 0 | N39: =SUMIFS(MOVIMIENTOS!$I:$I,MOVIMIENTOS!$D:$D,"Aporte",MOVIMIENTOS!$E:$E,"Anual",MOVIMIENTOS!$J:$J,$C39,MOVIMIENTOS!$B:$B,">="&DATE(2026,12,1),MOVIMIENTOS!$B:$B,"<"&DATE(2026,13,1)) -> 0 | O39: =SUM(E39:N39) -> 0 | P39: =SUMIFS(MOVIMIENTOS!$I:$I,MOVIMIENTOS!$D:$D,"Aporte",MOVIMIENTOS!$E:$E,"Extraordinaria",MOVIMIENTOS!$F:$F,P$4,MOVIMIENTOS!$J:$J,$C39) -> 0 | Q39: =SUMIFS(MOVIMIENTOS!$I:$I,MOVIMIENTOS!$D:$D,"Aporte",MOVIMIENTOS!$E:$E,"Extraordinaria",MOVIMIENTOS!$F:$F,Q$4,MOVIMIENTOS!$J:$J,$C39) -> 2000 | R39: =SUMIFS(MOVIMIENTOS!$I:$I,MOVIMIENTOS!$D:$D,"Aporte",MOVIMIENTOS!$E:$E,"Extraordinaria",MOVIMIENTOS!$F:$F,R$4,MOVIMIENTOS!$J:$J,$C39) -> 2000 | S39: =SUMIFS(MOVIMIENTOS!$I:$I,MOVIMIENTOS!$D:$D,"Aporte",MOVIMIENTOS!$E:$E,"Extraordinaria",MOVIMIENTOS!$F:$F,S$4,MOVIMIENTOS!$J:$J,$C39) -> 0 | T39: =SUMIFS(MOVIMIENTOS!$I:$I,MOVIMIENTOS!$D:$D,"Aporte",MOVIMIENTOS!$E:$E,"Extraordinaria",MOVIMIENTOS!$F:$F,T$4,MOVIMIENTOS!$J:$J,$C39) -> 0 | U39: =SUMIFS(MOVIMIENTOS!$I:$I,MOVIMIENTOS!$D:$D,"Aporte",MOVIMIENTOS!$E:$E,"Extraordinaria",MOVIMIENTOS!$F:$F,U$4,MOVIMIENTOS!$J:$J,$C39) -> 1000 | V39: =SUMIFS(MOVIMIENTOS!$I:$I,MOVIMIENTOS!$D:$D,"Aporte",MOVIMIENTOS!$E:$E,"Extraordinaria",MOVIMIENTOS!$F:$F,V$4,MOVIMIENTOS!$J:$J,$C39) -> 0 | W39: =SUM(P39:V39) -> 5000 | X39: =O39+W39 -> 5000
A40: 36 | C40: FARIAS EMILIA | D40: MARTA VALDIVIA | E40: =SUMIFS(MOVIMIENTOS!$I:$I,MOVIMIENTOS!$D:$D,"Aporte",MOVIMIENTOS!$E:$E,"Anual",MOVIMIENTOS!$J:$J,$C40,MOVIMIENTOS!$B:$B,">="&DATE(2026,3,1),MOVIMIENTOS!$B:$B,"<"&DATE(2026,4,1)) -> 0 | F40: =SUMIFS(MOVIMIENTOS!$I:$I,MOVIMIENTOS!$D:$D,"Aporte",MOVIMIENTOS!$E:$E,"Anual",MOVIMIENTOS!$J:$J,$C40,MOVIMIENTOS!$B:$B,">="&DATE(2026,4,1),MOVIMIENTOS!$B:$B,"<"&DATE(2026,5,1)) -> 0 | G40: =SUMIFS(MOVIMIENTOS!$I:$I,MOVIMIENTOS!$D:$D,"Aporte",MOVIMIENTOS!$E:$E,"Anual",MOVIMIENTOS!$J:$J,$C40,MOVIMIENTOS!$B:$B,">="&DATE(2026,5,1),MOVIMIENTOS!$B:$B,"<"&DATE(2026,6,1)) -> 0 | H40: =SUMIFS(MOVIMIENTOS!$I:$I,MOVIMIENTOS!$D:$D,"Aporte",MOVIMIENTOS!$E:$E,"Anual",MOVIMIENTOS!$J:$J,$C40,MOVIMIENTOS!$B:$B,">="&DATE(2026,6,1),MOVIMIENTOS!$B:$B,"<"&DATE(2026,7,1)) -> 0 | I40: =SUMIFS(MOVIMIENTOS!$I:$I,MOVIMIENTOS!$D:$D,"Aporte",MOVIMIENTOS!$E:$E,"Anual",MOVIMIENTOS!$J:$J,$C40,MOVIMIENTOS!$B:$B,">="&DATE(2026,7,1),MOVIMIENTOS!$B:$B,"<"&DATE(2026,8,1)) -> 0 | J40: =SUMIFS(MOVIMIENTOS!$I:$I,MOVIMIENTOS!$D:$D,"Aporte",MOVIMIENTOS!$E:$E,"Anual",MOVIMIENTOS!$J:$J,$C40,MOVIMIENTOS!$B:$B,">="&DATE(2026,8,1),MOVIMIENTOS!$B:$B,"<"&DATE(2026,9,1)) -> 0 | K40: =SUMIFS(MOVIMIENTOS!$I:$I,MOVIMIENTOS!$D:$D,"Aporte",MOVIMIENTOS!$E:$E,"Anual",MOVIMIENTOS!$J:$J,$C40,MOVIMIENTOS!$B:$B,">="&DATE(2026,9,1),MOVIMIENTOS!$B:$B,"<"&DATE(2026,10,1)) -> 0 | L40: =SUMIFS(MOVIMIENTOS!$I:$I,MOVIMIENTOS!$D:$D,"Aporte",MOVIMIENTOS!$E:$E,"Anual",MOVIMIENTOS!$J:$J,$C40,MOVIMIENTOS!$B:$B,">="&DATE(2026,10,1),MOVIMIENTOS!$B:$B,"<"&DATE(2026,11,1)) -> 0 | M40: =SUMIFS(MOVIMIENTOS!$I:$I,MOVIMIENTOS!$D:$D,"Aporte",MOVIMIENTOS!$E:$E,"Anual",MOVIMIENTOS!$J:$J,$C40,MOVIMIENTOS!$B:$B,">="&DATE(2026,11,1),MOVIMIENTOS!$B:$B,"<"&DATE(2026,12,1)) -> 0 | N40: =SUMIFS(MOVIMIENTOS!$I:$I,MOVIMIENTOS!$D:$D,"Aporte",MOVIMIENTOS!$E:$E,"Anual",MOVIMIENTOS!$J:$J,$C40,MOVIMIENTOS!$B:$B,">="&DATE(2026,12,1),MOVIMIENTOS!$B:$B,"<"&DATE(2026,13,1)) -> 0 | O40: =SUM(E40:N40) -> 0 | P40: =SUMIFS(MOVIMIENTOS!$I:$I,MOVIMIENTOS!$D:$D,"Aporte",MOVIMIENTOS!$E:$E,"Extraordinaria",MOVIMIENTOS!$F:$F,P$4,MOVIMIENTOS!$J:$J,$C40) -> 0 | Q40: =SUMIFS(MOVIMIENTOS!$I:$I,MOVIMIENTOS!$D:$D,"Aporte",MOVIMIENTOS!$E:$E,"Extraordinaria",MOVIMIENTOS!$F:$F,Q$4,MOVIMIENTOS!$J:$J,$C40) -> 0 | R40: =SUMIFS(MOVIMIENTOS!$I:$I,MOVIMIENTOS!$D:$D,"Aporte",MOVIMIENTOS!$E:$E,"Extraordinaria",MOVIMIENTOS!$F:$F,R$4,MOVIMIENTOS!$J:$J,$C40) -> 2000 | S40: =SUMIFS(MOVIMIENTOS!$I:$I,MOVIMIENTOS!$D:$D,"Aporte",MOVIMIENTOS!$E:$E,"Extraordinaria",MOVIMIENTOS!$F:$F,S$4,MOVIMIENTOS!$J:$J,$C40) -> 0 | T40: =SUMIFS(MOVIMIENTOS!$I:$I,MOVIMIENTOS!$D:$D,"Aporte",MOVIMIENTOS!$E:$E,"Extraordinaria",MOVIMIENTOS!$F:$F,T$4,MOVIMIENTOS!$J:$J,$C40) -> 0 | U40: =SUMIFS(MOVIMIENTOS!$I:$I,MOVIMIENTOS!$D:$D,"Aporte",MOVIMIENTOS!$E:$E,"Extraordinaria",MOVIMIENTOS!$F:$F,U$4,MOVIMIENTOS!$J:$J,$C40) -> 0 | V40: =SUMIFS(MOVIMIENTOS!$I:$I,MOVIMIENTOS!$D:$D,"Aporte",MOVIMIENTOS!$E:$E,"Extraordinaria",MOVIMIENTOS!$F:$F,V$4,MOVIMIENTOS!$J:$J,$C40) -> 0 | W40: =SUM(P40:V40) -> 2000 | X40: =O40+W40 -> 2000
A41: 37 | C41: CUBILLOS MATIAS | E41: =SUMIFS(MOVIMIENTOS!$I:$I,MOVIMIENTOS!$D:$D,"Aporte",MOVIMIENTOS!$E:$E,"Anual",MOVIMIENTOS!$J:$J,$C41,MOVIMIENTOS!$B:$B,">="&DATE(2026,3,1),MOVIMIENTOS!$B:$B,"<"&DATE(2026,4,1)) -> 0 | F41: =SUMIFS(MOVIMIENTOS!$I:$I,MOVIMIENTOS!$D:$D,"Aporte",MOVIMIENTOS!$E:$E,"Anual",MOVIMIENTOS!$J:$J,$C41,MOVIMIENTOS!$B:$B,">="&DATE(2026,4,1),MOVIMIENTOS!$B:$B,"<"&DATE(2026,5,1)) -> 0 | G41: =SUMIFS(MOVIMIENTOS!$I:$I,MOVIMIENTOS!$D:$D,"Aporte",MOVIMIENTOS!$E:$E,"Anual",MOVIMIENTOS!$J:$J,$C41,MOVIMIENTOS!$B:$B,">="&DATE(2026,5,1),MOVIMIENTOS!$B:$B,"<"&DATE(2026,6,1)) -> 0 | H41: =SUMIFS(MOVIMIENTOS!$I:$I,MOVIMIENTOS!$D:$D,"Aporte",MOVIMIENTOS!$E:$E,"Anual",MOVIMIENTOS!$J:$J,$C41,MOVIMIENTOS!$B:$B,">="&DATE(2026,6,1),MOVIMIENTOS!$B:$B,"<"&DATE(2026,7,1)) -> 0 | I41: =SUMIFS(MOVIMIENTOS!$I:$I,MOVIMIENTOS!$D:$D,"Aporte",MOVIMIENTOS!$E:$E,"Anual",MOVIMIENTOS!$J:$J,$C41,MOVIMIENTOS!$B:$B,">="&DATE(2026,7,1),MOVIMIENTOS!$B:$B,"<"&DATE(2026,8,1)) -> 0 | J41: =SUMIFS(MOVIMIENTOS!$I:$I,MOVIMIENTOS!$D:$D,"Aporte",MOVIMIENTOS!$E:$E,"Anual",MOVIMIENTOS!$J:$J,$C41,MOVIMIENTOS!$B:$B,">="&DATE(2026,8,1),MOVIMIENTOS!$B:$B,"<"&DATE(2026,9,1)) -> 0 | K41: =SUMIFS(MOVIMIENTOS!$I:$I,MOVIMIENTOS!$D:$D,"Aporte",MOVIMIENTOS!$E:$E,"Anual",MOVIMIENTOS!$J:$J,$C41,MOVIMIENTOS!$B:$B,">="&DATE(2026,9,1),MOVIMIENTOS!$B:$B,"<"&DATE(2026,10,1)) -> 0 | L41: =SUMIFS(MOVIMIENTOS!$I:$I,MOVIMIENTOS!$D:$D,"Aporte",MOVIMIENTOS!$E:$E,"Anual",MOVIMIENTOS!$J:$J,$C41,MOVIMIENTOS!$B:$B,">="&DATE(2026,10,1),MOVIMIENTOS!$B:$B,"<"&DATE(2026,11,1)) -> 0 | M41: =SUMIFS(MOVIMIENTOS!$I:$I,MOVIMIENTOS!$D:$D,"Aporte",MOVIMIENTOS!$E:$E,"Anual",MOVIMIENTOS!$J:$J,$C41,MOVIMIENTOS!$B:$B,">="&DATE(2026,11,1),MOVIMIENTOS!$B:$B,"<"&DATE(2026,12,1)) -> 0 | N41: =SUMIFS(MOVIMIENTOS!$I:$I,MOVIMIENTOS!$D:$D,"Aporte",MOVIMIENTOS!$E:$E,"Anual",MOVIMIENTOS!$J:$J,$C41,MOVIMIENTOS!$B:$B,">="&DATE(2026,12,1),MOVIMIENTOS!$B:$B,"<"&DATE(2026,13,1)) -> 0 | O41: =SUM(E41:N41) -> 0 | P41: =SUMIFS(MOVIMIENTOS!$I:$I,MOVIMIENTOS!$D:$D,"Aporte",MOVIMIENTOS!$E:$E,"Extraordinaria",MOVIMIENTOS!$F:$F,P$4,MOVIMIENTOS!$J:$J,$C41) -> 0 | Q41: =SUMIFS(MOVIMIENTOS!$I:$I,MOVIMIENTOS!$D:$D,"Aporte",MOVIMIENTOS!$E:$E,"Extraordinaria",MOVIMIENTOS!$F:$F,Q$4,MOVIMIENTOS!$J:$J,$C41) -> 0 | R41: =SUMIFS(MOVIMIENTOS!$I:$I,MOVIMIENTOS!$D:$D,"Aporte",MOVIMIENTOS!$E:$E,"Extraordinaria",MOVIMIENTOS!$F:$F,R$4,MOVIMIENTOS!$J:$J,$C41) -> 2000 | S41: =SUMIFS(MOVIMIENTOS!$I:$I,MOVIMIENTOS!$D:$D,"Aporte",MOVIMIENTOS!$E:$E,"Extraordinaria",MOVIMIENTOS!$F:$F,S$4,MOVIMIENTOS!$J:$J,$C41) -> 0 | T41: =SUMIFS(MOVIMIENTOS!$I:$I,MOVIMIENTOS!$D:$D,"Aporte",MOVIMIENTOS!$E:$E,"Extraordinaria",MOVIMIENTOS!$F:$F,T$4,MOVIMIENTOS!$J:$J,$C41) -> 0 | U41: =SUMIFS(MOVIMIENTOS!$I:$I,MOVIMIENTOS!$D:$D,"Aporte",MOVIMIENTOS!$E:$E,"Extraordinaria",MOVIMIENTOS!$F:$F,U$4,MOVIMIENTOS!$J:$J,$C41) -> 0 | V41: =SUMIFS(MOVIMIENTOS!$I:$I,MOVIMIENTOS!$D:$D,"Aporte",MOVIMIENTOS!$E:$E,"Extraordinaria",MOVIMIENTOS!$F:$F,V$4,MOVIMIENTOS!$J:$J,$C41) -> 0 | W41: =SUM(P41:V41) -> 2000 | X41: =O41+W41 -> 2000
D42: TOTALES | E42: =SUM(E5:E41) -> 81000 | F42: =SUM(F5:F41) -> 54000 | G42: =SUM(G5:G41) -> 54000 | H42: =SUM(H5:H41) -> 42000 | I42: =SUM(I5:I41) -> 27000 | J42: =SUM(J5:J41) -> 9000 | K42: =SUM(K5:K41) -> 3000 | L42: =SUM(L5:L41) -> 3000 | ... X42: =SUM(X5:X41) -> 434500
E43: =IF($C43="","",SUMIFS(MOVIMIENTOS!$I:$I,MOVIMIENTOS!$D:$D,"Aporte",MOVIMIENTOS!$E:$E,"Anual",MOVIMIENTOS!$J:$J,$C43,MOVIMIENTOS!$B:$B,">="&DATE(2026,3,1),MOVIMIENTOS!$B:$B,"<"&DATE(2026,4,1))) | F43: =IF($C43="","",SUMIFS(MOVIMIENTOS!$I:$I,MOVIMIENTOS!$D:$D,"Aporte",MOVIMIENTOS!$E:$E,"Anual",MOVIMIENTOS!$J:$J,$C43,MOVIMIENTOS!$B:$B,">="&DATE(2026,4,1),MOVIMIENTOS!$B:$B,"<"&DATE(2026,5,1))) | G43: =IF($C43="","",SUMIFS(MOVIMIENTOS!$I:$I,MOVIMIENTOS!$D:$D,"Aporte",MOVIMIENTOS!$E:$E,"Anual",MOVIMIENTOS!$J:$J,$C43,MOVIMIENTOS!$B:$B,">="&DATE(2026,5,1),MOVIMIENTOS!$B:$B,"<"&DATE(2026,6,1))) | H43: =IF($C43="","",SUMIFS(MOVIMIENTOS!$I:$I,MOVIMIENTOS!$D:$D,"Aporte",MOVIMIENTOS!$E:$E,"Anual",MOVIMIENTOS!$J:$J,$C43,MOVIMIENTOS!$B:$B,">="&DATE(2026,6,1),MOVIMIENTOS!$B:$B,"<"&DATE(2026,7,1))) | I43: =IF($C43="","",SUMIFS(MOVIMIENTOS!$I:$I,MOVIMIENTOS!$D:$D,"Aporte",MOVIMIENTOS!$E:$E,"Anual",MOVIMIENTOS!$J:$J,$C43,MOVIMIENTOS!$B:$B,">="&DATE(2026,7,1),MOVIMIENTOS!$B:$B,"<"&DATE(2026,8,1))) | J43: =IF($C43="","",SUMIFS(MOVIMIENTOS!$I:$I,MOVIMIENTOS!$D:$D,"Aporte",MOVIMIENTOS!$E:$E,"Anual",MOVIMIENTOS!$J:$J,$C43,MOVIMIENTOS!$B:$B,">="&DATE(2026,8,1),MOVIMIENTOS!$B:$B,"<"&DATE(2026,9,1))) | K43: =IF($C43="","",SUMIFS(MOVIMIENTOS!$I:$I,MOVIMIENTOS!$D:$D,"Aporte",MOVIMIENTOS!$E:$E,"Anual",MOVIMIENTOS!$J:$J,$C43,MOVIMIENTOS!$B:$B,">="&DATE(2026,9,1),MOVIMIENTOS!$B:$B,"<"&DATE(2026,10,1))) | L43: =IF($C43="","",SUMIFS(MOVIMIENTOS!$I:$I,MOVIMIENTOS!$D:$D,"Aporte",MOVIMIENTOS!$E:$E,"Anual",MOVIMIENTOS!$J:$J,$C43,MOVIMIENTOS!$B:$B,">="&DATE(2026,10,1),MOVIMIENTOS!$B:$B,"<"&DATE(2026,11,1))) | M43: =IF($C43="","",SUMIFS(MOVIMIENTOS!$I:$I,MOVIMIENTOS!$D:$D,"Aporte",MOVIMIENTOS!$E:$E,"Anual",MOVIMIENTOS!$J:$J,$C43,MOVIMIENTOS!$B:$B,">="&DATE(2026,11,1),MOVIMIENTOS!$B:$B,"<"&DATE(2026,12,1))) | N43: =IF($C43="","",SUMIFS(MOVIMIENTOS!$I:$I,MOVIMIENTOS!$D:$D,"Aporte",MOVIMIENTOS!$E:$E,"Anual",MOVIMIENTOS!$J:$J,$C43,MOVIMIENTOS!$B:$B,">="&DATE(2026,12,1),MOVIMIENTOS!$B:$B,"<"&DATE(2026,13,1))) | O43: =IF($C43="","",SUM(E43:N43)) | P43: =IF($C43="","",SUMIFS(MOVIMIENTOS!$I:$I,MOVIMIENTOS!$D:$D,"Aporte",MOVIMIENTOS!$E:$E,"Extraordinaria",MOVIMIENTOS!$F:$F,P$4,MOVIMIENTOS!$J:$J,$C43)) | Q43: =IF($C43="","",SUMIFS(MOVIMIENTOS!$I:$I,MOVIMIENTOS!$D:$D,"Aporte",MOVIMIENTOS!$E:$E,"Extraordinaria",MOVIMIENTOS!$F:$F,Q$4,MOVIMIENTOS!$J:$J,$C43)) | R43: =IF($C43="","",SUMIFS(MOVIMIENTOS!$I:$I,MOVIMIENTOS!$D:$D,"Aporte",MOVIMIENTOS!$E:$E,"Extraordinaria",MOVIMIENTOS!$F:$F,R$4,MOVIMIENTOS!$J:$J,$C43)) | S43: =IF($C43="","",SUMIFS(MOVIMIENTOS!$I:$I,MOVIMIENTOS!$D:$D,"Aporte",MOVIMIENTOS!$E:$E,"Extraordinaria",MOVIMIENTOS!$F:$F,S$4,MOVIMIENTOS!$J:$J,$C43)) | T43: =IF($C43="","",SUMIFS(MOVIMIENTOS!$I:$I,MOVIMIENTOS!$D:$D,"Aporte",MOVIMIENTOS!$E:$E,"Extraordinaria",MOVIMIENTOS!$F:$F,T$4,MOVIMIENTOS!$J:$J,$C43)) | U43: =IF($C43="","",SUMIFS(MOVIMIENTOS!$I:$I,MOVIMIENTOS!$D:$D,"Aporte",MOVIMIENTOS!$E:$E,"Extraordinaria",MOVIMIENTOS!$F:$F,U$4,MOVIMIENTOS!$J:$J,$C43)) | V43: =IF($C43="","",SUMIFS(MOVIMIENTOS!$I:$I,MOVIMIENTOS!$D:$D,"Aporte",MOVIMIENTOS!$E:$E,"Extraordinaria",MOVIMIENTOS!$F:$F,V$4,MOVIMIENTOS!$J:$J,$C43)) | W43: =IF($C43="","",SUM(P43:V43)) | X43: =IF($C43="","",O43+W43)
E44: =IF($C44="","",SUMIFS(MOVIMIENTOS!$I:$I,MOVIMIENTOS!$D:$D,"Aporte",MOVIMIENTOS!$E:$E,"Anual",MOVIMIENTOS!$J:$J,$C44,MOVIMIENTOS!$B:$B,">="&DATE(2026,3,1),MOVIMIENTOS!$B:$B,"<"&DATE(2026,4,1))) | F44: =IF($C44="","",SUMIFS(MOVIMIENTOS!$I:$I,MOVIMIENTOS!$D:$D,"Aporte",MOVIMIENTOS!$E:$E,"Anual",MOVIMIENTOS!$J:$J,$C44,MOVIMIENTOS!$B:$B,">="&DATE(2026,4,1),MOVIMIENTOS!$B:$B,"<"&DATE(2026,5,1))) | G44: =IF($C44="","",SUMIFS(MOVIMIENTOS!$I:$I,MOVIMIENTOS!$D:$D,"Aporte",MOVIMIENTOS!$E:$E,"Anual",MOVIMIENTOS!$J:$J,$C44,MOVIMIENTOS!$B:$B,">="&DATE(2026,5,1),MOVIMIENTOS!$B:$B,"<"&DATE(2026,6,1))) | H44: =IF($C44="","",SUMIFS(MOVIMIENTOS!$I:$I,MOVIMIENTOS!$D:$D,"Aporte",MOVIMIENTOS!$E:$E,"Anual",MOVIMIENTOS!$J:$J,$C44,MOVIMIENTOS!$B:$B,">="&DATE(2026,6,1),MOVIMIENTOS!$B:$B,"<"&DATE(2026,7,1))) | I44: =IF($C44="","",SUMIFS(MOVIMIENTOS!$I:$I,MOVIMIENTOS!$D:$D,"Aporte",MOVIMIENTOS!$E:$E,"Anual",MOVIMIENTOS!$J:$J,$C44,MOVIMIENTOS!$B:$B,">="&DATE(2026,7,1),MOVIMIENTOS!$B:$B,"<"&DATE(2026,8,1))) | J44: =IF($C44="","",SUMIFS(MOVIMIENTOS!$I:$I,MOVIMIENTOS!$D:$D,"Aporte",MOVIMIENTOS!$E:$E,"Anual",MOVIMIENTOS!$J:$J,$C44,MOVIMIENTOS!$B:$B,">="&DATE(2026,8,1),MOVIMIENTOS!$B:$B,"<"&DATE(2026,9,1))) | K44: =IF($C44="","",SUMIFS(MOVIMIENTOS!$I:$I,MOVIMIENTOS!$D:$D,"Aporte",MOVIMIENTOS!$E:$E,"Anual",MOVIMIENTOS!$J:$J,$C44,MOVIMIENTOS!$B:$B,">="&DATE(2026,9,1),MOVIMIENTOS!$B:$B,"<"&DATE(2026,10,1))) | L44: =IF($C44="","",SUMIFS(MOVIMIENTOS!$I:$I,MOVIMIENTOS!$D:$D,"Aporte",MOVIMIENTOS!$E:$E,"Anual",MOVIMIENTOS!$J:$J,$C44,MOVIMIENTOS!$B:$B,">="&DATE(2026,10,1),MOVIMIENTOS!$B:$B,"<"&DATE(2026,11,1))) | M44: =IF($C44="","",SUMIFS(MOVIMIENTOS!$I:$I,MOVIMIENTOS!$D:$D,"Aporte",MOVIMIENTOS!$E:$E,"Anual",MOVIMIENTOS!$J:$J,$C44,MOVIMIENTOS!$B:$B,">="&DATE(2026,11,1),MOVIMIENTOS!$B:$B,"<"&DATE(2026,12,1))) | N44: =IF($C44="","",SUMIFS(MOVIMIENTOS!$I:$I,MOVIMIENTOS!$D:$D,"Aporte",MOVIMIENTOS!$E:$E,"Anual",MOVIMIENTOS!$J:$J,$C44,MOVIMIENTOS!$B:$B,">="&DATE(2026,12,1),MOVIMIENTOS!$B:$B,"<"&DATE(2026,13,1))) | O44: =IF($C44="","",SUM(E44:N44)) | P44: =IF($C44="","",SUMIFS(MOVIMIENTOS!$I:$I,MOVIMIENTOS!$D:$D,"Aporte",MOVIMIENTOS!$E:$E,"Extraordinaria",MOVIMIENTOS!$F:$F,P$4,MOVIMIENTOS!$J:$J,$C44)) | Q44: =IF($C44="","",SUMIFS(MOVIMIENTOS!$I:$I,MOVIMIENTOS!$D:$D,"Aporte",MOVIMIENTOS!$E:$E,"Extraordinaria",MOVIMIENTOS!$F:$F,Q$4,MOVIMIENTOS!$J:$J,$C44)) | R44: =IF($C44="","",SUMIFS(MOVIMIENTOS!$I:$I,MOVIMIENTOS!$D:$D,"Aporte",MOVIMIENTOS!$E:$E,"Extraordinaria",MOVIMIENTOS!$F:$F,R$4,MOVIMIENTOS!$J:$J,$C44)) | S44: =IF($C44="","",SUMIFS(MOVIMIENTOS!$I:$I,MOVIMIENTOS!$D:$D,"Aporte",MOVIMIENTOS!$E:$E,"Extraordinaria",MOVIMIENTOS!$F:$F,S$4,MOVIMIENTOS!$J:$J,$C44)) | T44: =IF($C44="","",SUMIFS(MOVIMIENTOS!$I:$I,MOVIMIENTOS!$D:$D,"Aporte",MOVIMIENTOS!$E:$E,"Extraordinaria",MOVIMIENTOS!$F:$F,T$4,MOVIMIENTOS!$J:$J,$C44)) | U44: =IF($C44="","",SUMIFS(MOVIMIENTOS!$I:$I,MOVIMIENTOS!$D:$D,"Aporte",MOVIMIENTOS!$E:$E,"Extraordinaria",MOVIMIENTOS!$F:$F,U$4,MOVIMIENTOS!$J:$J,$C44)) | V44: =IF($C44="","",SUMIFS(MOVIMIENTOS!$I:$I,MOVIMIENTOS!$D:$D,"Aporte",MOVIMIENTOS!$E:$E,"Extraordinaria",MOVIMIENTOS!$F:$F,V$4,MOVIMIENTOS!$J:$J,$C44)) | W44: =IF($C44="","",SUM(P44:V44)) | X44: =IF($C44="","",O44+W44)
E45: =IF($C45="","",SUMIFS(MOVIMIENTOS!$I:$I,MOVIMIENTOS!$D:$D,"Aporte",MOVIMIENTOS!$E:$E,"Anual",MOVIMIENTOS!$J:$J,$C45,MOVIMIENTOS!$B:$B,">="&DATE(2026,3,1),MOVIMIENTOS!$B:$B,"<"&DATE(2026,4,1))) | F45: =IF($C45="","",SUMIFS(MOVIMIENTOS!$I:$I,MOVIMIENTOS!$D:$D,"Aporte",MOVIMIENTOS!$E:$E,"Anual",MOVIMIENTOS!$J:$J,$C45,MOVIMIENTOS!$B:$B,">="&DATE(2026,4,1),MOVIMIENTOS!$B:$B,"<"&DATE(2026,5,1))) | G45: =IF($C45="","",SUMIFS(MOVIMIENTOS!$I:$I,MOVIMIENTOS!$D:$D,"Aporte",MOVIMIENTOS!$E:$E,"Anual",MOVIMIENTOS!$J:$J,$C45,MOVIMIENTOS!$B:$B,">="&DATE(2026,5,1),MOVIMIENTOS!$B:$B,"<"&DATE(2026,6,1))) | H45: =IF($C45="","",SUMIFS(MOVIMIENTOS!$I:$I,MOVIMIENTOS!$D:$D,"Aporte",MOVIMIENTOS!$E:$E,"Anual",MOVIMIENTOS!$J:$J,$C45,MOVIMIENTOS!$B:$B,">="&DATE(2026,6,1),MOVIMIENTOS!$B:$B,"<"&DATE(2026,7,1))) | I45: =IF($C45="","",SUMIFS(MOVIMIENTOS!$I:$I,MOVIMIENTOS!$D:$D,"Aporte",MOVIMIENTOS!$E:$E,"Anual",MOVIMIENTOS!$J:$J,$C45,MOVIMIENTOS!$B:$B,">="&DATE(2026,7,1),MOVIMIENTOS!$B:$B,"<"&DATE(2026,8,1))) | J45: =IF($C45="","",SUMIFS(MOVIMIENTOS!$I:$I,MOVIMIENTOS!$D:$D,"Aporte",MOVIMIENTOS!$E:$E,"Anual",MOVIMIENTOS!$J:$J,$C45,MOVIMIENTOS!$B:$B,">="&DATE(2026,8,1),MOVIMIENTOS!$B:$B,"<"&DATE(2026,9,1))) | K45: =IF($C45="","",SUMIFS(MOVIMIENTOS!$I:$I,MOVIMIENTOS!$D:$D,"Aporte",MOVIMIENTOS!$E:$E,"Anual",MOVIMIENTOS!$J:$J,$C45,MOVIMIENTOS!$B:$B,">="&DATE(2026,9,1),MOVIMIENTOS!$B:$B,"<"&DATE(2026,10,1))) | L45: =IF($C45="","",SUMIFS(MOVIMIENTOS!$I:$I,MOVIMIENTOS!$D:$D,"Aporte",MOVIMIENTOS!$E:$E,"Anual",MOVIMIENTOS!$J:$J,$C45,MOVIMIENTOS!$B:$B,">="&DATE(2026,10,1),MOVIMIENTOS!$B:$B,"<"&DATE(2026,11,1))) | M45: =IF($C45="","",SUMIFS(MOVIMIENTOS!$I:$I,MOVIMIENTOS!$D:$D,"Aporte",MOVIMIENTOS!$E:$E,"Anual",MOVIMIENTOS!$J:$J,$C45,MOVIMIENTOS!$B:$B,">="&DATE(2026,11,1),MOVIMIENTOS!$B:$B,"<"&DATE(2026,12,1))) | N45: =IF($C45="","",SUMIFS(MOVIMIENTOS!$I:$I,MOVIMIENTOS!$D:$D,"Aporte",MOVIMIENTOS!$E:$E,"Anual",MOVIMIENTOS!$J:$J,$C45,MOVIMIENTOS!$B:$B,">="&DATE(2026,12,1),MOVIMIENTOS!$B:$B,"<"&DATE(2026,13,1))) | O45: =IF($C45="","",SUM(E45:N45)) | P45: =IF($C45="","",SUMIFS(MOVIMIENTOS!$I:$I,MOVIMIENTOS!$D:$D,"Aporte",MOVIMIENTOS!$E:$E,"Extraordinaria",MOVIMIENTOS!$F:$F,P$4,MOVIMIENTOS!$J:$J,$C45)) | Q45: =IF($C45="","",SUMIFS(MOVIMIENTOS!$I:$I,MOVIMIENTOS!$D:$D,"Aporte",MOVIMIENTOS!$E:$E,"Extraordinaria",MOVIMIENTOS!$F:$F,Q$4,MOVIMIENTOS!$J:$J,$C45)) | R45: =IF($C45="","",SUMIFS(MOVIMIENTOS!$I:$I,MOVIMIENTOS!$D:$D,"Aporte",MOVIMIENTOS!$E:$E,"Extraordinaria",MOVIMIENTOS!$F:$F,R$4,MOVIMIENTOS!$J:$J,$C45)) | S45: =IF($C45="","",SUMIFS(MOVIMIENTOS!$I:$I,MOVIMIENTOS!$D:$D,"Aporte",MOVIMIENTOS!$E:$E,"Extraordinaria",MOVIMIENTOS!$F:$F,S$4,MOVIMIENTOS!$J:$J,$C45)) | T45: =IF($C45="","",SUMIFS(MOVIMIENTOS!$I:$I,MOVIMIENTOS!$D:$D,"Aporte",MOVIMIENTOS!$E:$E,"Extraordinaria",MOVIMIENTOS!$F:$F,T$4,MOVIMIENTOS!$J:$J,$C45)) | U45: =IF($C45="","",SUMIFS(MOVIMIENTOS!$I:$I,MOVIMIENTOS!$D:$D,"Aporte",MOVIMIENTOS!$E:$E,"Extraordinaria",MOVIMIENTOS!$F:$F,U$4,MOVIMIENTOS!$J:$J,$C45)) | V45: =IF($C45="","",SUMIFS(MOVIMIENTOS!$I:$I,MOVIMIENTOS!$D:$D,"Aporte",MOVIMIENTOS!$E:$E,"Extraordinaria",MOVIMIENTOS!$F:$F,V$4,MOVIMIENTOS!$J:$J,$C45)) | W45: =IF($C45="","",SUM(P45:V45)) | X45: =IF($C45="","",O45+W45)
E46: =IF($C46="","",SUMIFS(MOVIMIENTOS!$I:$I,MOVIMIENTOS!$D:$D,"Aporte",MOVIMIENTOS!$E:$E,"Anual",MOVIMIENTOS!$J:$J,$C46,MOVIMIENTOS!$B:$B,">="&DATE(2026,3,1),MOVIMIENTOS!$B:$B,"<"&DATE(2026,4,1))) | F46: =IF($C46="","",SUMIFS(MOVIMIENTOS!$I:$I,MOVIMIENTOS!$D:$D,"Aporte",MOVIMIENTOS!$E:$E,"Anual",MOVIMIENTOS!$J:$J,$C46,MOVIMIENTOS!$B:$B,">="&DATE(2026,4,1),MOVIMIENTOS!$B:$B,"<"&DATE(2026,5,1))) | G46: =IF($C46="","",SUMIFS(MOVIMIENTOS!$I:$I,MOVIMIENTOS!$D:$D,"Aporte",MOVIMIENTOS!$E:$E,"Anual",MOVIMIENTOS!$J:$J,$C46,MOVIMIENTOS!$B:$B,">="&DATE(2026,5,1),MOVIMIENTOS!$B:$B,"<"&DATE(2026,6,1))) | H46: =IF($C46="","",SUMIFS(MOVIMIENTOS!$I:$I,MOVIMIENTOS!$D:$D,"Aporte",MOVIMIENTOS!$E:$E,"Anual",MOVIMIENTOS!$J:$J,$C46,MOVIMIENTOS!$B:$B,">="&DATE(2026,6,1),MOVIMIENTOS!$B:$B,"<"&DATE(2026,7,1))) | I46: =IF($C46="","",SUMIFS(MOVIMIENTOS!$I:$I,MOVIMIENTOS!$D:$D,"Aporte",MOVIMIENTOS!$E:$E,"Anual",MOVIMIENTOS!$J:$J,$C46,MOVIMIENTOS!$B:$B,">="&DATE(2026,7,1),MOVIMIENTOS!$B:$B,"<"&DATE(2026,8,1))) | J46: =IF($C46="","",SUMIFS(MOVIMIENTOS!$I:$I,MOVIMIENTOS!$D:$D,"Aporte",MOVIMIENTOS!$E:$E,"Anual",MOVIMIENTOS!$J:$J,$C46,MOVIMIENTOS!$B:$B,">="&DATE(2026,8,1),MOVIMIENTOS!$B:$B,"<"&DATE(2026,9,1))) | K46: =IF($C46="","",SUMIFS(MOVIMIENTOS!$I:$I,MOVIMIENTOS!$D:$D,"Aporte",MOVIMIENTOS!$E:$E,"Anual",MOVIMIENTOS!$J:$J,$C46,MOVIMIENTOS!$B:$B,">="&DATE(2026,9,1),MOVIMIENTOS!$B:$B,"<"&DATE(2026,10,1))) | L46: =IF($C46="","",SUMIFS(MOVIMIENTOS!$I:$I,MOVIMIENTOS!$D:$D,"Aporte",MOVIMIENTOS!$E:$E,"Anual",MOVIMIENTOS!$J:$J,$C46,MOVIMIENTOS!$B:$B,">="&DATE(2026,10,1),MOVIMIENTOS!$B:$B,"<"&DATE(2026,11,1))) | M46: =IF($C46="","",SUMIFS(MOVIMIENTOS!$I:$I,MOVIMIENTOS!$D:$D,"Aporte",MOVIMIENTOS!$E:$E,"Anual",MOVIMIENTOS!$J:$J,$C46,MOVIMIENTOS!$B:$B,">="&DATE(2026,11,1),MOVIMIENTOS!$B:$B,"<"&DATE(2026,12,1))) | N46: =IF($C46="","",SUMIFS(MOVIMIENTOS!$I:$I,MOVIMIENTOS!$D:$D,"Aporte",MOVIMIENTOS!$E:$E,"Anual",MOVIMIENTOS!$J:$J,$C46,MOVIMIENTOS!$B:$B,">="&DATE(2026,12,1),MOVIMIENTOS!$B:$B,"<"&DATE(2026,13,1))) | O46: =IF($C46="","",SUM(E46:N46)) | P46: =IF($C46="","",SUMIFS(MOVIMIENTOS!$I:$I,MOVIMIENTOS!$D:$D,"Aporte",MOVIMIENTOS!$E:$E,"Extraordinaria",MOVIMIENTOS!$F:$F,P$4,MOVIMIENTOS!$J:$J,$C46)) | Q46: =IF($C46="","",SUMIFS(MOVIMIENTOS!$I:$I,MOVIMIENTOS!$D:$D,"Aporte",MOVIMIENTOS!$E:$E,"Extraordinaria",MOVIMIENTOS!$F:$F,Q$4,MOVIMIENTOS!$J:$J,$C46)) | R46: =IF($C46="","",SUMIFS(MOVIMIENTOS!$I:$I,MOVIMIENTOS!$D:$D,"Aporte",MOVIMIENTOS!$E:$E,"Extraordinaria",MOVIMIENTOS!$F:$F,R$4,MOVIMIENTOS!$J:$J,$C46)) | S46: =IF($C46="","",SUMIFS(MOVIMIENTOS!$I:$I,MOVIMIENTOS!$D:$D,"Aporte",MOVIMIENTOS!$E:$E,"Extraordinaria",MOVIMIENTOS!$F:$F,S$4,MOVIMIENTOS!$J:$J,$C46)) | T46: =IF($C46="","",SUMIFS(MOVIMIENTOS!$I:$I,MOVIMIENTOS!$D:$D,"Aporte",MOVIMIENTOS!$E:$E,"Extraordinaria",MOVIMIENTOS!$F:$F,T$4,MOVIMIENTOS!$J:$J,$C46)) | U46: =IF($C46="","",SUMIFS(MOVIMIENTOS!$I:$I,MOVIMIENTOS!$D:$D,"Aporte",MOVIMIENTOS!$E:$E,"Extraordinaria",MOVIMIENTOS!$F:$F,U$4,MOVIMIENTOS!$J:$J,$C46)) | V46: =IF($C46="","",SUMIFS(MOVIMIENTOS!$I:$I,MOVIMIENTOS!$D:$D,"Aporte",MOVIMIENTOS!$E:$E,"Extraordinaria",MOVIMIENTOS!$F:$F,V$4,MOVIMIENTOS!$J:$J,$C46)) | W46: =IF($C46="","",SUM(P46:V46)) | X46: =IF($C46="","",O46+W46)
E47: =IF($C47="","",SUMIFS(MOVIMIENTOS!$I:$I,MOVIMIENTOS!$D:$D,"Aporte",MOVIMIENTOS!$E:$E,"Anual",MOVIMIENTOS!$J:$J,$C47,MOVIMIENTOS!$B:$B,">="&DATE(2026,3,1),MOVIMIENTOS!$B:$B,"<"&DATE(2026,4,1))) | F47: =IF($C47="","",SUMIFS(MOVIMIENTOS!$I:$I,MOVIMIENTOS!$D:$D,"Aporte",MOVIMIENTOS!$E:$E,"Anual",MOVIMIENTOS!$J:$J,$C47,MOVIMIENTOS!$B:$B,">="&DATE(2026,4,1),MOVIMIENTOS!$B:$B,"<"&DATE(2026,5,1))) | G47: =IF($C47="","",SUMIFS(MOVIMIENTOS!$I:$I,MOVIMIENTOS!$D:$D,"Aporte",MOVIMIENTOS!$E:$E,"Anual",MOVIMIENTOS!$J:$J,$C47,MOVIMIENTOS!$B:$B,">="&DATE(2026,5,1),MOVIMIENTOS!$B:$B,"<"&DATE(2026,6,1))) | H47: =IF($C47="","",SUMIFS(MOVIMIENTOS!$I:$I,MOVIMIENTOS!$D:$D,"Aporte",MOVIMIENTOS!$E:$E,"Anual",MOVIMIENTOS!$J:$J,$C47,MOVIMIENTOS!$B:$B,">="&DATE(2026,6,1),MOVIMIENTOS!$B:$B,"<"&DATE(2026,7,1))) | I47: =IF($C47="","",SUMIFS(MOVIMIENTOS!$I:$I,MOVIMIENTOS!$D:$D,"Aporte",MOVIMIENTOS!$E:$E,"Anual",MOVIMIENTOS!$J:$J,$C47,MOVIMIENTOS!$B:$B,">="&DATE(2026,7,1),MOVIMIENTOS!$B:$B,"<"&DATE(2026,8,1))) | J47: =IF($C47="","",SUMIFS(MOVIMIENTOS!$I:$I,MOVIMIENTOS!$D:$D,"Aporte",MOVIMIENTOS!$E:$E,"Anual",MOVIMIENTOS!$J:$J,$C47,MOVIMIENTOS!$B:$B,">="&DATE(2026,8,1),MOVIMIENTOS!$B:$B,"<"&DATE(2026,9,1))) | K47: =IF($C47="","",SUMIFS(MOVIMIENTOS!$I:$I,MOVIMIENTOS!$D:$D,"Aporte",MOVIMIENTOS!$E:$E,"Anual",MOVIMIENTOS!$J:$J,$C47,MOVIMIENTOS!$B:$B,">="&DATE(2026,9,1),MOVIMIENTOS!$B:$B,"<"&DATE(2026,10,1))) | L47: =IF($C47="","",SUMIFS(MOVIMIENTOS!$I:$I,MOVIMIENTOS!$D:$D,"Aporte",MOVIMIENTOS!$E:$E,"Anual",MOVIMIENTOS!$J:$J,$C47,MOVIMIENTOS!$B:$B,">="&DATE(2026,10,1),MOVIMIENTOS!$B:$B,"<"&DATE(2026,11,1))) | M47: =IF($C47="","",SUMIFS(MOVIMIENTOS!$I:$I,MOVIMIENTOS!$D:$D,"Aporte",MOVIMIENTOS!$E:$E,"Anual",MOVIMIENTOS!$J:$J,$C47,MOVIMIENTOS!$B:$B,">="&DATE(2026,11,1),MOVIMIENTOS!$B:$B,"<"&DATE(2026,12,1))) | N47: =IF($C47="","",SUMIFS(MOVIMIENTOS!$I:$I,MOVIMIENTOS!$D:$D,"Aporte",MOVIMIENTOS!$E:$E,"Anual",MOVIMIENTOS!$J:$J,$C47,MOVIMIENTOS!$B:$B,">="&DATE(2026,12,1),MOVIMIENTOS!$B:$B,"<"&DATE(2026,13,1))) | O47: =IF($C47="","",SUM(E47:N47)) | P47: =IF($C47="","",SUMIFS(MOVIMIENTOS!$I:$I,MOVIMIENTOS!$D:$D,"Aporte",MOVIMIENTOS!$E:$E,"Extraordinaria",MOVIMIENTOS!$F:$F,P$4,MOVIMIENTOS!$J:$J,$C47)) | Q47: =IF($C47="","",SUMIFS(MOVIMIENTOS!$I:$I,MOVIMIENTOS!$D:$D,"Aporte",MOVIMIENTOS!$E:$E,"Extraordinaria",MOVIMIENTOS!$F:$F,Q$4,MOVIMIENTOS!$J:$J,$C47)) | R47: =IF($C47="","",SUMIFS(MOVIMIENTOS!$I:$I,MOVIMIENTOS!$D:$D,"Aporte",MOVIMIENTOS!$E:$E,"Extraordinaria",MOVIMIENTOS!$F:$F,R$4,MOVIMIENTOS!$J:$J,$C47)) | S47: =IF($C47="","",SUMIFS(MOVIMIENTOS!$I:$I,MOVIMIENTOS!$D:$D,"Aporte",MOVIMIENTOS!$E:$E,"Extraordinaria",MOVIMIENTOS!$F:$F,S$4,MOVIMIENTOS!$J:$J,$C47)) | T47: =IF($C47="","",SUMIFS(MOVIMIENTOS!$I:$I,MOVIMIENTOS!$D:$D,"Aporte",MOVIMIENTOS!$E:$E,"Extraordinaria",MOVIMIENTOS!$F:$F,T$4,MOVIMIENTOS!$J:$J,$C47)) | U47: =IF($C47="","",SUMIFS(MOVIMIENTOS!$I:$I,MOVIMIENTOS!$D:$D,"Aporte",MOVIMIENTOS!$E:$E,"Extraordinaria",MOVIMIENTOS!$F:$F,U$4,MOVIMIENTOS!$J:$J,$C47)) | V47: =IF($C47="","",SUMIFS(MOVIMIENTOS!$I:$I,MOVIMIENTOS!$D:$D,"Aporte",MOVIMIENTOS!$E:$E,"Extraordinaria",MOVIMIENTOS!$F:$F,V$4,MOVIMIENTOS!$J:$J,$C47)) | W47: =IF($C47="","",SUM(P47:V47)) | X47: =IF($C47="","",O47+W47)
E48: =IF($C48="","",SUMIFS(MOVIMIENTOS!$I:$I,MOVIMIENTOS!$D:$D,"Aporte",MOVIMIENTOS!$E:$E,"Anual",MOVIMIENTOS!$J:$J,$C48,MOVIMIENTOS!$B:$B,">="&DATE(2026,3,1),MOVIMIENTOS!$B:$B,"<"&DATE(2026,4,1))) | F48: =IF($C48="","",SUMIFS(MOVIMIENTOS!$I:$I,MOVIMIENTOS!$D:$D,"Aporte",MOVIMIENTOS!$E:$E,"Anual",MOVIMIENTOS!$J:$J,$C48,MOVIMIENTOS!$B:$B,">="&DATE(2026,4,1),MOVIMIENTOS!$B:$B,"<"&DATE(2026,5,1))) | G48: =IF($C48="","",SUMIFS(MOVIMIENTOS!$I:$I,MOVIMIENTOS!$D:$D,"Aporte",MOVIMIENTOS!$E:$E,"Anual",MOVIMIENTOS!$J:$J,$C48,MOVIMIENTOS!$B:$B,">="&DATE(2026,5,1),MOVIMIENTOS!$B:$B,"<"&DATE(2026,6,1))) | H48: =IF($C48="","",SUMIFS(MOVIMIENTOS!$I:$I,MOVIMIENTOS!$D:$D,"Aporte",MOVIMIENTOS!$E:$E,"Anual",MOVIMIENTOS!$J:$J,$C48,MOVIMIENTOS!$B:$B,">="&DATE(2026,6,1),MOVIMIENTOS!$B:$B,"<"&DATE(2026,7,1))) | I48: =IF($C48="","",SUMIFS(MOVIMIENTOS!$I:$I,MOVIMIENTOS!$D:$D,"Aporte",MOVIMIENTOS!$E:$E,"Anual",MOVIMIENTOS!$J:$J,$C48,MOVIMIENTOS!$B:$B,">="&DATE(2026,7,1),MOVIMIENTOS!$B:$B,"<"&DATE(2026,8,1))) | J48: =IF($C48="","",SUMIFS(MOVIMIENTOS!$I:$I,MOVIMIENTOS!$D:$D,"Aporte",MOVIMIENTOS!$E:$E,"Anual",MOVIMIENTOS!$J:$J,$C48,MOVIMIENTOS!$B:$B,">="&DATE(2026,8,1),MOVIMIENTOS!$B:$B,"<"&DATE(2026,9,1))) | K48: =IF($C48="","",SUMIFS(MOVIMIENTOS!$I:$I,MOVIMIENTOS!$D:$D,"Aporte",MOVIMIENTOS!$E:$E,"Anual",MOVIMIENTOS!$J:$J,$C48,MOVIMIENTOS!$B:$B,">="&DATE(2026,9,1),MOVIMIENTOS!$B:$B,"<"&DATE(2026,10,1))) | L48: =IF($C48="","",SUMIFS(MOVIMIENTOS!$I:$I,MOVIMIENTOS!$D:$D,"Aporte",MOVIMIENTOS!$E:$E,"Anual",MOVIMIENTOS!$J:$J,$C48,MOVIMIENTOS!$B:$B,">="&DATE(2026,10,1),MOVIMIENTOS!$B:$B,"<"&DATE(2026,11,1))) | M48: =IF($C48="","",SUMIFS(MOVIMIENTOS!$I:$I,MOVIMIENTOS!$D:$D,"Aporte",MOVIMIENTOS!$E:$E,"Anual",MOVIMIENTOS!$J:$J,$C48,MOVIMIENTOS!$B:$B,">="&DATE(2026,11,1),MOVIMIENTOS!$B:$B,"<"&DATE(2026,12,1))) | N48: =IF($C48="","",SUMIFS(MOVIMIENTOS!$I:$I,MOVIMIENTOS!$D:$D,"Aporte",MOVIMIENTOS!$E:$E,"Anual",MOVIMIENTOS!$J:$J,$C48,MOVIMIENTOS!$B:$B,">="&DATE(2026,12,1),MOVIMIENTOS!$B:$B,"<"&DATE(2026,13,1))) | O48: =IF($C48="","",SUM(E48:N48)) | P48: =IF($C48="","",SUMIFS(MOVIMIENTOS!$I:$I,MOVIMIENTOS!$D:$D,"Aporte",MOVIMIENTOS!$E:$E,"Extraordinaria",MOVIMIENTOS!$F:$F,P$4,MOVIMIENTOS!$J:$J,$C48)) | Q48: =IF($C48="","",SUMIFS(MOVIMIENTOS!$I:$I,MOVIMIENTOS!$D:$D,"Aporte",MOVIMIENTOS!$E:$E,"Extraordinaria",MOVIMIENTOS!$F:$F,Q$4,MOVIMIENTOS!$J:$J,$C48)) | R48: =IF($C48="","",SUMIFS(MOVIMIENTOS!$I:$I,MOVIMIENTOS!$D:$D,"Aporte",MOVIMIENTOS!$E:$E,"Extraordinaria",MOVIMIENTOS!$F:$F,R$4,MOVIMIENTOS!$J:$J,$C48)) | S48: =IF($C48="","",SUMIFS(MOVIMIENTOS!$I:$I,MOVIMIENTOS!$D:$D,"Aporte",MOVIMIENTOS!$E:$E,"Extraordinaria",MOVIMIENTOS!$F:$F,S$4,MOVIMIENTOS!$J:$J,$C48)) | T48: =IF($C48="","",SUMIFS(MOVIMIENTOS!$I:$I,MOVIMIENTOS!$D:$D,"Aporte",MOVIMIENTOS!$E:$E,"Extraordinaria",MOVIMIENTOS!$F:$F,T$4,MOVIMIENTOS!$J:$J,$C48)) | U48: =IF($C48="","",SUMIFS(MOVIMIENTOS!$I:$I,MOVIMIENTOS!$D:$D,"Aporte",MOVIMIENTOS!$E:$E,"Extraordinaria",MOVIMIENTOS!$F:$F,U$4,MOVIMIENTOS!$J:$J,$C48)) | V48: =IF($C48="","",SUMIFS(MOVIMIENTOS!$I:$I,MOVIMIENTOS!$D:$D,"Aporte",MOVIMIENTOS!$E:$E,"Extraordinaria",MOVIMIENTOS!$F:$F,V$4,MOVIMIENTOS!$J:$J,$C48)) | W48: =IF($C48="","",SUM(P48:V48)) | X48: =IF($C48="","",O48+W48)
E49: =IF($C49="","",SUMIFS(MOVIMIENTOS!$I:$I,MOVIMIENTOS!$D:$D,"Aporte",MOVIMIENTOS!$E:$E,"Anual",MOVIMIENTOS!$J:$J,$C49,MOVIMIENTOS!$B:$B,">="&DATE(2026,3,1),MOVIMIENTOS!$B:$B,"<"&DATE(2026,4,1))) | F49: =IF($C49="","",SUMIFS(MOVIMIENTOS!$I:$I,MOVIMIENTOS!$D:$D,"Aporte",MOVIMIENTOS!$E:$E,"Anual",MOVIMIENTOS!$J:$J,$C49,MOVIMIENTOS!$B:$B,">="&DATE(2026,4,1),MOVIMIENTOS!$B:$B,"<"&DATE(2026,5,1))) | G49: =IF($C49="","",SUMIFS(MOVIMIENTOS!$I:$I,MOVIMIENTOS!$D:$D,"Aporte",MOVIMIENTOS!$E:$E,"Anual",MOVIMIENTOS!$J:$J,$C49,MOVIMIENTOS!$B:$B,">="&DATE(2026,5,1),MOVIMIENTOS!$B:$B,"<"&DATE(2026,6,1))) | H49: =IF($C49="","",SUMIFS(MOVIMIENTOS!$I:$I,MOVIMIENTOS!$D:$D,"Aporte",MOVIMIENTOS!$E:$E,"Anual",MOVIMIENTOS!$J:$J,$C49,MOVIMIENTOS!$B:$B,">="&DATE(2026,6,1),MOVIMIENTOS!$B:$B,"<"&DATE(2026,7,1))) | I49: =IF($C49="","",SUMIFS(MOVIMIENTOS!$I:$I,MOVIMIENTOS!$D:$D,"Aporte",MOVIMIENTOS!$E:$E,"Anual",MOVIMIENTOS!$J:$J,$C49,MOVIMIENTOS!$B:$B,">="&DATE(2026,7,1),MOVIMIENTOS!$B:$B,"<"&DATE(2026,8,1))) | J49: =IF($C49="","",SUMIFS(MOVIMIENTOS!$I:$I,MOVIMIENTOS!$D:$D,"Aporte",MOVIMIENTOS!$E:$E,"Anual",MOVIMIENTOS!$J:$J,$C49,MOVIMIENTOS!$B:$B,">="&DATE(2026,8,1),MOVIMIENTOS!$B:$B,"<"&DATE(2026,9,1))) | K49: =IF($C49="","",SUMIFS(MOVIMIENTOS!$I:$I,MOVIMIENTOS!$D:$D,"Aporte",MOVIMIENTOS!$E:$E,"Anual",MOVIMIENTOS!$J:$J,$C49,MOVIMIENTOS!$B:$B,">="&DATE(2026,9,1),MOVIMIENTOS!$B:$B,"<"&DATE(2026,10,1))) | L49: =IF($C49="","",SUMIFS(MOVIMIENTOS!$I:$I,MOVIMIENTOS!$D:$D,"Aporte",MOVIMIENTOS!$E:$E,"Anual",MOVIMIENTOS!$J:$J,$C49,MOVIMIENTOS!$B:$B,">="&DATE(2026,10,1),MOVIMIENTOS!$B:$B,"<"&DATE(2026,11,1))) | M49: =IF($C49="","",SUMIFS(MOVIMIENTOS!$I:$I,MOVIMIENTOS!$D:$D,"Aporte",MOVIMIENTOS!$E:$E,"Anual",MOVIMIENTOS!$J:$J,$C49,MOVIMIENTOS!$B:$B,">="&DATE(2026,11,1),MOVIMIENTOS!$B:$B,"<"&DATE(2026,12,1))) | N49: =IF($C49="","",SUMIFS(MOVIMIENTOS!$I:$I,MOVIMIENTOS!$D:$D,"Aporte",MOVIMIENTOS!$E:$E,"Anual",MOVIMIENTOS!$J:$J,$C49,MOVIMIENTOS!$B:$B,">="&DATE(2026,12,1),MOVIMIENTOS!$B:$B,"<"&DATE(2026,13,1))) | O49: =IF($C49="","",SUM(E49:N49)) | P49: =IF($C49="","",SUMIFS(MOVIMIENTOS!$I:$I,MOVIMIENTOS!$D:$D,"Aporte",MOVIMIENTOS!$E:$E,"Extraordinaria",MOVIMIENTOS!$F:$F,P$4,MOVIMIENTOS!$J:$J,$C49)) | Q49: =IF($C49="","",SUMIFS(MOVIMIENTOS!$I:$I,MOVIMIENTOS!$D:$D,"Aporte",MOVIMIENTOS!$E:$E,"Extraordinaria",MOVIMIENTOS!$F:$F,Q$4,MOVIMIENTOS!$J:$J,$C49)) | R49: =IF($C49="","",SUMIFS(MOVIMIENTOS!$I:$I,MOVIMIENTOS!$D:$D,"Aporte",MOVIMIENTOS!$E:$E,"Extraordinaria",MOVIMIENTOS!$F:$F,R$4,MOVIMIENTOS!$J:$J,$C49)) | S49: =IF($C49="","",SUMIFS(MOVIMIENTOS!$I:$I,MOVIMIENTOS!$D:$D,"Aporte",MOVIMIENTOS!$E:$E,"Extraordinaria",MOVIMIENTOS!$F:$F,S$4,MOVIMIENTOS!$J:$J,$C49)) | T49: =IF($C49="","",SUMIFS(MOVIMIENTOS!$I:$I,MOVIMIENTOS!$D:$D,"Aporte",MOVIMIENTOS!$E:$E,"Extraordinaria",MOVIMIENTOS!$F:$F,T$4,MOVIMIENTOS!$J:$J,$C49)) | U49: =IF($C49="","",SUMIFS(MOVIMIENTOS!$I:$I,MOVIMIENTOS!$D:$D,"Aporte",MOVIMIENTOS!$E:$E,"Extraordinaria",MOVIMIENTOS!$F:$F,U$4,MOVIMIENTOS!$J:$J,$C49)) | V49: =IF($C49="","",SUMIFS(MOVIMIENTOS!$I:$I,MOVIMIENTOS!$D:$D,"Aporte",MOVIMIENTOS!$E:$E,"Extraordinaria",MOVIMIENTOS!$F:$F,V$4,MOVIMIENTOS!$J:$J,$C49)) | W49: =IF($C49="","",SUM(P49:V49)) | X49: =IF($C49="","",O49+W49)
E50: =IF($C50="","",SUMIFS(MOVIMIENTOS!$I:$I,MOVIMIENTOS!$D:$D,"Aporte",MOVIMIENTOS!$E:$E,"Anual",MOVIMIENTOS!$J:$J,$C50,MOVIMIENTOS!$B:$B,">="&DATE(2026,3,1),MOVIMIENTOS!$B:$B,"<"&DATE(2026,4,1))) | F50: =IF($C50="","",SUMIFS(MOVIMIENTOS!$I:$I,MOVIMIENTOS!$D:$D,"Aporte",MOVIMIENTOS!$E:$E,"Anual",MOVIMIENTOS!$J:$J,$C50,MOVIMIENTOS!$B:$B,">="&DATE(2026,4,1),MOVIMIENTOS!$B:$B,"<"&DATE(2026,5,1))) | G50: =IF($C50="","",SUMIFS(MOVIMIENTOS!$I:$I,MOVIMIENTOS!$D:$D,"Aporte",MOVIMIENTOS!$E:$E,"Anual",MOVIMIENTOS!$J:$J,$C50,MOVIMIENTOS!$B:$B,">="&DATE(2026,5,1),MOVIMIENTOS!$B:$B,"<"&DATE(2026,6,1))) | H50: =IF($C50="","",SUMIFS(MOVIMIENTOS!$I:$I,MOVIMIENTOS!$D:$D,"Aporte",MOVIMIENTOS!$E:$E,"Anual",MOVIMIENTOS!$J:$J,$C50,MOVIMIENTOS!$B:$B,">="&DATE(2026,6,1),MOVIMIENTOS!$B:$B,"<"&DATE(2026,7,1))) | I50: =IF($C50="","",SUMIFS(MOVIMIENTOS!$I:$I,MOVIMIENTOS!$D:$D,"Aporte",MOVIMIENTOS!$E:$E,"Anual",MOVIMIENTOS!$J:$J,$C50,MOVIMIENTOS!$B:$B,">="&DATE(2026,7,1),MOVIMIENTOS!$B:$B,"<"&DATE(2026,8,1))) | J50: =IF($C50="","",SUMIFS(MOVIMIENTOS!$I:$I,MOVIMIENTOS!$D:$D,"Aporte",MOVIMIENTOS!$E:$E,"Anual",MOVIMIENTOS!$J:$J,$C50,MOVIMIENTOS!$B:$B,">="&DATE(2026,8,1),MOVIMIENTOS!$B:$B,"<"&DATE(2026,9,1))) | K50: =IF($C50="","",SUMIFS(MOVIMIENTOS!$I:$I,MOVIMIENTOS!$D:$D,"Aporte",MOVIMIENTOS!$E:$E,"Anual",MOVIMIENTOS!$J:$J,$C50,MOVIMIENTOS!$B:$B,">="&DATE(2026,9,1),MOVIMIENTOS!$B:$B,"<"&DATE(2026,10,1))) | L50: =IF($C50="","",SUMIFS(MOVIMIENTOS!$I:$I,MOVIMIENTOS!$D:$D,"Aporte",MOVIMIENTOS!$E:$E,"Anual",MOVIMIENTOS!$J:$J,$C50,MOVIMIENTOS!$B:$B,">="&DATE(2026,10,1),MOVIMIENTOS!$B:$B,"<"&DATE(2026,11,1))) | M50: =IF($C50="","",SUMIFS(MOVIMIENTOS!$I:$I,MOVIMIENTOS!$D:$D,"Aporte",MOVIMIENTOS!$E:$E,"Anual",MOVIMIENTOS!$J:$J,$C50,MOVIMIENTOS!$B:$B,">="&DATE(2026,11,1),MOVIMIENTOS!$B:$B,"<"&DATE(2026,12,1))) | N50: =IF($C50="","",SUMIFS(MOVIMIENTOS!$I:$I,MOVIMIENTOS!$D:$D,"Aporte",MOVIMIENTOS!$E:$E,"Anual",MOVIMIENTOS!$J:$J,$C50,MOVIMIENTOS!$B:$B,">="&DATE(2026,12,1),MOVIMIENTOS!$B:$B,"<"&DATE(2026,13,1))) | O50: =IF($C50="","",SUM(E50:N50)) | P50: =IF($C50="","",SUMIFS(MOVIMIENTOS!$I:$I,MOVIMIENTOS!$D:$D,"Aporte",MOVIMIENTOS!$E:$E,"Extraordinaria",MOVIMIENTOS!$F:$F,P$4,MOVIMIENTOS!$J:$J,$C50)) | Q50: =IF($C50="","",SUMIFS(MOVIMIENTOS!$I:$I,MOVIMIENTOS!$D:$D,"Aporte",MOVIMIENTOS!$E:$E,"Extraordinaria",MOVIMIENTOS!$F:$F,Q$4,MOVIMIENTOS!$J:$J,$C50)) | R50: =IF($C50="","",SUMIFS(MOVIMIENTOS!$I:$I,MOVIMIENTOS!$D:$D,"Aporte",MOVIMIENTOS!$E:$E,"Extraordinaria",MOVIMIENTOS!$F:$F,R$4,MOVIMIENTOS!$J:$J,$C50)) | S50: =IF($C50="","",SUMIFS(MOVIMIENTOS!$I:$I,MOVIMIENTOS!$D:$D,"Aporte",MOVIMIENTOS!$E:$E,"Extraordinaria",MOVIMIENTOS!$F:$F,S$4,MOVIMIENTOS!$J:$J,$C50)) | T50: =IF($C50="","",SUMIFS(MOVIMIENTOS!$I:$I,MOVIMIENTOS!$D:$D,"Aporte",MOVIMIENTOS!$E:$E,"Extraordinaria",MOVIMIENTOS!$F:$F,T$4,MOVIMIENTOS!$J:$J,$C50)) | U50: =IF($C50="","",SUMIFS(MOVIMIENTOS!$I:$I,MOVIMIENTOS!$D:$D,"Aporte",MOVIMIENTOS!$E:$E,"Extraordinaria",MOVIMIENTOS!$F:$F,U$4,MOVIMIENTOS!$J:$J,$C50)) | V50: =IF($C50="","",SUMIFS(MOVIMIENTOS!$I:$I,MOVIMIENTOS!$D:$D,"Aporte",MOVIMIENTOS!$E:$E,"Extraordinaria",MOVIMIENTOS!$F:$F,V$4,MOVIMIENTOS!$J:$J,$C50)) | W50: =IF($C50="","",SUM(P50:V50)) | X50: =IF($C50="","",O50+W50)
E51: =IF($C51="","",SUMIFS(MOVIMIENTOS!$I:$I,MOVIMIENTOS!$D:$D,"Aporte",MOVIMIENTOS!$E:$E,"Anual",MOVIMIENTOS!$J:$J,$C51,MOVIMIENTOS!$B:$B,">="&DATE(2026,3,1),MOVIMIENTOS!$B:$B,"<"&DATE(2026,4,1))) | F51: =IF($C51="","",SUMIFS(MOVIMIENTOS!$I:$I,MOVIMIENTOS!$D:$D,"Aporte",MOVIMIENTOS!$E:$E,"Anual",MOVIMIENTOS!$J:$J,$C51,MOVIMIENTOS!$B:$B,">="&DATE(2026,4,1),MOVIMIENTOS!$B:$B,"<"&DATE(2026,5,1))) | G51: =IF($C51="","",SUMIFS(MOVIMIENTOS!$I:$I,MOVIMIENTOS!$D:$D,"Aporte",MOVIMIENTOS!$E:$E,"Anual",MOVIMIENTOS!$J:$J,$C51,MOVIMIENTOS!$B:$B,">="&DATE(2026,5,1),MOVIMIENTOS!$B:$B,"<"&DATE(2026,6,1))) | H51: =IF($C51="","",SUMIFS(MOVIMIENTOS!$I:$I,MOVIMIENTOS!$D:$D,"Aporte",MOVIMIENTOS!$E:$E,"Anual",MOVIMIENTOS!$J:$J,$C51,MOVIMIENTOS!$B:$B,">="&DATE(2026,6,1),MOVIMIENTOS!$B:$B,"<"&DATE(2026,7,1))) | I51: =IF($C51="","",SUMIFS(MOVIMIENTOS!$I:$I,MOVIMIENTOS!$D:$D,"Aporte",MOVIMIENTOS!$E:$E,"Anual",MOVIMIENTOS!$J:$J,$C51,MOVIMIENTOS!$B:$B,">="&DATE(2026,7,1),MOVIMIENTOS!$B:$B,"<"&DATE(2026,8,1))) | J51: =IF($C51="","",SUMIFS(MOVIMIENTOS!$I:$I,MOVIMIENTOS!$D:$D,"Aporte",MOVIMIENTOS!$E:$E,"Anual",MOVIMIENTOS!$J:$J,$C51,MOVIMIENTOS!$B:$B,">="&DATE(2026,8,1),MOVIMIENTOS!$B:$B,"<"&DATE(2026,9,1))) | K51: =IF($C51="","",SUMIFS(MOVIMIENTOS!$I:$I,MOVIMIENTOS!$D:$D,"Aporte",MOVIMIENTOS!$E:$E,"Anual",MOVIMIENTOS!$J:$J,$C51,MOVIMIENTOS!$B:$B,">="&DATE(2026,9,1),MOVIMIENTOS!$B:$B,"<"&DATE(2026,10,1))) | L51: =IF($C51="","",SUMIFS(MOVIMIENTOS!$I:$I,MOVIMIENTOS!$D:$D,"Aporte",MOVIMIENTOS!$E:$E,"Anual",MOVIMIENTOS!$J:$J,$C51,MOVIMIENTOS!$B:$B,">="&DATE(2026,10,1),MOVIMIENTOS!$B:$B,"<"&DATE(2026,11,1))) | M51: =IF($C51="","",SUMIFS(MOVIMIENTOS!$I:$I,MOVIMIENTOS!$D:$D,"Aporte",MOVIMIENTOS!$E:$E,"Anual",MOVIMIENTOS!$J:$J,$C51,MOVIMIENTOS!$B:$B,">="&DATE(2026,11,1),MOVIMIENTOS!$B:$B,"<"&DATE(2026,12,1))) | N51: =IF($C51="","",SUMIFS(MOVIMIENTOS!$I:$I,MOVIMIENTOS!$D:$D,"Aporte",MOVIMIENTOS!$E:$E,"Anual",MOVIMIENTOS!$J:$J,$C51,MOVIMIENTOS!$B:$B,">="&DATE(2026,12,1),MOVIMIENTOS!$B:$B,"<"&DATE(2026,13,1))) | O51: =IF($C51="","",SUM(E51:N51)) | P51: =IF($C51="","",SUMIFS(MOVIMIENTOS!$I:$I,MOVIMIENTOS!$D:$D,"Aporte",MOVIMIENTOS!$E:$E,"Extraordinaria",MOVIMIENTOS!$F:$F,P$4,MOVIMIENTOS!$J:$J,$C51)) | Q51: =IF($C51="","",SUMIFS(MOVIMIENTOS!$I:$I,MOVIMIENTOS!$D:$D,"Aporte",MOVIMIENTOS!$E:$E,"Extraordinaria",MOVIMIENTOS!$F:$F,Q$4,MOVIMIENTOS!$J:$J,$C51)) | R51: =IF($C51="","",SUMIFS(MOVIMIENTOS!$I:$I,MOVIMIENTOS!$D:$D,"Aporte",MOVIMIENTOS!$E:$E,"Extraordinaria",MOVIMIENTOS!$F:$F,R$4,MOVIMIENTOS!$J:$J,$C51)) | S51: =IF($C51="","",SUMIFS(MOVIMIENTOS!$I:$I,MOVIMIENTOS!$D:$D,"Aporte",MOVIMIENTOS!$E:$E,"Extraordinaria",MOVIMIENTOS!$F:$F,S$4,MOVIMIENTOS!$J:$J,$C51)) | T51: =IF($C51="","",SUMIFS(MOVIMIENTOS!$I:$I,MOVIMIENTOS!$D:$D,"Aporte",MOVIMIENTOS!$E:$E,"Extraordinaria",MOVIMIENTOS!$F:$F,T$4,MOVIMIENTOS!$J:$J,$C51)) | U51: =IF($C51="","",SUMIFS(MOVIMIENTOS!$I:$I,MOVIMIENTOS!$D:$D,"Aporte",MOVIMIENTOS!$E:$E,"Extraordinaria",MOVIMIENTOS!$F:$F,U$4,MOVIMIENTOS!$J:$J,$C51)) | V51: =IF($C51="","",SUMIFS(MOVIMIENTOS!$I:$I,MOVIMIENTOS!$D:$D,"Aporte",MOVIMIENTOS!$E:$E,"Extraordinaria",MOVIMIENTOS!$F:$F,V$4,MOVIMIENTOS!$J:$J,$C51)) | W51: =IF($C51="","",SUM(P51:V51)) | X51: =IF($C51="","",O51+W51)
E52: =IF($C52="","",SUMIFS(MOVIMIENTOS!$I:$I,MOVIMIENTOS!$D:$D,"Aporte",MOVIMIENTOS!$E:$E,"Anual",MOVIMIENTOS!$J:$J,$C52,MOVIMIENTOS!$B:$B,">="&DATE(2026,3,1),MOVIMIENTOS!$B:$B,"<"&DATE(2026,4,1))) | F52: =IF($C52="","",SUMIFS(MOVIMIENTOS!$I:$I,MOVIMIENTOS!$D:$D,"Aporte",MOVIMIENTOS!$E:$E,"Anual",MOVIMIENTOS!$J:$J,$C52,MOVIMIENTOS!$B:$B,">="&DATE(2026,4,1),MOVIMIENTOS!$B:$B,"<"&DATE(2026,5,1))) | G52: =IF($C52="","",SUMIFS(MOVIMIENTOS!$I:$I,MOVIMIENTOS!$D:$D,"Aporte",MOVIMIENTOS!$E:$E,"Anual",MOVIMIENTOS!$J:$J,$C52,MOVIMIENTOS!$B:$B,">="&DATE(2026,5,1),MOVIMIENTOS!$B:$B,"<"&DATE(2026,6,1))) | H52: =IF($C52="","",SUMIFS(MOVIMIENTOS!$I:$I,MOVIMIENTOS!$D:$D,"Aporte",MOVIMIENTOS!$E:$E,"Anual",MOVIMIENTOS!$J:$J,$C52,MOVIMIENTOS!$B:$B,">="&DATE(2026,6,1),MOVIMIENTOS!$B:$B,"<"&DATE(2026,7,1))) | I52: =IF($C52="","",SUMIFS(MOVIMIENTOS!$I:$I,MOVIMIENTOS!$D:$D,"Aporte",MOVIMIENTOS!$E:$E,"Anual",MOVIMIENTOS!$J:$J,$C52,MOVIMIENTOS!$B:$B,">="&DATE(2026,7,1),MOVIMIENTOS!$B:$B,"<"&DATE(2026,8,1))) | J52: =IF($C52="","",SUMIFS(MOVIMIENTOS!$I:$I,MOVIMIENTOS!$D:$D,"Aporte",MOVIMIENTOS!$E:$E,"Anual",MOVIMIENTOS!$J:$J,$C52,MOVIMIENTOS!$B:$B,">="&DATE(2026,8,1),MOVIMIENTOS!$B:$B,"<"&DATE(2026,9,1))) | K52: =IF($C52="","",SUMIFS(MOVIMIENTOS!$I:$I,MOVIMIENTOS!$D:$D,"Aporte",MOVIMIENTOS!$E:$E,"Anual",MOVIMIENTOS!$J:$J,$C52,MOVIMIENTOS!$B:$B,">="&DATE(2026,9,1),MOVIMIENTOS!$B:$B,"<"&DATE(2026,10,1))) | L52: =IF($C52="","",SUMIFS(MOVIMIENTOS!$I:$I,MOVIMIENTOS!$D:$D,"Aporte",MOVIMIENTOS!$E:$E,"Anual",MOVIMIENTOS!$J:$J,$C52,MOVIMIENTOS!$B:$B,">="&DATE(2026,10,1),MOVIMIENTOS!$B:$B,"<"&DATE(2026,11,1))) | M52: =IF($C52="","",SUMIFS(MOVIMIENTOS!$I:$I,MOVIMIENTOS!$D:$D,"Aporte",MOVIMIENTOS!$E:$E,"Anual",MOVIMIENTOS!$J:$J,$C52,MOVIMIENTOS!$B:$B,">="&DATE(2026,11,1),MOVIMIENTOS!$B:$B,"<"&DATE(2026,12,1))) | N52: =IF($C52="","",SUMIFS(MOVIMIENTOS!$I:$I,MOVIMIENTOS!$D:$D,"Aporte",MOVIMIENTOS!$E:$E,"Anual",MOVIMIENTOS!$J:$J,$C52,MOVIMIENTOS!$B:$B,">="&DATE(2026,12,1),MOVIMIENTOS!$B:$B,"<"&DATE(2026,13,1))) | O52: =IF($C52="","",SUM(E52:N52)) | P52: =IF($C52="","",SUMIFS(MOVIMIENTOS!$I:$I,MOVIMIENTOS!$D:$D,"Aporte",MOVIMIENTOS!$E:$E,"Extraordinaria",MOVIMIENTOS!$F:$F,P$4,MOVIMIENTOS!$J:$J,$C52)) | Q52: =IF($C52="","",SUMIFS(MOVIMIENTOS!$I:$I,MOVIMIENTOS!$D:$D,"Aporte",MOVIMIENTOS!$E:$E,"Extraordinaria",MOVIMIENTOS!$F:$F,Q$4,MOVIMIENTOS!$J:$J,$C52)) | R52: =IF($C52="","",SUMIFS(MOVIMIENTOS!$I:$I,MOVIMIENTOS!$D:$D,"Aporte",MOVIMIENTOS!$E:$E,"Extraordinaria",MOVIMIENTOS!$F:$F,R$4,MOVIMIENTOS!$J:$J,$C52)) | S52: =IF($C52="","",SUMIFS(MOVIMIENTOS!$I:$I,MOVIMIENTOS!$D:$D,"Aporte",MOVIMIENTOS!$E:$E,"Extraordinaria",MOVIMIENTOS!$F:$F,S$4,MOVIMIENTOS!$J:$J,$C52)) | T52: =IF($C52="","",SUMIFS(MOVIMIENTOS!$I:$I,MOVIMIENTOS!$D:$D,"Aporte",MOVIMIENTOS!$E:$E,"Extraordinaria",MOVIMIENTOS!$F:$F,T$4,MOVIMIENTOS!$J:$J,$C52)) | U52: =IF($C52="","",SUMIFS(MOVIMIENTOS!$I:$I,MOVIMIENTOS!$D:$D,"Aporte",MOVIMIENTOS!$E:$E,"Extraordinaria",MOVIMIENTOS!$F:$F,U$4,MOVIMIENTOS!$J:$J,$C52)) | V52: =IF($C52="","",SUMIFS(MOVIMIENTOS!$I:$I,MOVIMIENTOS!$D:$D,"Aporte",MOVIMIENTOS!$E:$E,"Extraordinaria",MOVIMIENTOS!$F:$F,V$4,MOVIMIENTOS!$J:$J,$C52)) | W52: =IF($C52="","",SUM(P52:V52)) | X52: =IF($C52="","",O52+W52)
E53: =IF($C53="","",SUMIFS(MOVIMIENTOS!$I:$I,MOVIMIENTOS!$D:$D,"Aporte",MOVIMIENTOS!$E:$E,"Anual",MOVIMIENTOS!$J:$J,$C53,MOVIMIENTOS!$B:$B,">="&DATE(2026,3,1),MOVIMIENTOS!$B:$B,"<"&DATE(2026,4,1))) | F53: =IF($C53="","",SUMIFS(MOVIMIENTOS!$I:$I,MOVIMIENTOS!$D:$D,"Aporte",MOVIMIENTOS!$E:$E,"Anual",MOVIMIENTOS!$J:$J,$C53,MOVIMIENTOS!$B:$B,">="&DATE(2026,4,1),MOVIMIENTOS!$B:$B,"<"&DATE(2026,5,1))) | G53: =IF($C53="","",SUMIFS(MOVIMIENTOS!$I:$I,MOVIMIENTOS!$D:$D,"Aporte",MOVIMIENTOS!$E:$E,"Anual",MOVIMIENTOS!$J:$J,$C53,MOVIMIENTOS!$B:$B,">="&DATE(2026,5,1),MOVIMIENTOS!$B:$B,"<"&DATE(2026,6,1))) | H53: =IF($C53="","",SUMIFS(MOVIMIENTOS!$I:$I,MOVIMIENTOS!$D:$D,"Aporte",MOVIMIENTOS!$E:$E,"Anual",MOVIMIENTOS!$J:$J,$C53,MOVIMIENTOS!$B:$B,">="&DATE(2026,6,1),MOVIMIENTOS!$B:$B,"<"&DATE(2026,7,1))) | I53: =IF($C53="","",SUMIFS(MOVIMIENTOS!$I:$I,MOVIMIENTOS!$D:$D,"Aporte",MOVIMIENTOS!$E:$E,"Anual",MOVIMIENTOS!$J:$J,$C53,MOVIMIENTOS!$B:$B,">="&DATE(2026,7,1),MOVIMIENTOS!$B:$B,"<"&DATE(2026,8,1))) | J53: =IF($C53="","",SUMIFS(MOVIMIENTOS!$I:$I,MOVIMIENTOS!$D:$D,"Aporte",MOVIMIENTOS!$E:$E,"Anual",MOVIMIENTOS!$J:$J,$C53,MOVIMIENTOS!$B:$B,">="&DATE(2026,8,1),MOVIMIENTOS!$B:$B,"<"&DATE(2026,9,1))) | K53: =IF($C53="","",SUMIFS(MOVIMIENTOS!$I:$I,MOVIMIENTOS!$D:$D,"Aporte",MOVIMIENTOS!$E:$E,"Anual",MOVIMIENTOS!$J:$J,$C53,MOVIMIENTOS!$B:$B,">="&DATE(2026,9,1),MOVIMIENTOS!$B:$B,"<"&DATE(2026,10,1))) | L53: =IF($C53="","",SUMIFS(MOVIMIENTOS!$I:$I,MOVIMIENTOS!$D:$D,"Aporte",MOVIMIENTOS!$E:$E,"Anual",MOVIMIENTOS!$J:$J,$C53,MOVIMIENTOS!$B:$B,">="&DATE(2026,10,1),MOVIMIENTOS!$B:$B,"<"&DATE(2026,11,1))) | M53: =IF($C53="","",SUMIFS(MOVIMIENTOS!$I:$I,MOVIMIENTOS!$D:$D,"Aporte",MOVIMIENTOS!$E:$E,"Anual",MOVIMIENTOS!$J:$J,$C53,MOVIMIENTOS!$B:$B,">="&DATE(2026,11,1),MOVIMIENTOS!$B:$B,"<"&DATE(2026,12,1))) | N53: =IF($C53="","",SUMIFS(MOVIMIENTOS!$I:$I,MOVIMIENTOS!$D:$D,"Aporte",MOVIMIENTOS!$E:$E,"Anual",MOVIMIENTOS!$J:$J,$C53,MOVIMIENTOS!$B:$B,">="&DATE(2026,12,1),MOVIMIENTOS!$B:$B,"<"&DATE(2026,13,1))) | O53: =IF($C53="","",SUM(E53:N53)) | P53: =IF($C53="","",SUMIFS(MOVIMIENTOS!$I:$I,MOVIMIENTOS!$D:$D,"Aporte",MOVIMIENTOS!$E:$E,"Extraordinaria",MOVIMIENTOS!$F:$F,P$4,MOVIMIENTOS!$J:$J,$C53)) | Q53: =IF($C53="","",SUMIFS(MOVIMIENTOS!$I:$I,MOVIMIENTOS!$D:$D,"Aporte",MOVIMIENTOS!$E:$E,"Extraordinaria",MOVIMIENTOS!$F:$F,Q$4,MOVIMIENTOS!$J:$J,$C53)) | R53: =IF($C53="","",SUMIFS(MOVIMIENTOS!$I:$I,MOVIMIENTOS!$D:$D,"Aporte",MOVIMIENTOS!$E:$E,"Extraordinaria",MOVIMIENTOS!$F:$F,R$4,MOVIMIENTOS!$J:$J,$C53)) | S53: =IF($C53="","",SUMIFS(MOVIMIENTOS!$I:$I,MOVIMIENTOS!$D:$D,"Aporte",MOVIMIENTOS!$E:$E,"Extraordinaria",MOVIMIENTOS!$F:$F,S$4,MOVIMIENTOS!$J:$J,$C53)) | T53: =IF($C53="","",SUMIFS(MOVIMIENTOS!$I:$I,MOVIMIENTOS!$D:$D,"Aporte",MOVIMIENTOS!$E:$E,"Extraordinaria",MOVIMIENTOS!$F:$F,T$4,MOVIMIENTOS!$J:$J,$C53)) | U53: =IF($C53="","",SUMIFS(MOVIMIENTOS!$I:$I,MOVIMIENTOS!$D:$D,"Aporte",MOVIMIENTOS!$E:$E,"Extraordinaria",MOVIMIENTOS!$F:$F,U$4,MOVIMIENTOS!$J:$J,$C53)) | V53: =IF($C53="","",SUMIFS(MOVIMIENTOS!$I:$I,MOVIMIENTOS!$D:$D,"Aporte",MOVIMIENTOS!$E:$E,"Extraordinaria",MOVIMIENTOS!$F:$F,V$4,MOVIMIENTOS!$J:$J,$C53)) | W53: =IF($C53="","",SUM(P53:V53)) | X53: =IF($C53="","",O53+W53)
E54: =IF($C54="","",SUMIFS(MOVIMIENTOS!$I:$I,MOVIMIENTOS!$D:$D,"Aporte",MOVIMIENTOS!$E:$E,"Anual",MOVIMIENTOS!$J:$J,$C54,MOVIMIENTOS!$B:$B,">="&DATE(2026,3,1),MOVIMIENTOS!$B:$B,"<"&DATE(2026,4,1))) | F54: =IF($C54="","",SUMIFS(MOVIMIENTOS!$I:$I,MOVIMIENTOS!$D:$D,"Aporte",MOVIMIENTOS!$E:$E,"Anual",MOVIMIENTOS!$J:$J,$C54,MOVIMIENTOS!$B:$B,">="&DATE(2026,4,1),MOVIMIENTOS!$B:$B,"<"&DATE(2026,5,1))) | G54: =IF($C54="","",SUMIFS(MOVIMIENTOS!$I:$I,MOVIMIENTOS!$D:$D,"Aporte",MOVIMIENTOS!$E:$E,"Anual",MOVIMIENTOS!$J:$J,$C54,MOVIMIENTOS!$B:$B,">="&DATE(2026,5,1),MOVIMIENTOS!$B:$B,"<"&DATE(2026,6,1))) | H54: =IF($C54="","",SUMIFS(MOVIMIENTOS!$I:$I,MOVIMIENTOS!$D:$D,"Aporte",MOVIMIENTOS!$E:$E,"Anual",MOVIMIENTOS!$J:$J,$C54,MOVIMIENTOS!$B:$B,">="&DATE(2026,6,1),MOVIMIENTOS!$B:$B,"<"&DATE(2026,7,1))) | I54: =IF($C54="","",SUMIFS(MOVIMIENTOS!$I:$I,MOVIMIENTOS!$D:$D,"Aporte",MOVIMIENTOS!$E:$E,"Anual",MOVIMIENTOS!$J:$J,$C54,MOVIMIENTOS!$B:$B,">="&DATE(2026,7,1),MOVIMIENTOS!$B:$B,"<"&DATE(2026,8,1))) | J54: =IF($C54="","",SUMIFS(MOVIMIENTOS!$I:$I,MOVIMIENTOS!$D:$D,"Aporte",MOVIMIENTOS!$E:$E,"Anual",MOVIMIENTOS!$J:$J,$C54,MOVIMIENTOS!$B:$B,">="&DATE(2026,8,1),MOVIMIENTOS!$B:$B,"<"&DATE(2026,9,1))) | K54: =IF($C54="","",SUMIFS(MOVIMIENTOS!$I:$I,MOVIMIENTOS!$D:$D,"Aporte",MOVIMIENTOS!$E:$E,"Anual",MOVIMIENTOS!$J:$J,$C54,MOVIMIENTOS!$B:$B,">="&DATE(2026,9,1),MOVIMIENTOS!$B:$B,"<"&DATE(2026,10,1))) | L54: =IF($C54="","",SUMIFS(MOVIMIENTOS!$I:$I,MOVIMIENTOS!$D:$D,"Aporte",MOVIMIENTOS!$E:$E,"Anual",MOVIMIENTOS!$J:$J,$C54,MOVIMIENTOS!$B:$B,">="&DATE(2026,10,1),MOVIMIENTOS!$B:$B,"<"&DATE(2026,11,1))) | M54: =IF($C54="","",SUMIFS(MOVIMIENTOS!$I:$I,MOVIMIENTOS!$D:$D,"Aporte",MOVIMIENTOS!$E:$E,"Anual",MOVIMIENTOS!$J:$J,$C54,MOVIMIENTOS!$B:$B,">="&DATE(2026,11,1),MOVIMIENTOS!$B:$B,"<"&DATE(2026,12,1))) | N54: =IF($C54="","",SUMIFS(MOVIMIENTOS!$I:$I,MOVIMIENTOS!$D:$D,"Aporte",MOVIMIENTOS!$E:$E,"Anual",MOVIMIENTOS!$J:$J,$C54,MOVIMIENTOS!$B:$B,">="&DATE(2026,12,1),MOVIMIENTOS!$B:$B,"<"&DATE(2026,13,1))) | O54: =IF($C54="","",SUM(E54:N54)) | P54: =IF($C54="","",SUMIFS(MOVIMIENTOS!$I:$I,MOVIMIENTOS!$D:$D,"Aporte",MOVIMIENTOS!$E:$E,"Extraordinaria",MOVIMIENTOS!$F:$F,P$4,MOVIMIENTOS!$J:$J,$C54)) | Q54: =IF($C54="","",SUMIFS(MOVIMIENTOS!$I:$I,MOVIMIENTOS!$D:$D,"Aporte",MOVIMIENTOS!$E:$E,"Extraordinaria",MOVIMIENTOS!$F:$F,Q$4,MOVIMIENTOS!$J:$J,$C54)) | R54: =IF($C54="","",SUMIFS(MOVIMIENTOS!$I:$I,MOVIMIENTOS!$D:$D,"Aporte",MOVIMIENTOS!$E:$E,"Extraordinaria",MOVIMIENTOS!$F:$F,R$4,MOVIMIENTOS!$J:$J,$C54)) | S54: =IF($C54="","",SUMIFS(MOVIMIENTOS!$I:$I,MOVIMIENTOS!$D:$D,"Aporte",MOVIMIENTOS!$E:$E,"Extraordinaria",MOVIMIENTOS!$F:$F,S$4,MOVIMIENTOS!$J:$J,$C54)) | T54: =IF($C54="","",SUMIFS(MOVIMIENTOS!$I:$I,MOVIMIENTOS!$D:$D,"Aporte",MOVIMIENTOS!$E:$E,"Extraordinaria",MOVIMIENTOS!$F:$F,T$4,MOVIMIENTOS!$J:$J,$C54)) | U54: =IF($C54="","",SUMIFS(MOVIMIENTOS!$I:$I,MOVIMIENTOS!$D:$D,"Aporte",MOVIMIENTOS!$E:$E,"Extraordinaria",MOVIMIENTOS!$F:$F,U$4,MOVIMIENTOS!$J:$J,$C54)) | V54: =IF($C54="","",SUMIFS(MOVIMIENTOS!$I:$I,MOVIMIENTOS!$D:$D,"Aporte",MOVIMIENTOS!$E:$E,"Extraordinaria",MOVIMIENTOS!$F:$F,V$4,MOVIMIENTOS!$J:$J,$C54)) | W54: =IF($C54="","",SUM(P54:V54)) | X54: =IF($C54="","",O54+W54)
... E104: =IF($C104="","",SUMIFS(MOVIMIENTOS!$I:$I,MOVIMIENTOS!$D:$D,"Aporte",MOVIMIENTOS!$E:$E,"Anual",MOVIMIENTOS!$J:$J,$C104,MOVIMIENTOS!$B:$B,">="&DATE(2026,3,1),MOVIMIENTOS!$B:$B,"<"&DATE(2026,4,1))) | F104: =IF($C104="","",SUMIFS(MOVIMIENTOS!$I:$I,MOVIMIENTOS!$D:$D,"Aporte",MOVIMIENTOS!$E:$E,"Anual",MOVIMIENTOS!$J:$J,$C104,MOVIMIENTOS!$B:$B,">="&DATE(2026,4,1),MOVIMIENTOS!$B:$B,"<"&DATE(2026,5,1))) | G104: =IF($C104="","",SUMIFS(MOVIMIENTOS!$I:$I,MOVIMIENTOS!$D:$D,"Aporte",MOVIMIENTOS!$E:$E,"Anual",MOVIMIENTOS!$J:$J,$C104,MOVIMIENTOS!$B:$B,">="&DATE(2026,5,1),MOVIMIENTOS!$B:$B,"<"&DATE(2026,6,1))) | H104: =IF($C104="","",SUMIFS(MOVIMIENTOS!$I:$I,MOVIMIENTOS!$D:$D,"Aporte",MOVIMIENTOS!$E:$E,"Anual",MOVIMIENTOS!$J:$J,$C104,MOVIMIENTOS!$B:$B,">="&DATE(2026,6,1),MOVIMIENTOS!$B:$B,"<"&DATE(2026,7,1))) | I104: =IF($C104="","",SUMIFS(MOVIMIENTOS!$I:$I,MOVIMIENTOS!$D:$D,"Aporte",MOVIMIENTOS!$E:$E,"Anual",MOVIMIENTOS!$J:$J,$C104,MOVIMIENTOS!$B:$B,">="&DATE(2026,7,1),MOVIMIENTOS!$B:$B,"<"&DATE(2026,8,1))) | J104: =IF($C104="","",SUMIFS(MOVIMIENTOS!$I:$I,MOVIMIENTOS!$D:$D,"Aporte",MOVIMIENTOS!$E:$E,"Anual",MOVIMIENTOS!$J:$J,$C104,MOVIMIENTOS!$B:$B,">="&DATE(2026,8,1),MOVIMIENTOS!$B:$B,"<"&DATE(2026,9,1))) | K104: =IF($C104="","",SUMIFS(MOVIMIENTOS!$I:$I,MOVIMIENTOS!$D:$D,"Aporte",MOVIMIENTOS!$E:$E,"Anual",MOVIMIENTOS!$J:$J,$C104,MOVIMIENTOS!$B:$B,">="&DATE(2026,9,1),MOVIMIENTOS!$B:$B,"<"&DATE(2026,10,1))) | L104: =IF($C104="","",SUMIFS(MOVIMIENTOS!$I:$I,MOVIMIENTOS!$D:$D,"Aporte",MOVIMIENTOS!$E:$E,"Anual",MOVIMIENTOS!$J:$J,$C104,MOVIMIENTOS!$B:$B,">="&DATE(2026,10,1),MOVIMIENTOS!$B:$B,"<"&DATE(2026,11,1))) | M104: =IF($C104="","",SUMIFS(MOVIMIENTOS!$I:$I,MOVIMIENTOS!$D:$D,"Aporte",MOVIMIENTOS!$E:$E,"Anual",MOVIMIENTOS!$J:$J,$C104,MOVIMIENTOS!$B:$B,">="&DATE(2026,11,1),MOVIMIENTOS!$B:$B,"<"&DATE(2026,12,1))) | N104: =IF($C104="","",SUMIFS(MOVIMIENTOS!$I:$I,MOVIMIENTOS!$D:$D,"Aporte",MOVIMIENTOS!$E:$E,"Anual",MOVIMIENTOS!$J:$J,$C104,MOVIMIENTOS!$B:$B,">="&DATE(2026,12,1),MOVIMIENTOS!$B:$B,"<"&DATE(2026,13,1))) | O104: =IF($C104="","",SUM(E104:N104)) | P104: =IF($C104="","",SUMIFS(MOVIMIENTOS!$I:$I,MOVIMIENTOS!$D:$D,"Aporte",MOVIMIENTOS!$E:$E,"Extraordinaria",MOVIMIENTOS!$F:$F,P$4,MOVIMIENTOS!$J:$J,$C104)) | Q104: =IF($C104="","",SUMIFS(MOVIMIENTOS!$I:$I,MOVIMIENTOS!$D:$D,"Aporte",MOVIMIENTOS!$E:$E,"Extraordinaria",MOVIMIENTOS!$F:$F,Q$4,MOVIMIENTOS!$J:$J,$C104)) | R104: =IF($C104="","",SUMIFS(MOVIMIENTOS!$I:$I,MOVIMIENTOS!$D:$D,"Aporte",MOVIMIENTOS!$E:$E,"Extraordinaria",MOVIMIENTOS!$F:$F,R$4,MOVIMIENTOS!$J:$J,$C104)) | S104: =IF($C104="","",SUMIFS(MOVIMIENTOS!$I:$I,MOVIMIENTOS!$D:$D,"Aporte",MOVIMIENTOS!$E:$E,"Extraordinaria",MOVIMIENTOS!$F:$F,S$4,MOVIMIENTOS!$J:$J,$C104)) | T104: =IF($C104="","",SUMIFS(MOVIMIENTOS!$I:$I,MOVIMIENTOS!$D:$D,"Aporte",MOVIMIENTOS!$E:$E,"Extraordinaria",MOVIMIENTOS!$F:$F,T$4,MOVIMIENTOS!$J:$J,$C104)) | U104: =IF($C104="","",SUMIFS(MOVIMIENTOS!$I:$I,MOVIMIENTOS!$D:$D,"Aporte",MOVIMIENTOS!$E:$E,"Extraordinaria",MOVIMIENTOS!$F:$F,U$4,MOVIMIENTOS!$J:$J,$C104)) | V104: =IF($C104="","",SUMIFS(MOVIMIENTOS!$I:$I,MOVIMIENTOS!$D:$D,"Aporte",MOVIMIENTOS!$E:$E,"Extraordinaria",MOVIMIENTOS!$F:$F,V$4,MOVIMIENTOS!$J:$J,$C104)) | W104: =IF($C104="","",SUM(P104:V104)) | X104: =IF($C104="","",O104+W104)

Sheet ORIGINAL - RESUMEN GENERAL
B1: TESORERÍA 5°B - RESUMEN GENERAL CONSOLIDADO
B2: El curso administra dos cajas -Tesorería y Presidenta- que este resumen consolida.
B4: CONCEPTO | C4: TESORERÍA | D4: PRESIDENTA | E4: TOTAL CURSO
B5: INGRESOS | C5: ='ingresos tesorero'!k1 -> #NAME? | D5: ='caja presidenta'!d1 -> #NAME? | E5: =C5+D5 -> #NAME?
B6: EGRESOS | C6: ='ingresos tesorero'!k2 -> #NAME? | D6: ='caja presidenta'!d2 -> #NAME? | E6: =C6+D6 -> #NAME?
B7: SALDO | C7: ='ingresos tesorero'!k3 -> #NAME? | D7: ='caja presidenta'!d3 -> #NAME? | E7: =C7+D7 -> #NAME?
B9: SALDO EN PODER DE LA PRESIDENTA — PENDIENTE DE REINTEGRO A TESORERÍA | E9: ='caja presidenta'!d3 -> #NAME?
B11: TOTAL DE FONDOS DISPONIBLES DEL CURSO A LA FECHA (Tesorería + saldo pendiente en poder de la Presidenta)
B12: TOTAL CURSO | E12: ='ingresos tesorero'!k3+'caja presidenta'!d3 -> #NAME?

Sheet ORIGINAL - GENERAL
B1: TESORERÍA 5°B - INGRESOS (PLANILLA ÚNICA CUOTAS OBLIGATORIAS)
B2: En rojo: montos recibidos por la Presidenta (aun no reintegrados en su totalidad a Tesoreria, ver hoja CAJA PRESIDENTA). Sin color: montos recibidos por Tesoreria.
B4: RUT | C4: NOMBRE | D4: APODERADO | E4: CUMPL PROFESOR | F4: DIA ALUMNO | G4: CONVIVENCIA JUNIO | H4: MARZO | I4: ABRIL | J4: MAYO | K4: JUNIO | L4: JULIO | M4: AGOSTO | N4: SEPTIEMBRE | O4: OCTUBRE | P4: NOVIEMBRE | Q4: DICIEMBRE | R4: RIFA | S4: TOTAL
A5: 1 | B5: 25310795-2 | C5: ARAYA PINO RENATA ANTONELA | D5: PATRICIA PINO | E5: 1000 | F5: 2000 | H5: 3000 | I5: 3000 | J5: 3000 | K5: 3000 | L5: 3000 | S5: =SUM(tabla18[[#this row],[cumpl profesor]:[rifa]]) -> #N/A
A6: 2 | B6: 25299343-6 | C6: ASTUDILLO PINO TABATA JESÚS | D6: ROXANA PINO | E6: 1000 | G6: 2000 | H6: 3000 | S6: =SUM(tabla18[[#this row],[cumpl profesor]:[rifa]]) -> #N/A
A7: 3 | B7: 25172569-1 | C7: AZAGRA ABRIGO AMARO ALONSO | D7: BEATRIZ ABRIGO | E7: 1000 | F7: 2000 | G7: 2000 | R7: 1000 | S7: =SUM(tabla18[[#this row],[cumpl profesor]:[rifa]]) -> #N/A
A8: 4 | B8: 25074761-6 | C8: BECERRA CARRASCO AGUSTIN SALVADOR THOMAS | D8: ALICIA ARAYA | E8: 1000 | F8: 2000 | G8: 2000 | H8: 3000 | I8: 3000 | J8: 3000 | S8: =SUM(tabla18[[#this row],[cumpl profesor]:[rifa]]) -> #N/A
C9: BERTEL MONTES GLEYMIS | H9: 3000 | S9: =SUM(tabla18[[#this row],[cumpl profesor]:[rifa]]) -> #N/A
A10: 6 | B10: 25186502-7 | C10: CASTILLO DÍAZ NAHUEL ANDRÉS | S10: =SUM(tabla18[[#this row],[cumpl profesor]:[rifa]]) -> #N/A
A11: 7 | B11: 24387554-4 | C11: CASTILLO GRACIA JOSEFA ANTONIA | E11: 1000 | G11: 2000 | H11: 3000 | I11: 3000 | J11: 3000 | S11: =SUM(tabla18[[#this row],[cumpl profesor]:[rifa]]) -> #N/A
A12: 8 | B12: 25117099-1 | C12: CASTRO VALDERRAMA EIMY PASCALLE | D12: ANA VALDERRAMA | E12: 1000 | F12: 2000 | G12: 2000 | H12: 3000 | I12: 3000 | J12: 3000 | K12: 3000 | L12: 3000 | S12: =SUM(tabla18[[#this row],[cumpl profesor]:[rifa]]) -> #N/A
A13: 9 | B13: 25091106-8 | C13: DONOSO MONSALVE ANGEL ISAAC | E13: 1000 | F13: 2000 | G13: 2000 | H13: 3000 | I13: 3000 | J13: 3000 | K13: 3000 | S13: =SUM(tabla18[[#this row],[cumpl profesor]:[rifa]]) -> #N/A
A14: 10 | B14: 25091116-5 | C14: DONOSO MONSALVE THOMAS IGNACIO | E14: 1000 | F14: 2000 | G14: 2000 | H14: 3000 | I14: 3000 | J14: 3000 | K14: 3000 | S14: =SUM(tabla18[[#this row],[cumpl profesor]:[rifa]]) -> #N/A
A15: 11 | B15: 24953133-2 | C15: DONOSO ZAMORA SOFÍA ELENA | D15: JENNY ZAMORA | E15: 1000 | F15: 2000 | G15: 2000 | H15: 3000 | I15: 3000 | J15: 3000 | K15: 3000 | L15: 3000 | R15: 1000 | S15: =SUM(tabla18[[#this row],[cumpl profesor]:[rifa]]) -> #N/A
A16: 12 | B16: 24751135-0 | C16: INOSTROZA MOLINA MATÍAS ALONSO | D16: OLGA MOLINA | E16: 1000 | F16: 2000 | H16: 3000 | I16: 3000 | J16: 3000 | K16: 3000 | L16: 3000 | M16: 3000 | S16: =SUM(tabla18[[#this row],[cumpl profesor]:[rifa]]) -> #N/A
A17: 13 | B17: 25049508-0 | C17: ITURRIETA HERNÁNDEZ MAXIMILIANO ALEJANDRO | D17: VALERIA HERNANDEZ | E17: 1000 | F17: 2000 | G17: 2000 | H17: 3000 | S17: =SUM(tabla18[[#this row],[cumpl profesor]:[rifa]]) -> #N/A
A18: 14 | B18: 25049482-3 | C18: ITURRIETA HERNÁNDEZ VICENTE IGNACIO | D18: VALERIA HERNANDEZ | E18: 1000 | F18: 2000 | G18: 2000 | H18: 3000 | S18: =SUM(tabla18[[#this row],[cumpl profesor]:[rifa]]) -> #N/A
A19: 15 | B19: 25067494-5 | C19: JATIB DÍAZ ABDOLASIS MAXIMILIANO | D19: MARISOL DIAZ | E19: 1000 | F19: 2000 | G19: 2000 | H19: 3000 | S19: =SUM(tabla18[[#this row],[cumpl profesor]:[rifa]]) -> #N/A
A20: 16 | B20: 25015009-1 | C20: MENESES YÁÑEZ ALEXANDRA MODESTA | E20: 1000 | F20: 2000 | G20: 2000 | S20: =SUM(tabla18[[#this row],[cumpl profesor]:[rifa]]) -> #N/A
A21: 17 | B21: 25179616-5 | C21: MICHEA ALIAGA JOAQUÍN ELÍAS | D21: STEFANY ALIAGA | E21: 1000 | F21: 2000 | G21: 2000 | H21: 3000 | I21: 3000 | J21: 3000 | K21: 3000 | L21: 3000 | S21: =SUM(tabla18[[#this row],[cumpl profesor]:[rifa]]) -> #N/A
A22: 18 | B22: 25026561-1 | C22: MOYA SALAS COLOMBA AYLÉN | D22: NATALIE SALAS | E22: 1000 | F22: 2000 | G22: 2000 | H22: 3000 | R22: 1000 | S22: =SUM(tabla18[[#this row],[cumpl profesor]:[rifa]]) -> #N/A
A23: 19 | B23: 25012737-5 | C23: MUÑOZ BECERRA AGUSTINA ISIDORA | D23: YERI | E23: 1000 | F23: 2000 | G23: 2000 | H23: 3000 | S23: =SUM(tabla18[[#this row],[cumpl profesor]:[rifa]]) -> #N/A
A24: 20 | B24: 25276474-7 | C24: MUÑOZ NAVARRETE ANTONELLA ESTEFANÍA | D24: JANETTE NAVARRETE | E24: 1000 | F24: 2000 | G24: 2000 | H24: 3000 | I24: 3000 | J24: 3000 | S24: =SUM(tabla18[[#this row],[cumpl profesor]:[rifa]]) -> #N/A
A25: 21 | B25: 25280245-2 | C25: MUÑOZ VALENZUELA BENJAMÍN IGNACIO | D25: NATALIA VALENZUELA | E25: 1000 | F25: 2000 | G25: 2000 | H25: 3000 | I25: 3000 | J25: 3000 | K25: 3000 | S25: =SUM(tabla18[[#this row],[cumpl profesor]:[rifa]]) -> #N/A
A26: 22 | B26: 25312924-7 | C26: ORELLANA IBARRA PABLO ALFONSO | S26: =SUM(tabla18[[#this row],[cumpl profesor]:[rifa]]) -> #N/A
A27: 23 | B27: 25006274-5 | C27: OYARCE CABELLO MONSERRAT ANTONELLA | D27: MONSERRAT OLLARCE | E27: 1000 | F27: 2000 | G27: 2000 | H27: 3000 | R27: 1000 | S27: =SUM(tabla18[[#this row],[cumpl profesor]:[rifa]]) -> #N/A
A28: 24 | B28: 24758384-4 | C28: PÉREZ HIGUERAS ANTONELLA NICOLE | D28: NELLY HIGUERAS | E28: 1000 | F28: 2000 | G28: 2000 | H28: 3000 | R28: 1000 | S28: =SUM(tabla18[[#this row],[cumpl profesor]:[rifa]]) -> #N/A
A29: 25 | B29: 25042952-5 | C29: RAMÍREZ MUÑOZ ANHAI ESPERANZA | D29: ROSA LLANOS | E29: 1000 | F29: 2000 | G29: 2000 | H29: 3000 | I29: 3000 | J29: 3000 | K29: 3000 | L29: 3000 | R29: 1000 | S29: =SUM(tabla18[[#this row],[cumpl profesor]:[rifa]]) -> #N/A
A30: 26 | B30: 24911564-9 | C30: REYES RODRÍGUEZ FERNANDA CATALINA | D30: YASNA RODRIGUEZ | E30: 1000 | F30: 2000 | H30: 3000 | I30: 3000 | J30: 3000 | K30: 3000 | L30: 3000 | M30: 3000 | S30: =SUM(tabla18[[#this row],[cumpl profesor]:[rifa]]) -> #N/A
A31: 27 | B31: 25255361-0 | C31: RIVERA AVENDAÑO BERTA AMPARO | D31: BLANCA AVENDAÑO | E31: 1000 | F31: 2000 | G31: 2000 | H31: 3000 | I31: 3000 | J31: 3000 | K31: 3000 | L31: 3000 | M31: 3000 | N31: 3000 | O31: 3000 | P31: 3000 | Q31: 3000 | S31: =SUM(tabla18[[#this row],[cumpl profesor]:[rifa]]) -> #N/A
A32: 28 | B32: 24973619-8 | C32: RUBIO REYES JOSÉ ALONSO | E32: 1000 | F32: 2000 | G32: 2000 | S32: =SUM(tabla18[[#this row],[cumpl profesor]:[rifa]]) -> #N/A
A33: 29 | B33: 28939190-8 | C33: SANCHEZ ZAMBRANO MIULER DAVID | D33: YERKA ZAMBRANO | E33: 1000 | F33: 2000 | G33: 2000 | H33: 3000 | I33: 3000 | J33: 3000 | S33: =SUM(tabla18[[#this row],[cumpl profesor]:[rifa]]) -> #N/A
A34: 30 | B34: 25033740-K | C34: SOTO URZÚA COLOMBA JANÍS | D34: MABEL URZUA | E34: 1000 | F34: 2000 | G34: 2000 | H34: 3000 | I34: 3000 | J34: 3000 | K34: 3000 | L34: 3000 | S34: =SUM(tabla18[[#this row],[cumpl profesor]:[rifa]]) -> #N/A
A35: 31 | B35: 25001015-K | C35: UNZUETA GONZÁLEZ JESÚS VINKO ALEJANDRO | S35: =SUM(tabla18[[#this row],[cumpl profesor]:[rifa]]) -> #N/A
A36: 32 | C36: VALDÉS ORMAZÁBAL LAURA FRANCISCA RAYEN | E36: 1000 | F36: 2000 | G36: 2000 | H36: 3000 | I36: 3000 | J36: 3000 | K36: 3000 | S36: =SUM(tabla18[[#this row],[cumpl profesor]:[rifa]]) -> #N/A
A37: 33 | C37: VÁSQUEZ BRAVO RAÚL FELICIANO | D37: LUZMENIA BRAVO | E37: 1000 | F37: 2000 | H37: 3000 | I37: 3000 | J37: 3000 | K37: 3000 | R37: 1000 | S37: =SUM(tabla18[[#this row],[cumpl profesor]:[rifa]]) -> #N/A
A38: 34 | C38: GIANELA FLORES | D38: JANIS OYARCE | E38: 1000 | F38: 2000 | G38: 2000 | R38: 1500 | S38: =SUM(tabla18[[#this row],[cumpl profesor]:[rifa]]) -> #N/A
A39: 35 | C39: LUEIZA BELTRAN JUAN PABLO | D39: FABIOLA BELTRAN | F39: 2000 | G39: 2000 | R39: 1000 | S39: =SUM(tabla18[[#this row],[cumpl profesor]:[rifa]]) -> #N/A
A40: 36 | C40: FARIAS EMILIA | D40: MARTA VALDIVIA | G40: 2000 | S40: =SUM(tabla18[[#this row],[cumpl profesor]:[rifa]]) -> #N/A
A41: 37 | C41: CUBILLOS MATIAS | G41: 2000 | S41: =SUM(tabla18[[#this row],[cumpl profesor]:[rifa]]) -> #N/A
E42: =SUM(E5:E40) -> 30000 | F42: =SUM(F5:F40) -> 58000 | G42: =SUBTOTAL(109,tabla18[convivencia junio]) -> #VALUE! | H42: =SUM(H5:H40) -> 81000 | I42: =SUM(I5:I40) -> 54000 | J42: =SUM(J5:J40) -> 54000 | K42: =SUM(K5:K40) -> 42000 | L42: =SUM(L5:L40) -> 27000 | M42: =SUM(M5:M40) -> 9000 | N42: =SUM(N5:N40) -> 3000 | O42: =SUM(O5:O40) -> 3000 | ... R42: =SUM(R5:R40) -> 9500 | S42: =SUBTOTAL(109,tabla18[total]) -> #VALUE!
P44: RECIBIDO TESORERO | S44: =S42-S45 -> #VALUE!
P45: RECIBIDO PRESIDENTA | S45: =SUM(E20,E21,E24,E29,E31,E32,F5,F12,F13,F14,F17,F18,F19,F20,F21,F24,F25,F27,F28,F29,F31,F32,F33,H9,R27,R28) -> 45000
J46: SALDO PENDIENTE DE REINTEGRO DE LA PRESIDENTA | S46: ='caja presidenta'!d3 -> #NAME?

Sheet ORIGINAL - INGRESOS TESORERO
B1: TESORERÍA 5°B - INGRESOS Y EGRESOS EN PODER DEL TESORERO | H1: INGRESOS | K1: =S45+D54 -> #VALUE!
B2: Solo montos administrados directamente por Tesorería (no incluye lo recibido por la Presidenta). | H2: EGRESOS | K2: ='egresos tesorero'!f24 -> #NAME?
H3: SALDO DISPONIBLE | K3: =K1-K2 -> #NAME?
B7: RUT | C7: NOMBRE | D7: APODERADO | E7: CUMPL PROFESOR | F7: DIA ALUMNO | G7: CONVIVENCIA JUNIO | H7: MARZO | I7: ABRIL | J7: MAYO | K7: JUNIO | L7: JULIO | M7: AGOSTO | N7: SEPTIEMBRE | O7: OCTUBRE | P7: NOVIEMBRE | Q7: DICIEMBRE | R7: RIFA | S7: TOTAL
A8: 1 | B8: 25310795-2 | C8: ARAYA PINO RENATA ANTONELA | D8: PATRICIA PINO | E8: 1000 | H8: 3000 | I8: 3000 | J8: 3000 | K8: 3000 | L8: 3000 | S8: =SUM(tabla1[[#this row],[cumpl profesor]:[rifa]]) -> #N/A
A9: 2 | B9: 25299343-6 | C9: ASTUDILLO PINO TABATA JESÚS | D9: ROXANA PINO | E9: 1000 | G9: 2000 | H9: 3000 | S9: =SUM(tabla1[[#this row],[cumpl profesor]:[rifa]]) -> #N/A
A10: 3 | B10: 25172569-1 | C10: AZAGRA ABRIGO AMARO ALONSO | D10: BEATRIZ ABRIGO | E10: 1000 | F10: 2000 | G10: 2000 | R10: 1000 | S10: =SUM(tabla1[[#this row],[cumpl profesor]:[rifa]]) -> #N/A
A11: 4 | B11: 25074761-6 | C11: BECERRA CARRASCO AGUSTIN SALVADOR THOMAS | D11: ALICIA ARAYA | E11: 1000 | F11: 2000 | G11: 2000 | H11: 3000 | I11: 3000 | J11: 3000 | S11: =SUM(tabla1[[#this row],[cumpl profesor]:[rifa]]) -> #N/A
C12: BERTEL MONTES GLEYMIS | S12: =SUM(tabla1[[#this row],[cumpl profesor]:[rifa]]) -> #N/A
A13: 6 | B13: 25186502-7 | C13: CASTILLO DÍAZ NAHUEL ANDRÉS | S13: =SUM(tabla1[[#this row],[cumpl profesor]:[rifa]]) -> #N/A
A14: 7 | B14: 24387554-4 | C14: CASTILLO GRACIA JOSEFA ANTONIA | E14: 1000 | G14: 2000 | H14: 3000 | I14: 3000 | J14: 3000 | S14: =SUM(tabla1[[#this row],[cumpl profesor]:[rifa]]) -> #N/A
A15: 8 | B15: 25117099-1 | C15: CASTRO VALDERRAMA EIMY PASCALLE | D15: ANA VALDERRAMA | E15: 1000 | G15: 2000 | H15: 3000 | I15: 3000 | J15: 3000 | K15: 3000 | L15: 3000 | S15: =SUM(tabla1[[#this row],[cumpl profesor]:[rifa]]) -> #N/A
A16: 9 | B16: 25091106-8 | C16: DONOSO MONSALVE ANGEL ISAAC | E16: 1000 | G16: 2000 | H16: 3000 | I16: 3000 | J16: 3000 | K16: 3000 | S16: =SUM(tabla1[[#this row],[cumpl profesor]:[rifa]]) -> #N/A
A17: 10 | B17: 25091116-5 | C17: DONOSO MONSALVE THOMAS IGNACIO | E17: 1000 | G17: 2000 | H17: 3000 | I17: 3000 | J17: 3000 | K17: 3000 | S17: =SUM(tabla1[[#this row],[cumpl profesor]:[rifa]]) -> #N/A
A18: 11 | B18: 24953133-2 | C18: DONOSO ZAMORA SOFÍA ELENA | D18: JENNY ZAMORA | E18: 1000 | F18: 2000 | G18: 2000 | H18: 3000 | I18: 3000 | J18: 3000 | K18: 3000 | L18: 3000 | R18: 1000 | S18: =SUM(tabla1[[#this row],[cumpl profesor]:[rifa]]) -> #N/A
A19: 12 | B19: 24751135-0 | C19: INOSTROZA MOLINA MATÍAS ALONSO | D19: OLGA MOLINA | E19: 1000 | F19: 2000 | H19: 3000 | I19: 3000 | J19: 3000 | K19: 3000 | L19: 3000 | M19: 3000 | S19: =SUM(tabla1[[#this row],[cumpl profesor]:[rifa]]) -> #N/A
A20: 13 | B20: 25049508-0 | C20: ITURRIETA HERNÁNDEZ MAXIMILIANO ALEJANDRO | D20: VALERIA HERNANDEZ | E20: 1000 | G20: 2000 | H20: 3000 | S20: =SUM(tabla1[[#this row],[cumpl profesor]:[rifa]]) -> #N/A
A21: 14 | B21: 25049482-3 | C21: ITURRIETA HERNÁNDEZ VICENTE IGNACIO | D21: VALERIA HERNANDEZ | E21: 1000 | G21: 2000 | H21: 3000 | S21: =SUM(tabla1[[#this row],[cumpl profesor]:[rifa]]) -> #N/A
A22: 15 | B22: 25067494-5 | C22: JATIB DÍAZ ABDOLASIS MAXIMILIANO | D22: MARISOL DIAZ | E22: 1000 | G22: 2000 | H22: 3000 | S22: =SUM(tabla1[[#this row],[cumpl profesor]:[rifa]]) -> #N/A
A23: 16 | B23: 25015009-1 | C23: MENESES YÁÑEZ ALEXANDRA MODESTA | G23: 2000 | S23: =SUM(tabla1[[#this row],[cumpl profesor]:[rifa]]) -> #N/A
A24: 17 | B24: 25179616-5 | C24: MICHEA ALIAGA JOAQUÍN ELÍAS | D24: STEFANY ALIAGA | G24: 2000 | H24: 3000 | I24: 3000 | J24: 3000 | K24: 3000 | L24: 3000 | S24: =SUM(tabla1[[#this row],[cumpl profesor]:[rifa]]) -> #N/A
A25: 18 | B25: 25026561-1 | C25: MOYA SALAS COLOMBA AYLÉN | D25: NATALIE SALAS | E25: 1000 | F25: 2000 | G25: 2000 | H25: 3000 | R25: 1000 | S25: =SUM(tabla1[[#this row],[cumpl profesor]:[rifa]]) -> #N/A
A26: 19 | B26: 25012737-5 | C26: MUÑOZ BECERRA AGUSTINA ISIDORA | D26: YERI | E26: 1000 | F26: 2000 | G26: 2000 | H26: 3000 | S26: =SUM(tabla1[[#this row],[cumpl profesor]:[rifa]]) -> #N/A
A27: 20 | B27: 25276474-7 | C27: MUÑOZ NAVARRETE ANTONELLA ESTEFANÍA | D27: JANETTE NAVARRETE | G27: 2000 | H27: 3000 | I27: 3000 | J27: 3000 | S27: =SUM(tabla1[[#this row],[cumpl profesor]:[rifa]]) -> #N/A
A28: 21 | B28: 25280245-2 | C28: MUÑOZ VALENZUELA BENJAMÍN IGNACIO | D28: NATALIA VALENZUELA | E28: 1000 | G28: 2000 | H28: 3000 | I28: 3000 | J28: 3000 | K28: 3000 | S28: =SUM(tabla1[[#this row],[cumpl profesor]:[rifa]]) -> #N/A
A29: 22 | B29: 25312924-7 | C29: ORELLANA IBARRA PABLO ALFONSO | S29: =SUM(tabla1[[#this row],[cumpl profesor]:[rifa]]) -> #N/A
A30: 23 | B30: 25006274-5 | C30: OYARCE CABELLO MONSERRAT ANTONELLA | D30: MONSERRAT OLLARCE | E30: 1000 | G30: 2000 | H30: 3000 | S30: =SUM(tabla1[[#this row],[cumpl profesor]:[rifa]]) -> #N/A
A31: 24 | B31: 24758384-4 | C31: PÉREZ HIGUERAS ANTONELLA NICOLE | D31: NELLY HIGUERAS | E31: 1000 | G31: 2000 | H31: 3000 | S31: =SUM(tabla1[[#this row],[cumpl profesor]:[rifa]]) -> #N/A
A32: 25 | B32: 25042952-5 | C32: RAMÍREZ MUÑOZ ANHAI ESPERANZA | D32: ROSA LLANOS | G32: 2000 | H32: 3000 | I32: 3000 | J32: 3000 | K32: 3000 | L32: 3000 | R32: 1000 | S32: =SUM(tabla1[[#this row],[cumpl profesor]:[rifa]]) -> #N/A
A33: 26 | B33: 24911564-9 | C33: REYES RODRÍGUEZ FERNANDA CATALINA | D33: YASNA RODRIGUEZ | E33: 1000 | F33: 2000 | H33: 3000 | I33: 3000 | J33: 3000 | K33: 3000 | L33: 3000 | M33: 3000 | S33: =SUM(tabla1[[#this row],[cumpl profesor]:[rifa]]) -> #N/A
A34: 27 | B34: 25255361-0 | C34: RIVERA AVENDAÑO BERTA AMPARO | D34: BLANCA AVENDAÑO | G34: 2000 | H34: 3000 | I34: 3000 | J34: 3000 | K34: 3000 | L34: 3000 | M34: 3000 | N34: 3000 | O34: 3000 | P34: 3000 | Q34: 3000 | S34: =SUM(tabla1[[#this row],[cumpl profesor]:[rifa]]) -> #N/A
A35: 28 | B35: 24973619-8 | C35: RUBIO REYES JOSÉ ALONSO | G35: 2000 | S35: =SUM(tabla1[[#this row],[cumpl profesor]:[rifa]]) -> #N/A
A36: 29 | B36: 28939190-8 | C36: SANCHEZ ZAMBRANO MIULER DAVID | D36: YERKA ZAMBRANO | E36: 1000 | G36: 2000 | H36: 3000 | I36: 3000 | J36: 3000 | S36: =SUM(tabla1[[#this row],[cumpl profesor]:[rifa]]) -> #N/A
A37: 30 | B37: 25033740-K | C37: SOTO URZÚA COLOMBA JANÍS | D37: MABEL URZUA | E37: 1000 | F37: 2000 | G37: 2000 | H37: 3000 | I37: 3000 | J37: 3000 | K37: 3000 | L37: 3000 | S37: =SUM(tabla1[[#this row],[cumpl profesor]:[rifa]]) -> #N/A
A38: 31 | B38: 25001015-K | C38: UNZUETA GONZÁLEZ JESÚS VINKO ALEJANDRO | S38: =SUM(tabla1[[#this row],[cumpl profesor]:[rifa]]) -> #N/A
A39: 32 | C39: VALDÉS ORMAZÁBAL LAURA FRANCISCA RAYEN | E39: 1000 | F39: 2000 | G39: 2000 | H39: 3000 | I39: 3000 | J39: 3000 | K39: 3000 | S39: =SUM(tabla1[[#this row],[cumpl profesor]:[rifa]]) -> #N/A
A40: 33 | C40: VÁSQUEZ BRAVO RAÚL FELICIANO | D40: LUZMENIA BRAVO | E40: 1000 | F40: 2000 | H40: 3000 | I40: 3000 | J40: 3000 | K40: 3000 | R40: 1000 | S40: =SUM(tabla1[[#this row],[cumpl profesor]:[rifa]]) -> #N/A
A41: 34 | C41: GIANELLA FLORES | D41: JANIS OYARCE | E41: 1000 | F41: 2000 | G41: 2000 | R41: 1500 | S41: =SUM(tabla1[[#this row],[cumpl profesor]:[rifa]]) -> #N/A
A42: 35 | C42: LUEIZA BELTRAN JUAN PABLO | D42: FABIOLA BELTRAN | F42: 2000 | G42: 2000 | R42: 1000 | S42: =SUM(tabla1[[#this row],[cumpl profesor]:[rifa]]) -> #N/A
A43: 36 | C43: FARIAS EMILIA | D43: MARTA VALDIVIA | G43: 2000 | S43: =SUM(tabla1[[#this row],[cumpl profesor]:[rifa]]) -> #N/A
A44: 37 | C44: CUBILLOS MATIAS | G44: 2000 | S44: =SUM(tabla1[[#this row],[cumpl profesor]:[rifa]]) -> #N/A | T44: =SUM(tabla1[total]) -> #VALUE!
E45: =SUM(E8:E43) -> 24000 | F45: =SUM(F8:F43) -> 24000 | G45: =SUBTOTAL(109,tabla1[convivencia junio]) -> #VALUE! | H45: =SUM(H8:H43) -> 78000 | I45: =SUM(I8:I43) -> 54000 | J45: =SUM(J8:J43) -> 54000 | K45: =SUM(K8:K43) -> 42000 | L45: =SUM(L8:L43) -> 27000 | M45: =SUM(M8:M43) -> 9000 | N45: =SUM(N8:N43) -> 3000 | O45: =SUM(O8:O43) -> 3000 | ... R45: =SUM(R8:R43) -> 7500 | S45: =SUM(E45:R45) -> #VALUE!
B51: FECHA | C51: DETALLE | D51: MONTO
B52: 46225 | C52: VENTA CAFÉ (REUNION) | D52: 14500
D54: =SUM(D52:D53) -> 14500

Sheet ORIGINAL - EGRESOS TESORERO
A1: TESORERÍA 5°B - DETALLE DE EGRESOS
A2: Gastos pagados directamente por Tesorería, respaldados con boleta o comprobante.
A6: ACTIVIDAD | B6: FECHA | C6: DETALLE | D6: LOCAL COMERCIAL | E6: COMPROBANTE | F6: MONTO
B7: 46107 | C7: TORTA | D7: PANEDERIA MODELO | E7: BOLETA 5346708 | F7: 21490
B8: 46107 | C8: BEBESTIBLES | D8: JUMBO | E8: BOLETA 3341113655 | F8: 9610
B9: 46119 | C9: REGALO CUMPLEAÑOS PROFESOR | D9: FALABELLA | E9: BOLETA 944627229 | F9: 24990
B10: 46133 | C10: DECORACION LIBRO | D10: PRESIDENTA | E10: TE 8084312 | F10: 10000
B11: 46170 | C11: BEBIDAS | D11: JUMBO | E11: BOLETA 33883893415 | F11: 7670
B12: 46170 | C12: PLATOS | D12: COMERCIAL PAMY | E12: BOLETA 113895 | F12: 5540
B13: 46170 | C13: TORTA 16P | D13: PANEDERIA MODELO | E13: BOLETA 5258358 | F13: 9990
B14: 46170 | C14: TORTA 24P | D14: PANEDERIA MODELO | E14: BOLETA 5258336 | F14: 13990
B15: 46191 | C15: VIENESA ADEREZOS | D15: JUMBO | E15: 3403993582 | F15: 18550
B16: 46192 | C16: TRANSFERENCIA A PRESIDENTA PALTAS | D16: BANCOESTADO | E16: 8000745 | F16: 5000
B17: 46191 | C17: PAN COMPLETO ABONO | D17: PANADERIA MULTIMASAS SPA | E17: 3196 | F17: 2000
B18: 46192 | C18: PAN COMPLETO | D18: PANADERIA MULTIMASAS SPA | E18: 3231 | F18: 10930
B19: 46192 | C19: TOMATE BEBIDAS | D19: ROSA VILLACURA | E19: 53017 | F19: 13040
A20: REUNION | B20: 46225 | C20: CUCHARAS | D20: COMERCIAL PAMY | E20: BOLETA 117765 | F20: 1100
A21: CUMPLEAÑOS | B21: 46233 | C21: TORTA MANJAR CHOCOLATE 32 P | D21: PANADERIA MODELO | E21: BOLETA 5285166 | F21: 25490
A22: DIA DEL NIÑO | B22: 46240 | C22: POTES HELADOS - PAPEL CELOFAN | D22: COMERCIAL PAMY | E22: BOLETA 118864 | F22: 17330
A23: DIA DEL NIÑO | B23: 46209 | C23: DIFERENCIA POTES (VASOS) | D23: COMERCIAL PAMY | E23: BOLETA 118920 | F23: 4250
A24: Total | F24: =SUBTOTAL(109,tabla3[monto]) -> #VALUE!

Sheet ORIGINAL - CAJA PRESIDENTA
C1: INGRESOS | D1: =H43+tabla133[[#totals],[monto]] -> #N/A | F1: CAJA DE LA PRESIDENTA
C2: EGRESOS | D2: =tabla156[[#totals],[monto]] -> #N/A | F2: Dinero recibido directamente por la Presidenta (cuotas, rifa, convivencia, transferencias) y gastos que ella ha rendido con boleta.
C3: SALDO PENDIENTE DE REINTEGRO | D3: =D1-D2 -> #N/A
C4: ESTADO | D4: Este monto corresponde a dinero que la Presidenta ha recibido a nombre del curso y que, a la fecha, aún no ha reintegrado a Tesorería.
B5: RUT | C5: NOMBRE | D5: CUMPL PROFESOR | E5: DIA ALUMNO | F5: MARZO | G5: RIFA | H5: TOTAL
A6: 1 | B6: 25310795-2 | C6: ARAYA PINO RENATA ANTONELA | E6: 2000 | H6: =SUM(tabla17[[#this row],[cumpl profesor]:[rifa]]) -> #N/A
A7: 2 | B7: 25299343-6 | C7: ASTUDILLO PINO TABATA JESÚS | H7: =SUM(tabla17[[#this row],[cumpl profesor]:[rifa]]) -> #N/A
A8: 3 | B8: 25172569-1 | C8: AZAGRA ABRIGO AMARO ALONSO | H8: =SUM(tabla17[[#this row],[cumpl profesor]:[rifa]]) -> #N/A
A9: 4 | B9: 25074761-6 | C9: BECERRA CARRASCO AGUSTIN SALVADOR THOMAS | H9: =SUM(tabla17[[#this row],[cumpl profesor]:[rifa]]) -> #N/A
C10: BERTEL MONTES GLEYMIS | F10: 3000 | H10: =SUM(tabla17[[#this row],[cumpl profesor]:[rifa]]) -> #N/A
A11: 6 | B11: 25186502-7 | C11: CASTILLO DÍAZ NAHUEL ANDRÉS | H11: =SUM(tabla17[[#this row],[cumpl profesor]:[rifa]]) -> #N/A
A12: 7 | B12: 24387554-4 | C12: CASTILLO GRACIA JOSEFA ANTONIA | H12: =SUM(tabla17[[#this row],[cumpl profesor]:[rifa]]) -> #N/A
A13: 8 | B13: 25117099-1 | C13: CASTRO VALDERRAMA EIMY PASCALLE | E13: 2000 | H13: =SUM(tabla17[[#this row],[cumpl profesor]:[rifa]]) -> #N/A
A14: 9 | B14: 25091106-8 | C14: DONOSO MONSALVE ANGEL ISAAC | E14: 2000 | H14: =SUM(tabla17[[#this row],[cumpl profesor]:[rifa]]) -> #N/A
A15: 10 | B15: 25091116-5 | C15: DONOSO MONSALVE THOMAS IGNACIO | E15: 2000 | H15: =SUM(tabla17[[#this row],[cumpl profesor]:[rifa]]) -> #N/A
A16: 11 | B16: 24953133-2 | C16: DONOSO ZAMORA SOFÍA ELENA | H16: =SUM(tabla17[[#this row],[cumpl profesor]:[rifa]]) -> #N/A
A17: 12 | B17: 24751135-0 | C17: INOSTROZA MOLINA MATÍAS ALONSO | H17: =SUM(tabla17[[#this row],[cumpl profesor]:[rifa]]) -> #N/A
A18: 13 | B18: 25049508-0 | C18: ITURRIETA HERNÁNDEZ MAXIMILIANO ALEJANDRO | E18: 2000 | H18: =SUM(tabla17[[#this row],[cumpl profesor]:[rifa]]) -> #N/A
A19: 14 | B19: 25049482-3 | C19: ITURRIETA HERNÁNDEZ VICENTE IGNACIO | E19: 2000 | H19: =SUM(tabla17[[#this row],[cumpl profesor]:[rifa]]) -> #N/A
A20: 15 | B20: 25067494-5 | C20: JATIB DÍAZ ABDOLASIS MAXIMILIANO | E20: 2000 | H20: =SUM(tabla17[[#this row],[cumpl profesor]:[rifa]]) -> #N/A
A21: 16 | B21: 25015009-1 | C21: MENESES YÁÑEZ ALEXANDRA MODESTA | D21: 1000 | E21: 2000 | H21: =SUM(tabla17[[#this row],[cumpl profesor]:[rifa]]) -> #N/A
A22: 17 | B22: 25179616-5 | C22: MICHEA ALIAGA JOAQUÍN ELÍAS | D22: 1000 | E22: 2000 | H22: =SUM(tabla17[[#this row],[cumpl profesor]:[rifa]]) -> #N/A
A23: 18 | B23: 25026561-1 | C23: MOYA SALAS COLOMBA AYLÉN | H23: =SUM(tabla17[[#this row],[cumpl profesor]:[rifa]]) -> #N/A
A24: 19 | B24: 25012737-5 | C24: MUÑOZ BECERRA AGUSTINA ISIDORA | H24: =SUM(tabla17[[#this row],[cumpl profesor]:[rifa]]) -> #N/A
A25: 20 | B25: 25276474-7 | C25: MUÑOZ NAVARRETE ANTONELLA ESTEFANÍA | D25: 1000 | E25: 2000 | H25: =SUM(tabla17[[#this row],[cumpl profesor]:[rifa]]) -> #N/A
A26: 21 | B26: 25280245-2 | C26: MUÑOZ VALENZUELA BENJAMÍN IGNACIO | E26: 2000 | H26: =SUM(tabla17[[#this row],[cumpl profesor]:[rifa]]) -> #N/A
A27: 22 | B27: 25312924-7 | C27: ORELLANA IBARRA PABLO ALFONSO | H27: =SUM(tabla17[[#this row],[cumpl profesor]:[rifa]]) -> #N/A
A28: 23 | B28: 25006274-5 | C28: OYARCE CABELLO MONSERRAT ANTONELLA | E28: 2000 | G28: 1000 | H28: =SUM(tabla17[[#this row],[cumpl profesor]:[rifa]]) -> #N/A
A29: 24 | B29: 24758384-4 | C29: PÉREZ HIGUERAS ANTONELLA NICOLE | E29: 2000 | G29: 1000 | H29: =SUM(tabla17[[#this row],[cumpl profesor]:[rifa]]) -> #N/A
A30: 25 | B30: 25042952-5 | C30: RAMÍREZ MUÑOZ ANHAI ESPERANZA | D30: 1000 | E30: 2000 | H30: =SUM(tabla17[[#this row],[cumpl profesor]:[rifa]]) -> #N/A
A31: 26 | B31: 24911564-9 | C31: REYES RODRÍGUEZ FERNANDA CATALINA | H31: =SUM(tabla17[[#this row],[cumpl profesor]:[rifa]]) -> #N/A
A32: 27 | B32: 25255361-0 | C32: RIVERA AVENDAÑO BERTA AMPARO | D32: 1000 | E32: 2000 | H32: =SUM(tabla17[[#this row],[cumpl profesor]:[rifa]]) -> #N/A
A33: 28 | B33: 24973619-8 | C33: RUBIO REYES JOSÉ ALONSO | D33: 1000 | E33: 2000 | H33: =SUM(tabla17[[#this row],[cumpl profesor]:[rifa]]) -> #N/A
A34: 29 | B34: 28939190-8 | C34: SANCHEZ ZAMBRANO MIULER DAVID | E34: 2000 | H34: =SUM(tabla17[[#this row],[cumpl profesor]:[rifa]]) -> #N/A
A35: 30 | B35: 25033740-K | C35: SOTO URZÚA COLOMBA JANÍS | H35: =SUM(tabla17[[#this row],[cumpl profesor]:[rifa]]) -> #N/A
A36: 31 | B36: 25001015-K | C36: UNZUETA GONZÁLEZ JESÚS VINKO ALEJANDRO | H36: =SUM(tabla17[[#this row],[cumpl profesor]:[rifa]]) -> #N/A
A37: 32 | C37: VALDÉS ORMAZÁBAL LAURA FRANCISCA RAYEN | H37: =SUM(tabla17[[#this row],[cumpl profesor]:[rifa]]) -> #N/A
A38: 33 | C38: VÁSQUEZ BRAVO RAÚL FELICIANO | H38: =SUM(tabla17[[#this row],[cumpl profesor]:[rifa]]) -> #N/A
A39: 34 | C39: GIANELA FLORES | H39: =SUM(tabla17[[#this row],[cumpl profesor]:[rifa]]) -> #N/A
A40: 35 | C40: LUEIZA BELTRAN JUAN PABLO | H40: =SUM(tabla17[[#this row],[cumpl profesor]:[rifa]]) -> #N/A
A41: 36 | C41: FARIAS EMILIA | H41: =SUM(tabla17[[#this row],[cumpl profesor]:[rifa]]) -> #N/A
A42: 37 | C42: CUBILLOS MATIAS | H42: =SUM(tabla17[[#this row],[cumpl profesor]:[rifa]]) -> #N/A | I42: =SUM(tabla17[total]) -> #VALUE!
D43: =SUM(D6:D41) -> 6000 | E43: =SUM(E6:E41) -> 34000 | F43: =SUM(F6:F41) -> 3000 | G43: =SUM(G6:G41) -> 2000 | H43: =SUM(D43:G43) -> 45000
B47: OTROS INGRESOS | E47: GASTOS
B48: DETALLE | C48: MONTO | E48: FECHA | F48: DETALLE | G48: TIENDA | H48: COMPROBANTE | I48: MONTO
B49: RIFA | C49: 15000 | E49: 46107 | F49: VASOS SERVILLETAS BOLSA | G49: COMERCIAL PAMY | H49: BOLETA 108804 | I49: 6920
B50: CONVIVENCIA | C50: 36000 | E50: 46147 | F50: BOLSAS Y DULCES DEC LIBRO | G50: NEW YORK | H50: BOLETA 1958809 | I50: 36810
B51: TRANSFERENCIA | C51: 10000 | E51: 46147 | F51: RESALTADORES, PAN JAMON | G51: JUMBO | H51: BOLETA 3370616301 | I51: 30962
B52: Total | C52: =SUBTOTAL(109,tabla133[monto]) -> #VALUE! | E52: Total | I52: =SUBTOTAL(109,tabla156[monto]) -> #VALUE!

Sheet LISTAS
A1: TIPOS DE ORGANIZACIÓN | B1: TIPOS DE CUENTA | C1: MEDIOS | D1: TIPOS MOVIMIENTO | E1: TIPOS APORTE | F1: ESTADOS | G1: CATEGORÍAS
A2: Curso | B2: Cuenta RUT | C2: Efectivo | D2: Aporte | E2: Anual | F2: Registrado | G2: Alimentación
A3: Colegio | B3: Cuenta corriente | C3: Transferencia | D3: Ingreso | E3: Extraordinaria | F3: Pendiente | G3: Materiales
A4: Centro de Padres/Apoderados | B4: Cuenta vista | C4: Depósito | D4: Egreso | F4: Anulado | G4: Actividad
A5: Club deportivo | B5: Cuenta de ahorro | C5: Tarjeta | D5: Traspaso | F5: Pagado | G5: Transporte
A6: Junta de vecinos | B6: Otra | C6: Cheque | G6: Reembolso
A7: Agrupación | C7: Otro digital | G7: Servicio
A8: Fundación | G8: Compra
A9: Taller | G9: Convivencia
A10: Comité | G10: Cumpleaños
A11: Organización comunitaria | G11: Día del alumno / niño
A12: Otro | G12: Otro

Sheet PERSONAS
A1: PERSONAS — INTEGRANTES, TUTORES, RESPONSABLES Y BENEFICIARIOS
A2: Seleccione roles y datos bancarios. La suite reutiliza estos datos para evitar escribirlos nuevamente.
A4: ID | B4: N° | C4: RUT | D4: NOMBRE | E4: TELÉFONO | F4: CORREO | G4: TUTOR / RESPONSABLE | H4: ROLES | I4: BANCO | J4: TIPO CUENTA | K4: N° CUENTA | L4: TITULAR CUENTA | M4: RUT TITULAR | N4: CORREO TRANSFERENCIA | O4: OBSERVACIONES
A5: P001 | B5: 1 | C5: 25310795-2 | D5: ARAYA PINO RENATA ANTONELA | E5: +569 | G5: PATRICIA PINO | H5: Integrante
A6: P002 | B6: 2 | C6: 25299343-6 | D6: ASTUDILLO PINO TABATA JESÚS | E6: +569 | G6: ROXANA PINO | H6: Integrante
A7: P003 | B7: 3 | C7: 25172569-1 | D7: AZAGRA ABRIGO AMARO ALONSO | E7: +569 | G7: BEATRIZ ABRIGO | H7: Integrante
A8: P004 | B8: 4 | C8: 25074761-6 | D8: BECERRA CARRASCO AGUSTIN SALVADOR THOMAS | E8: +569 | G8: ALICIA ARAYA | H8: Integrante
A9: P005 | D9: BERTEL MONTES GLEYMIS | E9: +569 | H9: Integrante
A10: P006 | B10: 6 | C10: 25186502-7 | D10: CASTILLO DÍAZ NAHUEL ANDRÉS | E10: +569 | H10: Integrante
A11: P007 | B11: 7 | C11: 24387554-4 | D11: CASTILLO GRACIA JOSEFA ANTONIA | E11: +569 | H11: Integrante
A12: P008 | B12: 8 | C12: 25117099-1 | D12: CASTRO VALDERRAMA EIMY PASCALLE | E12: +569 | G12: ANA VALDERRAMA | H12: Integrante
A13: P009 | B13: 9 | C13: 25091106-8 | D13: DONOSO MONSALVE ANGEL ISAAC | E13: +569 | H13: Integrante
A14: P010 | B14: 10 | C14: 25091116-5 | D14: DONOSO MONSALVE THOMAS IGNACIO | E14: +569 | H14: Integrante
A15: P011 | B15: 11 | C15: 24953133-2 | D15: DONOSO ZAMORA SOFÍA ELENA | E15: +569 | G15: JENNY ZAMORA | H15: Integrante
A16: P012 | B16: 12 | C16: 24751135-0 | D16: INOSTROZA MOLINA MATÍAS ALONSO | E16: +569 | G16: OLGA MOLINA | H16: Integrante
A17: P013 | B17: 13 | C17: 25049508-0 | D17: ITURRIETA HERNÁNDEZ MAXIMILIANO ALEJANDRO | E17: +569 | G17: VALERIA HERNANDEZ | H17: Integrante
A18: P014 | B18: 14 | C18: 25049482-3 | D18: ITURRIETA HERNÁNDEZ VICENTE IGNACIO | E18: +569 | G18: VALERIA HERNANDEZ | H18: Integrante
A19: P015 | B19: 15 | C19: 25067494-5 | D19: JATIB DÍAZ ABDOLASIS MAXIMILIANO | E19: +569 | G19: MARISOL DIAZ | H19: Integrante
A20: P016 | B20: 16 | C20: 25015009-1 | D20: MENESES YÁÑEZ ALEXANDRA MODESTA | E20: +569 | H20: Integrante
A21: P017 | B21: 17 | C21: 25179616-5 | D21: MICHEA ALIAGA JOAQUÍN ELÍAS | E21: +569 | G21: STEFANY ALIAGA | H21: Integrante
A22: P018 | B22: 18 | C22: 25026561-1 | D22: MOYA SALAS COLOMBA AYLÉN | E22: +569 | G22: NATALIE SALAS | H22: Integrante
A23: P019 | B23: 19 | C23: 25012737-5 | D23: MUÑOZ BECERRA AGUSTINA ISIDORA | E23: +569 | G23: YERI | H23: Integrante
A24: P020 | B24: 20 | C24: 25276474-7 | D24: MUÑOZ NAVARRETE ANTONELLA ESTEFANÍA | E24: +569 | G24: JANETTE NAVARRETE | H24: Integrante
A25: P021 | B25: 21 | C25: 25280245-2 | D25: MUÑOZ VALENZUELA BENJAMÍN IGNACIO | E25: +569 | G25: NATALIA VALENZUELA | H25: Integrante
A26: P022 | B26: 22 | C26: 25312924-7 | D26: ORELLANA IBARRA PABLO ALFONSO | E26: +569 | H26: Integrante
A27: P023 | B27: 23 | C27: 25006274-5 | D27: OYARCE CABELLO MONSERRAT ANTONELLA | E27: +569 | G27: MONSERRAT OLLARCE | H27: Integrante
A28: P024 | B28: 24 | C28: 24758384-4 | D28: PÉREZ HIGUERAS ANTONELLA NICOLE | E28: +569 | G28: NELLY HIGUERAS | H28: Integrante
A29: P025 | B29: 25 | C29: 25042952-5 | D29: RAMÍREZ MUÑOZ ANHAI ESPERANZA | E29: +569 | G29: ROSA LLANOS | H29: Integrante
A30: P026 | B30: 26 | C30: 24911564-9 | D30: REYES RODRÍGUEZ FERNANDA CATALINA | E30: +569 | G30: YASNA RODRIGUEZ | H30: Integrante
A31: P027 | B31: 27 | C31: 25255361-0 | D31: RIVERA AVENDAÑO BERTA AMPARO | E31: +569 | G31: BLANCA AVENDAÑO | H31: Integrante
A32: P028 | B32: 28 | C32: 24973619-8 | D32: RUBIO REYES JOSÉ ALONSO | E32: +569 | H32: Integrante
A33: P029 | B33: 29 | C33: 28939190-8 | D33: SANCHEZ ZAMBRANO MIULER DAVID | E33: +569 | G33: YERKA ZAMBRANO | H33: Integrante
A34: P030 | B34: 30 | C34: 25033740-K | D34: SOTO URZÚA COLOMBA JANÍS | E34: +569 | G34: MABEL URZUA | H34: Integrante
A35: P031 | B35: 31 | C35: 25001015-K | D35: UNZUETA GONZÁLEZ JESÚS VINKO ALEJANDRO | E35: +569 | H35: Integrante
A36: P032 | B36: 32 | D36: VALDÉS ORMAZÁBAL LAURA FRANCISCA RAYEN | E36: +569 | H36: Integrante
A37: P033 | B37: 33 | D37: VÁSQUEZ BRAVO RAÚL FELICIANO | E37: +569 | G37: LUZMENIA BRAVO | H37: Integrante
A38: P034 | B38: 34 | D38: GIANELA FLORES | E38: +569 | G38: JANIS OYARCE | H38: Integrante
A39: P035 | B39: 35 | D39: LUEIZA BELTRAN JUAN PABLO | E39: +569 | G39: FABIOLA BELTRAN | H39: Integrante
A40: P036 | B40: 36 | D40: FARIAS EMILIA | E40: +569 | G40: MARTA VALDIVIA | H40: Integrante
A41: P037 | B41: 37 | D41: CUBILLOS MATIAS | E41: +569 | H41: Integrante
E42: +569
E43: +569
E44: +569
E45: +569
E46: +569
E47: +569
E48: +569
E49: +569
E50: +569
E51: +569
E52: +569
E53: +569
... E104: +569

Sheet MOVIMIENTOS
A1: PLANILLA MAESTRA DE MOVIMIENTOS — FORMATO HORIZONTAL
A2: Esta es la base de datos operativa. Todo lo que se registre aquí alimenta la Planilla General y los informes.
A4: ID | B4: FECHA | C4: ORGANIZACIÓN | D4: TIPO | E4: TIPO APORTE | F4: CONCEPTO / CATEGORÍA | G4: FONDO | H4: MEDIO | I4: MONTO | J4: PERSONA / BENEFICIARIO | K4: RUT | L4: TUTOR / RESPONSABLE | M4: RESPONSABLE | N4: AUTORIZA | O4: RESPONSABLE DEL GASTO | P4: BANCO | Q4: TIPO CUENTA | R4: N° CUENTA | S4: TITULAR CUENTA | T4: COMPROBANTE | U4: RESPALDO | V4: ESTADO | W4: OBSERVACIONES
A5: M0001 | B5: 46091 | C5: CPA 5°B 2026 | D5: Aporte | E5: Anual | F5: MARZO | G5: Tesorería | H5: Efectivo | I5: 3000 | J5: ARAYA PINO RENATA ANTONELA | K5: 25310795-2 | L5: PATRICIA PINO | U5: Carga masiva desde Excel | V5: Registrado | W5: Carga masiva; fecha referencial.
A6: M0002 | B6: 46122 | C6: CPA 5°B 2026 | D6: Aporte | E6: Anual | F6: ABRIL | G6: Tesorería | H6: Efectivo | I6: 3000 | J6: ARAYA PINO RENATA ANTONELA | K6: 25310795-2 | L6: PATRICIA PINO | U6: Carga masiva desde Excel | V6: Registrado | W6: Carga masiva; fecha referencial.
A7: M0003 | B7: 46152 | C7: CPA 5°B 2026 | D7: Aporte | E7: Anual | F7: MAYO | G7: Tesorería | H7: Efectivo | I7: 3000 | J7: ARAYA PINO RENATA ANTONELA | K7: 25310795-2 | L7: PATRICIA PINO | U7: Carga masiva desde Excel | V7: Registrado | W7: Carga masiva; fecha referencial.
A8: M0004 | B8: 46192 | C8: CPA 5°B 2026 | D8: Aporte | E8: Anual | F8: JUNIO | G8: Tesorería | H8: Efectivo | I8: 3000 | J8: ARAYA PINO RENATA ANTONELA | K8: 25310795-2 | L8: PATRICIA PINO | U8: Carga masiva desde Excel | V8: Registrado | W8: Carga masiva; fecha referencial.
A9: M0005 | B9: 46213 | C9: CPA 5°B 2026 | D9: Aporte | E9: Anual | F9: JULIO | G9: Tesorería | H9: Efectivo | I9: 3000 | J9: ARAYA PINO RENATA ANTONELA | K9: 25310795-2 | L9: PATRICIA PINO | U9: Carga masiva desde Excel | V9: Registrado | W9: Carga masiva; fecha referencial.
A10: M0006 | B10: 46178.417 | C10: CPA 5°B 2026 | D10: Aporte | E10: Extraordinaria | F10: CUMPL PROFESOR | G10: Tesorería | H10: Efectivo | I10: 1000 | J10: ARAYA PINO RENATA ANTONELA | K10: 25310795-2 | L10: PATRICIA PINO | U10: Carga masiva desde Excel | V10: Registrado | W10: Carga masiva; fecha referencial.
A11: M0007 | B11: 46178.417 | C11: CPA 5°B 2026 | D11: Aporte | E11: Extraordinaria | F11: DÍA ALUMNO / NIÑO | G11: Presidenta | H11: Efectivo | I11: 2000 | J11: ARAYA PINO RENATA ANTONELA | K11: 25310795-2 | L11: PATRICIA PINO | U11: Carga masiva desde Excel | V11: Registrado | W11: Carga masiva; fecha referencial.
A12: M0008 | B12: 46091 | C12: CPA 5°B 2026 | D12: Aporte | E12: Anual | F12: MARZO | G12: Tesorería | H12: Efectivo | I12: 3000 | J12: ASTUDILLO PINO TABATA JESÚS | K12: 25299343-6 | L12: ROXANA PINO | U12: Carga masiva desde Excel | V12: Registrado | W12: Carga masiva; fecha referencial.
A13: M0009 | B13: 46178.417 | C13: CPA 5°B 2026 | D13: Aporte | E13: Extraordinaria | F13: CUMPL PROFESOR | G13: Tesorería | H13: Efectivo | I13: 1000 | J13: ASTUDILLO PINO TABATA JESÚS | K13: 25299343-6 | L13: ROXANA PINO | U13: Carga masiva desde Excel | V13: Registrado | W13: Carga masiva; fecha referencial.
A14: M0010 | B14: 46192.417 | C14: CPA 5°B 2026 | D14: Aporte | E14: Extraordinaria | F14: CONVIVENCIA JUNIO | G14: Tesorería | H14: Efectivo | I14: 2000 | J14: ASTUDILLO PINO TABATA JESÚS | K14: 25299343-6 | L14: ROXANA PINO | U14: Carga masiva desde Excel | V14: Registrado | W14: Carga masiva; fecha referencial.
A15: M0011 | B15: 46178.417 | C15: CPA 5°B 2026 | D15: Aporte | E15: Extraordinaria | F15: CUMPL PROFESOR | G15: Tesorería | H15: Efectivo | I15: 1000 | J15: AZAGRA ABRIGO AMARO ALONSO | K15: 25172569-1 | L15: BEATRIZ ABRIGO | U15: Carga masiva desde Excel | V15: Registrado | W15: Carga masiva; fecha referencial.
A16: M0012 | B16: 46178.417 | C16: CPA 5°B 2026 | D16: Aporte | E16: Extraordinaria | F16: DÍA ALUMNO / NIÑO | G16: Tesorería | H16: Efectivo | I16: 2000 | J16: AZAGRA ABRIGO AMARO ALONSO | K16: 25172569-1 | L16: BEATRIZ ABRIGO | U16: Carga masiva desde Excel | V16: Registrado | W16: Carga masiva; fecha referencial.
... A24: M0020 | B24: 46192.417 | C24: CPA 5°B 2026 | D24: Aporte | E24: Extraordinaria | F24: CONVIVENCIA JUNIO | G24: Tesorería | H24: Efectivo | I24: 2000 | J24: BECERRA CARRASCO AGUSTIN SALVADOR THOMAS | K24: 25074761-6 | L24: ALICIA ARAYA | U24: Carga masiva desde Excel | V24: Registrado | W24: Carga masiva; fecha referencial.
A25: M0021 | B25: 46091 | C25: CPA 5°B 2026 | D25: Aporte | E25: Anual | F25: MARZO | G25: Presidenta | H25: Efectivo | I25: 3000 | J25: BERTEL MONTES GLEYMIS | U25: Carga masiva desde Excel | V25: Registrado | W25: Carga masiva; fecha referencial.
A26: M0022 | B26: 46091 | C26: CPA 5°B 2026 | D26: Aporte | E26: Anual | F26: MARZO | G26: Tesorería | H26: Efectivo | I26: 3000 | J26: CASTILLO GRACIA JOSEFA ANTONIA | K26: 24387554-4 | U26: Carga masiva desde Excel | V26: Registrado | W26: Carga masiva; fecha referencial.
A27: M0023 | B27: 46122 | C27: CPA 5°B 2026 | D27: Aporte | E27: Anual | F27: ABRIL | G27: Tesorería | H27: Efectivo | I27: 3000 | J27: CASTILLO GRACIA JOSEFA ANTONIA | K27: 24387554-4 | U27: Carga masiva desde Excel | V27: Registrado | W27: Carga masiva; fecha referencial.
A28: M0024 | B28: 46152 | C28: CPA 5°B 2026 | D28: Aporte | E28: Anual | F28: MAYO | G28: Tesorería | H28: Efectivo | I28: 3000 | J28: CASTILLO GRACIA JOSEFA ANTONIA | K28: 24387554-4 | U28: Carga masiva desde Excel | V28: Registrado | W28: Carga masiva; fecha referencial.
A29: M0025 | B29: 46178.417 | C29: CPA 5°B 2026 | D29: Aporte | E29: Extraordinaria | F29: CUMPL PROFESOR | G29: Tesorería | H29: Efectivo | I29: 1000 | J29: CASTILLO GRACIA JOSEFA ANTONIA | K29: 24387554-4 | U29: Carga masiva desde Excel | V29: Registrado | W29: Carga masiva; fecha referencial.
A30: M0026 | B30: 46192.417 | C30: CPA 5°B 2026 | D30: Aporte | E30: Extraordinaria | F30: CONVIVENCIA JUNIO | G30: Tesorería | H30: Efectivo | I30: 2000 | J30: CASTILLO GRACIA JOSEFA ANTONIA | K30: 24387554-4 | U30: Carga masiva desde Excel | V30: Registrado | W30: Carga masiva; fecha referencial.
A31: M0027 | B31: 46091 | C31: CPA 5°B 2026 | D31: Aporte | E31: Anual | F31: MARZO | G31: Tesorería | H31: Efectivo | I31: 3000 | J31: CASTRO VALDERRAMA EIMY PASCALLE | K31: 25117099-1 | L31: ANA VALDERRAMA | U31: Carga masiva desde Excel | V31: Registrado | W31: Carga masiva; fecha referencial.
A32: M0028 | B32: 46122 | C32: CPA 5°B 2026 | D32: Aporte | E32: Anual | F32: ABRIL | G32: Tesorería | H32: Efectivo | I32: 3000 | J32: CASTRO VALDERRAMA EIMY PASCALLE | K32: 25117099-1 | L32: ANA VALDERRAMA | U32: Carga masiva desde Excel | V32: Registrado | W32: Carga masiva; fecha referencial.
A33: M0029 | B33: 46152 | C33: CPA 5°B 2026 | D33: Aporte | E33: Anual | F33: MAYO | G33: Tesorería | H33: Efectivo | I33: 3000 | J33: CASTRO VALDERRAMA EIMY PASCALLE | K33: 25117099-1 | L33: ANA VALDERRAMA | U33: Carga masiva desde Excel | V33: Registrado | W33: Carga masiva; fecha referencial.
A34: M0030 | B34: 46192 | C34: CPA 5°B 2026 | D34: Aporte | E34: Anual | F34: JUNIO | G34: Tesorería | H34: Efectivo | I34: 3000 | J34: CASTRO VALDERRAMA EIMY PASCALLE | K34: 25117099-1 | L34: ANA VALDERRAMA | U34: Carga masiva desde Excel | V34: Registrado | W34: Carga masiva; fecha referencial.
A35: M0031 | B35: 46213 | C35: CPA 5°B 2026 | D35: Aporte | E35: Anual | F35: JULIO | G35: Tesorería | H35: Efectivo | I35: 3000 | J35: CASTRO VALDERRAMA EIMY PASCALLE | K35: 25117099-1 | L35: ANA VALDERRAMA | U35: Carga masiva desde Excel | V35: Registrado | W35: Carga masiva; fecha referencial.
A36: M0032 | B36: 46178.417 | C36: CPA 5°B 2026 | D36: Aporte | E36: Extraordinaria | F36: CUMPL PROFESOR | G36: Tesorería | H36: Efectivo | I36: 1000 | J36: CASTRO VALDERRAMA EIMY PASCALLE | K36: 25117099-1 | L36: ANA VALDERRAMA | U36: Carga masiva desde Excel | V36: Registrado | W36: Carga masiva; fecha referencial.
A37: M0033 | B37: 46178.417 | C37: CPA 5°B 2026 | D37: Aporte | E37: Extraordinaria | F37: DÍA ALUMNO / NIÑO | G37: Presidenta | H37: Efectivo | I37: 2000 | J37: CASTRO VALDERRAMA EIMY PASCALLE | K37: 25117099-1 | L37: ANA VALDERRAMA | U37: Carga masiva desde Excel | V37: Registrado | W37: Carga masiva; fecha referencial.
A38: M0034 | B38: 46192.417 | C38: CPA 5°B 2026 | D38: Aporte | E38: Extraordinaria | F38: CONVIVENCIA JUNIO | G38: Tesorería | H38: Efectivo | I38: 2000 | J38: CASTRO VALDERRAMA EIMY PASCALLE | K38: 25117099-1 | L38: ANA VALDERRAMA | U38: Carga masiva desde Excel | V38: Registrado | W38: Carga masiva; fecha referencial.
